Workbook
Name Slicer_Order_Date: #N/A
Name Slicer_Product_Category: #N/A
Name Slicer_Region: #N/A

Sheet Sales_Performance_Analysis.csv
A1: Order ID | B1: Order Date | C1: Region | D1: Product Category | E1: Sales Amount | F1: Quantity Sold | G1: Discount (%) | H1: Profit
A2: ab899d2f | B2: 45022 | C2: norTh | D2: groceries | E2: 859.29 | F2: 44 | G2: 37 | H2: 1653.87
A3: 73484eb1 | B3: 45412 | C3: Mes$t | D3: groceries | E3: 1546.81 | F3: 23 | G3: 33 | H3: 1932.71
A4: 19395924 | B4: 45363 | C4: eAsT | D4: groceries | E4: 4703.58 | F4: 31 | G4: 15 | H4: 527.47
A5: b3fded3d | B5: 45331 | C5: eAsT | D5: groceries | E5: 3377.17 | F5: 47 | G5: 3 | H5: 482.65
A6: 6e4bdd51 | B6: 45502 | C6: $0uTH | D6: Cloth ing | E6: 3517.49 | F6: 6 | G6: 28 | H6: 748.72
A7: 21d88d69 | B7: 45164 | C7: eAsT | D7: FURNiture | E7: 362.55 | F7: 19 | G7: 50 | H7: 314.71
A8: 9da2704d | B8: 45572 | C8: eAsT | D8: sports | E8: 4811.17 | F8: 22 | G8: 18 | H8: 1372.89
A9: a1bd6815 | B9: 45000 | C9: Mes$t | D9: electronicS | E9: 3565.2 | F9: 22 | G9: 16 | H9: 1437.3
A10: 0bbd51fc | B10: 45106 | C10: eAsT | D10: Cloth ing | E10: 3805.25 | F10: 19 | G10: 3 | H10: 1537.28
A11: 8bf7e4b3 | B11: 44998 | C11: $0uTH | D11: Cloth ing | E11: 2178.72 | F11: 15 | G11: 24 | H11: 1696.65
A12: e6cf1255 | B12: 45439 | C12: Mes$t | D12: groceries | E12: 2844.93 | F12: 34 | G12: 12 | H12: 1166.39
A13: 3ba1fc5c | B13: 45291 | C13: Mes$t | D13: electronicS | E13: 3600.04 | F13: 10 | G13: 2 | H13: 1632.75
A14: 388ff70d | B14: 45239 | C14: eAsT | D14: $port$ | E14: 941.88 | F14: 13 | G14: 28 | H14: 646.49
A15: ce2e9002 | B15: 44919 | C15: $0uTH | D15: $port$ | E15: 3300.86 | F15: 1 | G15: 48 | H15: 86.9
A16: a4f9a338 | B16: 45329 | C16: eAsT | D16: groceries | E16: 1081.62 | F16: 4 | G16: 19 | H16: 611.06
... A19: 35358e9c | B19: 45471 | C19: norTh | D19: Cloth ing | E19: 2784.79 | F19: 35 | G19: 40 | H19: 999.6
A20: 31676338 | B20: 45246 | C20: $0uTH | D20: Cloth ing | E20: 1082.98 | F20: 8 | G20: 11 | H20: 1604.19
A21: 05d72e20 | B21: 45556 | C21: eAsT | D21: Cloth ing | E21: 787.79 | F21: 47 | G21: 18 | H21: 1313.33
A22: 68dbe328 | B22: 45566 | C22: $0uTH | D22: FURNiture | E22: 312.7 | F22: 36 | G22: 43 | H22: 559.52
A23: 78d3f47b | B23: 45077 | C23: eAsT | D23: $port$ | E23: 265.32 | F23: 21 | G23: 36 | H23: 595.91
A24: 9e4d1fe0 | B24: 45400 | C24: Mes$t | D24: FURNiture | E24: 1253.64 | F24: 35 | G24: 14 | H24: 1653.66
A25: 9215a70e | B25: 45341 | C25: Mes$t | D25: Cloth ing | E25: 1874.07 | F25: 28 | G25: 23 | H25: 1783.26
A26: 54ca3433 | B26: 45041 | C26: eAsT | D26: Cloth ing | E26: 2561.71 | F26: 44 | G26: 10 | H26: 800.82
A27: 0ba75cc7 | B27: 45059 | C27: Mes$t | D27: $port$ | E27: 1960.74 | F27: 50 | G27: 6 | H27: 1530.61
A28: 601860b1 | B28: 45037 | C28: eAsT | D28: electronicS | E28: 2415.44 | F28: 35 | G28: 14 | H28: 335.57
A29: e393e106 | B29: 45290 | C29: eAsT | D29: electronicS | E29: 2284.22 | F29: 8 | G29: 41 | H29: 1866.59
A30: 7ab3d472 | B30: 44885 | C30: Mes$t | D30: $port$ | E30: 2118.55 | F30: 29 | G30: 24 | H30: 702.15
A31: 01d9b1ae | B31: 45248 | C31: $0uTH | D31: groceries | E31: 4803.6 | F31: 11 | G31: 12 | H31: 1086.74
A32: 20385cb6 | B32: 45533 | C32: norTh | D32: groceries | E32: 4297 | F32: 17 | G32: 49 | H32: 678.7
... A69: 92458ed3 | B69: 45024 | C69: norTh | D69: FURNiture | E69: 1356.62 | F69: 2 | G69: 21 | H69: 1213.34
A70: 76740552 | B70: 45201 | C70: $0uTH | D70: electronicS | E70: 2905.8 | F70: 20 | G70: 10 | H70: 1417.43
A71: f92de80d | B71: 45060 | C71: $0uTH | D71: FURNiture | E71: 2065.42 | F71: 22 | G71: 15 | H71: 787.51
A72: 647ff51a | B72: 45094 | C72: eAsT | D72: Cloth ing | E72: 272.88 | F72: 47 | G72: 29 | H72: 1208.68
A73: f8548ec7 | B73: 45594 | C73: eAsT | D73: Cloth ing | E73: 4126.4 | F73: 34 | G73: 13 | H73: 1690.11
A74: 7855a0d2 | B74: 45195 | C74: norTh | D74: FURNiture | E74: 4204.55 | F74: 49 | G74: 1 | H74: 1534.82
A75: bf586512 | B75: 45226 | C75: Mes$t | D75: Cloth ing | E75: 2130.98 | F75: 7 | G75: 29 | H75: 679.16
A76: deea1965 | B76: 45436 | C76: $0uTH | D76: FURNiture | E76: 1253.28 | F76: 4 | G76: 48 | H76: 317.33
A77: a0a8290f | B77: 45478 | C77: $0uTH | D77: $port$ | E77: 1050.29 | F77: 30 | G77: 4 | H77: 423.5
A78: 077a9429 | B78: 45079 | C78: norTh | D78: FURNiture | E78: 1269.1 | F78: 3 | G78: 7 | H78: 1819.88
A79: 8642940000 | B79: 45192 | C79: Mes$t | D79: Groceries | E79: 4229.47 | F79: 3 | G79: 9 | H79: 11.29
A80: 41d1321a | B80: 45243 | C80: $0uTH | D80: Groceries | E80: 3767.63 | F80: 30 | G80: 41 | H80: 1031.74
A81: 44afa795 | B81: 45068 | C81: Mes$t | D81: $port$ | E81: 640.91 | F81: 19 | G81: 19 | H81: 1148.62
A82: 8c329e53 | B82: 45461 | C82: norTh | D82: FURNiture | E82: 2958 | F82: 4 | G82: 22 | H82: 1968.62
A83: cdbba08a | B83: 44948 | C83: Mes$t | D83: $port$ | E83: 4049.49 | F83: 5 | G83: 1 | H83: 1151.9
A84: 4415c908 | B84: 45385 | C84: norTh | D84: $port$ | E84: 4155.03 | F84: 32 | G84: 5 | H84: 1637.7
A85: a9ac13d3 | B85: 45556 | C85: norTh | D85: FURNiture | E85: 2011.35 | F85: 44 | G85: 10 | H85: 829.69
A86: 5fbf219e | B86: 45299 | C86: Mes$t | D86: electronicS | E86: 2365.24 | F86: 10 | G86: 33 | H86: 1970.1
A87: f3ba50cf | B87: 45321 | C87: $0uTH | D87: Cloth ing | E87: 2615.84 | F87: 31 | G87: 9 | H87: 1276.87
A88: 88840b0f | B88: 45399 | C88: Mes$t | D88: Cloth ing | E88: 4954.33 | F88: 26 | G88: 43 | H88: 1723.31
A89: 3dcffe93 | B89: 45082 | C89: norTh | D89: Cloth ing | E89: 1969.35 | F89: 27 | G89: 11 | H89: 1532.9
A90: 745eb905 | B90: 45383 | C90: norTh | D90: Cloth ing | E90: 2083.02 | F90: 49 | G90: 11 | H90: 105.26
A91: b8fca939 | B91: 45530 | C91: $0uTH | D91: electronicS | E91: 4752.49 | F91: 36 | G91: 8 | H91: 1903.35
... A150: c41efe4c | B150: 45434 | C150: $0uTH | D150: FURNiture | E150: 1453.8 | F150: 13 | G150: 16 | H150: 385.22
A151: 61831599 | B151: 44923 | C151: eAsT | D151: $port$ | E151: 4889.46 | F151: 1 | G151: 20 | H151: 807.13
A152: cf159d42 | B152: 45106 | C152: eAsT | D152: $port$ | E152: 2548.91 | F152: 3 | G152: 7 | H152: 694.24
A153: ffa6342d | B153: 45144 | C153: $0uTH | D153: Cloth ing | E153: 3804.77 | F153: 31 | G153: 47 | H153: 185.46
A154: 459360d4 | B154: 45499 | C154: eAsT | D154: Groceries | E154: 372.53 | F154: 19 | G154: 13 | H154: 232.82
A155: fdf4755a | B155: 45497 | C155: norTh | D155: electronicS | E155: 2573.55 | F155: 48 | G155: 36 | H155: 1707.54
A156: 0a7d436c | B156: 45235 | C156: Mes$t | D156: Cloth ing | E156: 1761.29 | F156: 27 | G156: 12 | H156: 492.03
A157: 3c1ab674 | B157: 44972 | C157: eAsT | D157: GrocerieS | E157: 4113.4 | F157: 32 | G157: 3 | H157: 1726.09
A158: 42b5d016 | B158: 45147 | C158: Mes$t | D158: electronicS | E158: 202.21 | F158: 6 | G158: 43 | H158: 734.47
A159: 2616d5b4 | B159: 45576 | C159: norTh | D159: $port$ | E159: 4347.15 | F159: 20 | G159: 34 | H159: 1392.45
A160: 338c4722 | B160: 45364 | C160: Mes$t | D160: Cloth ing | E160: 4992.83 | F160: 2 | G160: 28 | H160: 1468.94
A161: 6b1e9797 | B161: 45500 | C161: eAsT | D161: $port$ | E161: 1387.18 | F161: 28 | G161: 9 | H161: 381.96
A162: 6e4fab78 | B162: 45566 | C162: norTh | D162: Cloth ing | E162: 4642.87 | F162: 35 | G162: 14 | H162: 216.96
A163: 8944bc68 | B163: 45165 | C163: eAsT | D163: electronicS | E163: 4879.9 | F163: 37 | G163: 5 | H163: 1424.1
... A199: 1e18c00a | B199: 44931 | C199: norTh | D199: Cloth ing | E199: 2925.27 | F199: 24 | G199: 4 | H199: 1753.87
A200: 37431000 | B200: 45161 | C200: $0uTH | D200: GrocerieS | E200: 2454.67 | F200: 10 | G200: 28 | H200: 47.54
A201: af24551a | B201: 45040 | C201: norTh | D201: GrocerieS | E201: 4662.47 | F201: 13 | G201: 22 | H201: 735.39
A202: 6b389c40 | B202: 45113 | C202: Mes$t | D202: Cloth ing | E202: 2943.33 | F202: 45 | G202: 8 | H202: 571.04
A203: 7743bcd0 | B203: 45022 | C203: $0uTH | D203: GrocerieS | E203: 2261.46 | F203: 46 | G203: 39 | H203: 373.45
A204: 84d09672 | B204: 45180 | C204: norTh | D204: $port$ | E204: 2679.53 | F204: 36 | G204: 6 | H204: 1471
A205: bd554f96 | B205: 45011 | C205: eAsT | D205: electronicS | E205: 1290.66 | F205: 46 | G205: 8 | H205: 147.39
A206: dee8766b | B206: 45410 | C206: eAsT | D206: GrocerieS | E206: 211.31 | F206: 45 | G206: 48 | H206: 1844.45
A207: 733628ca | B207: 45310 | C207: Mes$t | D207: FURNiture | E207: 3582.85 | F207: 42 | G207: 48 | H207: 1359.36
A208: 7101a707 | B208: 45097 | C208: Mes$t | D208: FURNiture | E208: 419.94 | F208: 12 | G208: 22 | H208: 1047.8
A209: 7349ac4e | B209: 45259 | C209: eAsT | D209: $port$ | E209: 4422.18 | F209: 14 | G209: 33 | H209: 237.47
A210: fbe74fbe | B210: 44907 | C210: eAsT | D210: FURNiture | E210: 3277.47 | F210: 11 | G210: 2 | H210: 379.92
A211: 6bde908c | B211: 45524 | C211: norTh | D211: Cloth ing | E211: 4264.38 | F211: 31 | G211: 24 | H211: 1179.93
A212: 56a98641 | B212: 45016 | C212: $0uTH | D212: FURNiture | E212: 647.38 | F212: 16 | G212: 34 | H212: 1937.88
... A216: 2ecc60c1 | B216: 44934 | C216: $0uTH | D216: Cloth ing | E216: 4559.22 | F216: 14 | G216: 29 | H216: 1055.86
A217: 60839616 | B217: 45529 | C217: $0uTH | D217: $port$ | E217: 1787.05 | F217: 11 | G217: 19 | H217: 40.81
A218: a65dfe8b | B218: 45104 | C218: Mes$t | D218: FURNiture | E218: 901.68 | F218: 7 | G218: 48 | H218: 903.11
A219: 850b0c26 | B219: 45423 | C219: norTh | D219: electronicS | E219: 2934.72 | F219: 20 | G219: 12 | H219: 528.02
A220: 21fd10ea | B220: 45388 | C220: Mes$t | D220: GrocerieS | E220: 1058.57 | F220: 6 | G220: 13 | H220: 697.72
A221: 8d90e130 | B221: 44965 | C221: eAsT | D221: FURNiture | E221: 3988.42 | F221: 36 | G221: 1 | H221: 1637.88
A222: 41aee1e8 | B222: 45010 | C222: $0uTH | D222: $port$ | E222: 2727.47 | F222: 35 | G222: 1 | H222: 1875.23
A223: 2f562dc0 | B223: 45275 | C223: $0uTH | D223: GrocerieS | E223: 1765.49 | F223: 13 | G223: 24 | H223: 1951.72
A224: 1790f693 | B224: 44947 | C224: norTh | D224: FURNiture | E224: 4383.76 | F224: 40 | G224: 21 | H224: 1013.33
A225: 1ad9d5e9 | B225: 45476 | C225: $0uTH | D225: GrocerieS | E225: 4240.64 | F225: 49 | G225: 14 | H225: 1765.62
A226: ae129571 | B226: 44970 | C226: $0uTH | D226: FURNiture | E226: 273.84 | F226: 44 | G226: 29 | H226: 821
A227: 79a06bc6 | B227: 45019 | C227: eAsT | D227: $port$ | E227: 152.53 | F227: 10 | G227: 16 | H227: 1958.8
A228: 65240ae3 | B228: 45106 | C228: Mes$t | D228: GrocerieS | E228: 1407.97 | F228: 26 | G228: 35 | H228: 978.17
A229: d4df366c | B229: 45459 | C229: Mes$t | D229: FURNiture | E229: 4083.3 | F229: 22 | G229: 40 | H229: 1003.31
... A271: d344a2c7 | B271: 45135 | C271: eAsT | D271: FURNiture | E271: 3012.88 | F271: 16 | G271: 16 | H271: 789.81
A272: 6.7765e+71 | B272: 44970 | C272: norTh | D272: Cloth ing | E272: 1877.37 | F272: 40 | G272: 46 | H272: 730.86
A273: 3cccf911 | B273: 45595 | C273: Mes$t | D273: electronicS | E273: 2634.24 | F273: 19 | G273: 35 | H273: 38.85
A274: 7fc85b77 | B274: 45023 | C274: eAsT | D274: $port$ | E274: 2112.39 | F274: 29 | G274: 15 | H274: 1063.37
A275: 67786d7a | B275: 45028 | C275: norTh | D275: GroCerieS | E275: 1184.59 | F275: 10 | G275: 32 | H275: 1911.66
...

Sheet Data cleaning
A1: Order ID | B1: Order Date | C1: Region | D1: Product Category | E1: Sales Amount | F1: Quantity Sold | G1: Discount (%) | H1: Profit | L1: order id | M1: Order Date | N1: Region | O1: Product Category | P1: Sales Amount | Q1: Quantity Sold | R1: Discount % | S1: profit
A2: ab899d2f | B2: 45022 | C2: North | D2: Groceries | E2: 859.29 | F2: 44 | G2: 37 | H2: 1653.87 | L2: =TRIM(A2) -> ab899d2f | M2: 45022 | N2: =PROPER(Table1[[#This Row],[Region]]) -> North | O2: =PROPER(Table1[[#This Row],[Product Category]]) -> Groceries | P2: =ROUND(Table1[[#This Row],[Sales Amount]],1) -> 859.3 | Q2: =Table1[[#This Row],[Quantity Sold]] -> 44 | R2: =Table1[[#This Row],[Discount (%)]] -> 37 | S2: =Table1[[#This Row],[Profit]] -> 1653.87
A3: 73484eb1 | B3: 45023 | C3: West | D3: Groceries | E3: 1546.81 | F3: 23 | G3: 33 | H3: 1932.71 | L3: =TRIM(A3) -> 73484eb1 | M3: 45023 | N3: =PROPER(Table1[[#This Row],[Region]]) -> West | O3: =PROPER(Table1[[#This Row],[Product Category]]) -> Groceries | P3: =ROUND(Table1[[#This Row],[Sales Amount]],1) -> 1546.8 | Q3: =Table1[[#This Row],[Quantity Sold]] -> 23 | R3: =Table1[[#This Row],[Discount (%)]] -> 33 | S3: =Table1[[#This Row],[Profit]] -> 1932.71
A4: 19395924 | B4: 45024 | C4: East | D4: Groceries | E4: 4703.58 | F4: 31 | G4: 15 | H4: 527.47 | L4: =TRIM(A4) -> 19395924 | M4: 45024 | N4: =PROPER(Table1[[#This Row],[Region]]) -> East | O4: =PROPER(Table1[[#This Row],[Product Category]]) -> Groceries | P4: =ROUND(Table1[[#This Row],[Sales Amount]],1) -> 4703.6 | Q4: =Table1[[#This Row],[Quantity Sold]] -> 31 | R4: =Table1[[#This Row],[Discount (%)]] -> 15 | S4: =Table1[[#This Row],[Profit]] -> 527.47
A5: b3fded3d | B5: 45025 | C5: East | D5: Groceries | E5: 3377.17 | F5: 47 | G5: 3 | H5: 482.65 | L5: =TRIM(A5) -> b3fded3d | M5: 45025 | N5: =PROPER(Table1[[#This Row],[Region]]) -> East | O5: =PROPER(Table1[[#This Row],[Product Category]]) -> Groceries | P5: =ROUND(Table1[[#This Row],[Sales Amount]],1) -> 3377.2 | Q5: =Table1[[#This Row],[Quantity Sold]] -> 47 | R5: =Table1[[#This Row],[Discount (%)]] -> 3 | S5: =Table1[[#This Row],[Profit]] -> 482.65
A6: 6e4bdd51 | B6: 45026 | C6: South | D6: Clothing | E6: 3517.49 | F6: 6 | G6: 28 | H6: 748.72 | L6: =TRIM(A6) -> 6e4bdd51 | M6: 45026 | N6: =PROPER(Table1[[#This Row],[Region]]) -> South | O6: =PROPER(Table1[[#This Row],[Product Category]]) -> Clothing | P6: =ROUND(Table1[[#This Row],[Sales Amount]],1) -> 3517.5 | Q6: =Table1[[#This Row],[Quantity Sold]] -> 6 | R6: =Table1[[#This Row],[Discount (%)]] -> 28 | S6: =Table1[[#This Row],[Profit]] -> 748.72
A7: 21d88d69 | B7: 45027 | C7: East | D7: Furniture | E7: 362.55 | F7: 19 | G7: 50 | H7: 314.71 | L7: =TRIM(A7) -> 21d88d69 | M7: 45027 | N7: =PROPER(Table1[[#This Row],[Region]]) -> East | O7: =PROPER(Table1[[#This Row],[Product Category]]) -> Furniture | P7: =ROUND(Table1[[#This Row],[Sales Amount]],1) -> 362.6 | Q7: =Table1[[#This Row],[Quantity Sold]] -> 19 | R7: =Table1[[#This Row],[Discount (%)]] -> 50 | S7: =Table1[[#This Row],[Profit]] -> 314.71
A8: 9da2704d | B8: 45028 | C8: East | D8: Sports | E8: 4811.17 | F8: 22 | G8: 18 | H8: 1372.89 | L8: =TRIM(A8) -> 9da2704d | M8: 45028 | N8: =PROPER(Table1[[#This Row],[Region]]) -> East | O8: =PROPER(Table1[[#This Row],[Product Category]]) -> Sports | P8: =ROUND(Table1[[#This Row],[Sales Amount]],1) -> 4811.2 | Q8: =Table1[[#This Row],[Quantity Sold]] -> 22 | R8: =Table1[[#This Row],[Discount (%)]] -> 18 | S8: =Table1[[#This Row],[Profit]] -> 1372.89
A9: a1bd6815 | B9: 45029 | C9: West | D9: Electronics | E9: 3565.2 | F9: 22 | G9: 16 | H9: 1437.3 | L9: =TRIM(A9) -> a1bd6815 | M9: 45029 | N9: =PROPER(Table1[[#This Row],[Region]]) -> West | O9: =PROPER(Table1[[#This Row],[Product Category]]) -> Electronics | P9: =ROUND(Table1[[#This Row],[Sales Amount]],1) -> 3565.2 | Q9: =Table1[[#This Row],[Quantity Sold]] -> 22 | R9: =Table1[[#This Row],[Discount (%)]] -> 16 | S9: =Table1[[#This Row],[Profit]] -> 1437.3
A10: 0bbd51fc | B10: 45030 | C10: East | D10: Clothing | E10: 3805.25 | F10: 19 | G10: 3 | H10: 1537.28 | L10: =TRIM(A10) -> 0bbd51fc | M10: 45030 | N10: =PROPER(Table1[[#This Row],[Region]]) -> East | O10: =PROPER(Table1[[#This Row],[Product Category]]) -> Clothing | P10: =ROUND(Table1[[#This Row],[Sales Amount]],1) -> 3805.3 | Q10: =Table1[[#This Row],[Quantity Sold]] -> 19 | R10: =Table1[[#This Row],[Discount (%)]] -> 3 | S10: =Table1[[#This Row],[Profit]] -> 1537.28
A11: 8bf7e4b3 | B11: 45031 | C11: South | D11: Clothing | E11: 2178.72 | F11: 15 | G11: 24 | H11: 1696.65 | L11: =TRIM(A11) -> 8bf7e4b3 | M11: 45031 | N11: =PROPER(Table1[[#This Row],[Region]]) -> South | O11: =PROPER(Table1[[#This Row],[Product Category]]) -> Clothing | P11: =ROUND(Table1[[#This Row],[Sales Amount]],1) -> 2178.7 | Q11: =Table1[[#This Row],[Quantity Sold]] -> 15 | R11: =Table1[[#This Row],[Discount (%)]] -> 24 | S11: =Table1[[#This Row],[Profit]] -> 1696.65
A12: e6cf1255 | B12: 45032 | C12: West | D12: Groceries | E12: 2844.93 | F12: 34 | G12: 12 | H12: 1166.39 | L12: =TRIM(A12) -> e6cf1255 | M12: 45032 | N12: =PROPER(Table1[[#This Row],[Region]]) -> West | O12: =PROPER(Table1[[#This Row],[Product Category]]) -> Groceries | P12: =ROUND(Table1[[#This Row],[Sales Amount]],1) -> 2844.9 | Q12: =Table1[[#This Row],[Quantity Sold]] -> 34 | R12: =Table1[[#This Row],[Discount (%)]] -> 12 | S12: =Table1[[#This Row],[Profit]] -> 1166.39
A13: 3ba1fc5c | B13: 45033 | C13: West | D13: Electronics | E13: 3600.04 | F13: 10 | G13: 2 | H13: 1632.75 | L13: =TRIM(A13) -> 3ba1fc5c | M13: 45033 | N13: =PROPER(Table1[[#This Row],[Region]]) -> West | O13: =PROPER(Table1[[#This Row],[Product Category]]) -> Electronics | P13: =ROUND(Table1[[#This Row],[Sales Amount]],1) -> 3600 | Q13: =Table1[[#This Row],[Quantity Sold]] -> 10 | R13: =Table1[[#This Row],[Discount (%)]] -> 2 | S13: =Table1[[#This Row],[Profit]] -> 1632.75
A14: 388ff70d | B14: 45034 | C14: East | D14: Sports | E14: 941.88 | F14: 13 | G14: 28 | H14: 646.49 | L14: =TRIM(A14) -> 388ff70d | M14: 45034 | N14: =PROPER(Table1[[#This Row],[Region]]) -> East | O14: =PROPER(Table1[[#This Row],[Product Category]]) -> Sports | P14: =ROUND(Table1[[#This Row],[Sales Amount]],1) -> 941.9 | Q14: =Table1[[#This Row],[Quantity Sold]] -> 13 | R14: =Table1[[#This Row],[Discount (%)]] -> 28 | S14: =Table1[[#This Row],[Profit]] -> 646.49
A15: ce2e9002 | B15: 45035 | C15: South | D15: Sports | E15: 3300.86 | F15: 1 | G15: 48 | H15: 86.9 | L15: =TRIM(A15) -> ce2e9002 | M15: 45035 | N15: =PROPER(Table1[[#This Row],[Region]]) -> South | O15: =PROPER(Table1[[#This Row],[Product Category]]) -> Sports | P15: =ROUND(Table1[[#This Row],[Sales Amount]],1) -> 3300.9 | Q15: =Table1[[#This Row],[Quantity Sold]] -> 1 | R15: =Table1[[#This Row],[Discount (%)]] -> 48 | S15: =Table1[[#This Row],[Profit]] -> 86.9
A16: a4f9a338 | B16: 45036 | C16: East | D16: Groceries | E16: 1081.62 | F16: 4 | G16: 19 | H16: 611.06 | L16: =TRIM(A16) -> a4f9a338 | M16: 45036 | N16: =PROPER(Table1[[#This Row],[Region]]) -> East | O16: =PROPER(Table1[[#This Row],[Product Category]]) -> Groceries | P16: =ROUND(Table1[[#This Row],[Sales Amount]],1) -> 1081.6 | Q16: =Table1[[#This Row],[Quantity Sold]] -> 4 | R16: =Table1[[#This Row],[Discount (%)]] -> 19 | S16: =Table1[[#This Row],[Profit]] -> 611.06
... A19: 35358e9c | B19: 45039 | C19: North | D19: Clothing | E19: 2784.79 | F19: 35 | G19: 40 | H19: 999.6 | L19: =TRIM(A19) -> 35358e9c | M19: 45039 | N19: =PROPER(Table1[[#This Row],[Region]]) -> North | O19: =PROPER(Table1[[#This Row],[Product Category]]) -> Clothing | P19: =ROUND(Table1[[#This Row],[Sales Amount]],1) -> 2784.8 | Q19: =Table1[[#This Row],[Quantity Sold]] -> 35 | R19: =Table1[[#This Row],[Discount (%)]] -> 40 | S19: =Table1[[#This Row],[Profit]] -> 999.6
A20: 31676338 | B20: 45040 | C20: South | D20: Clothing | E20: 1082.98 | F20: 8 | G20: 11 | H20: 1604.19 | L20: =TRIM(A20) -> 31676338 | M20: 45040 | N20: =PROPER(Table1[[#This Row],[Region]]) -> South | O20: =PROPER(Table1[[#This Row],[Product Category]]) -> Clothing | P20: =ROUND(Table1[[#This Row],[Sales Amount]],1) -> 1083 | Q20: =Table1[[#This Row],[Quantity Sold]] -> 8 | R20: =Table1[[#This Row],[Discount (%)]] -> 11 | S20: =Table1[[#This Row],[Profit]] -> 1604.19
A21: 05d72e20 | B21: 45041 | C21: East | D21: Clothing | E21: 787.79 | F21: 47 | G21: 18 | H21: 1313.33 | L21: =TRIM(A21) -> 05d72e20 | M21: 45041 | N21: =PROPER(Table1[[#This Row],[Region]]) -> East | O21: =PROPER(Table1[[#This Row],[Product Category]]) -> Clothing | P21: =ROUND(Table1[[#This Row],[Sales Amount]],1) -> 787.8 | Q21: =Table1[[#This Row],[Quantity Sold]] -> 47 | R21: =Table1[[#This Row],[Discount (%)]] -> 18 | S21: =Table1[[#This Row],[Profit]] -> 1313.33
A22: 68dbe328 | B22: 45042 | C22: South | D22: Furniture | E22: 312.7 | F22: 36 | G22: 43 | H22: 559.52 | L22: =TRIM(A22) -> 68dbe328 | M22: 45042 | N22: =PROPER(Table1[[#This Row],[Region]]) -> South | O22: =PROPER(Table1[[#This Row],[Product Category]]) -> Furniture | P22: =ROUND(Table1[[#This Row],[Sales Amount]],1) -> 312.7 | Q22: =Table1[[#This Row],[Quantity Sold]] -> 36 | R22: =Table1[[#This Row],[Discount (%)]] -> 43 | S22: =Table1[[#This Row],[Profit]] -> 559.52
A23: 78d3f47b | B23: 45043 | C23: East | D23: Sports | E23: 265.32 | F23: 21 | G23: 36 | H23: 595.91 | L23: =TRIM(A23) -> 78d3f47b | M23: 45043 | N23: =PROPER(Table1[[#This Row],[Region]]) -> East | O23: =PROPER(Table1[[#This Row],[Product Category]]) -> Sports | P23: =ROUND(Table1[[#This Row],[Sales Amount]],1) -> 265.3 | Q23: =Table1[[#This Row],[Quantity Sold]] -> 21 | R23: =Table1[[#This Row],[Discount (%)]] -> 36 | S23: =Table1[[#This Row],[Profit]] -> 595.91
A24: 9e4d1fe0 | B24: 45044 | C24: West | D24: Furniture | E24: 1253.64 | F24: 35 | G24: 14 | H24: 1653.66 | L24: =TRIM(A24) -> 9e4d1fe0 | M24: 45044 | N24: =PROPER(Table1[[#This Row],[Region]]) -> West | O24: =PROPER(Table1[[#This Row],[Product Category]]) -> Furniture | P24: =ROUND(Table1[[#This Row],[Sales Amount]],1) -> 1253.6 | Q24: =Table1[[#This Row],[Quantity Sold]] -> 35 | R24: =Table1[[#This Row],[Discount (%)]] -> 14 | S24: =Table1[[#This Row],[Profit]] -> 1653.66
A25: 9215a70e | B25: 45045 | C25: West | D25: Clothing | E25: 1874.07 | F25: 28 | G25: 23 | H25: 1783.26 | L25: =TRIM(A25) -> 9215a70e | M25: 45045 | N25: =PROPER(Table1[[#This Row],[Region]]) -> West | O25: =PROPER(Table1[[#This Row],[Product Category]]) -> Clothing | P25: =ROUND(Table1[[#This Row],[Sales Amount]],1) -> 1874.1 | Q25: =Table1[[#This Row],[Quantity Sold]] -> 28 | R25: =Table1[[#This Row],[Discount (%)]] -> 23 | S25: =Table1[[#This Row],[Profit]] -> 1783.26
A26: 54ca3433 | B26: 45046 | C26: East | D26: Clothing | E26: 2561.71 | F26: 44 | G26: 10 | H26: 800.82 | L26: =TRIM(A26) -> 54ca3433 | M26: 45046 | N26: =PROPER(Table1[[#This Row],[Region]]) -> East | O26: =PROPER(Table1[[#This Row],[Product Category]]) -> Clothing | P26: =ROUND(Table1[[#This Row],[Sales Amount]],1) -> 2561.7 | Q26: =Table1[[#This Row],[Quantity Sold]] -> 44 | R26: =Table1[[#This Row],[Discount (%)]] -> 10 | S26: =Table1[[#This Row],[Profit]] -> 800.82
A27: 0ba75cc7 | B27: 45047 | C27: West | D27: Sports | E27: 1960.74 | F27: 50 | G27: 6 | H27: 1530.61 | L27: =TRIM(A27) -> 0ba75cc7 | M27: 45047 | N27: =PROPER(Table1[[#This Row],[Region]]) -> West | O27: =PROPER(Table1[[#This Row],[Product Category]]) -> Sports | P27: =ROUND(Table1[[#This Row],[Sales Amount]],1) -> 1960.7 | Q27: =Table1[[#This Row],[Quantity Sold]] -> 50 | R27: =Table1[[#This Row],[Discount (%)]] -> 6 | S27: =Table1[[#This Row],[Profit]] -> 1530.61
A28: 601860b1 | B28: 45048 | C28: East | D28: Electronics | E28: 2415.44 | F28: 35 | G28: 14 | H28: 335.57 | L28: =TRIM(A28) -> 601860b1 | M28: 45048 | N28: =PROPER(Table1[[#This Row],[Region]]) -> East | O28: =PROPER(Table1[[#This Row],[Product Category]]) -> Electronics | P28: =ROUND(Table1[[#This Row],[Sales Amount]],1) -> 2415.4 | Q28: =Table1[[#This Row],[Quantity Sold]] -> 35 | R28: =Table1[[#This Row],[Discount (%)]] -> 14 | S28: =Table1[[#This Row],[Profit]] -> 335.57
A29: e393e106 | B29: 45049 | C29: East | D29: Electronics | E29: 2284.22 | F29: 8 | G29: 41 | H29: 1866.59 | L29: =TRIM(A29) -> e393e106 | M29: 45049 | N29: =PROPER(Table1[[#This Row],[Region]]) -> East | O29: =PROPER(Table1[[#This Row],[Product Category]]) -> Electronics | P29: =ROUND(Table1[[#This Row],[Sales Amount]],1) -> 2284.2 | Q29: =Table1[[#This Row],[Quantity Sold]] -> 8 | R29: =Table1[[#This Row],[Discount (%)]] -> 41 | S29: =Table1[[#This Row],[Profit]] -> 1866.59
A30: 7ab3d472 | B30: 45050 | C30: West | D30: Sports | E30: 2118.55 | F30: 29 | G30: 24 | H30: 702.15 | L30: =TRIM(A30) -> 7ab3d472 | M30: 45050 | N30: =PROPER(Table1[[#This Row],[Region]]) -> West | O30: =PROPER(Table1[[#This Row],[Product Category]]) -> Sports | P30: =ROUND(Table1[[#This Row],[Sales Amount]],1) -> 2118.6 | Q30: =Table1[[#This Row],[Quantity Sold]] -> 29 | R30: =Table1[[#This Row],[Discount (%)]] -> 24 | S30: =Table1[[#This Row],[Profit]] -> 702.15
A31: 01d9b1ae | B31: 45051 | C31: South | D31: Groceries | E31: 4803.6 | F31: 11 | G31: 12 | H31: 1086.74 | L31: =TRIM(A31) -> 01d9b1ae | M31: 45051 | N31: =PROPER(Table1[[#This Row],[Region]]) -> South | O31: =PROPER(Table1[[#This Row],[Product Category]]) -> Groceries | P31: =ROUND(Table1[[#This Row],[Sales Amount]],1) -> 4803.6 | Q31: =Table1[[#This Row],[Quantity Sold]] -> 11 | R31: =Table1[[#This Row],[Discount (%)]] -> 12 | S31: =Table1[[#This Row],[Profit]] -> 1086.74
A32: 20385cb6 | B32: 45052 | C32: North | D32: Groceries | E32: 4297 | F32: 17 | G32: 49 | H32: 678.7 | L32: =TRIM(A32) -> 20385cb6 | M32: 45052 | N32: =PROPER(Table1[[#This Row],[Region]]) -> North | O32: =PROPER(Table1[[#This Row],[Product Category]]) -> Groceries | P32: =ROUND(Table1[[#This Row],[Sales Amount]],1) -> 4297 | Q32: =Table1[[#This Row],[Quantity Sold]] -> 17 | R32: =Table1[[#This Row],[Discount (%)]] -> 49 | S32: =Table1[[#This Row],[Profit]] -> 678.7
... A69: 92458ed3 | B69: 45089 | C69: North | D69: Furniture | E69: 1356.62 | F69: 2 | G69: 21 | H69: 1213.34 | L69: =TRIM(A69) -> 92458ed3 | M69: 45089 | N69: =PROPER(Table1[[#This Row],[Region]]) -> North | O69: =PROPER(Table1[[#This Row],[Product Category]]) -> Furniture | P69: =ROUND(Table1[[#This Row],[Sales Amount]],1) -> 1356.6 | Q69: =Table1[[#This Row],[Quantity Sold]] -> 2 | R69: =Table1[[#This Row],[Discount (%)]] -> 21 | S69: =Table1[[#This Row],[Profit]] -> 1213.34
A70: 76740552 | B70: 45090 | C70: South | D70: Electronics | E70: 2905.8 | F70: 20 | G70: 10 | H70: 1417.43 | L70: =TRIM(A70) -> 76740552 | M70: 45090 | N70: =PROPER(Table1[[#This Row],[Region]]) -> South | O70: =PROPER(Table1[[#This Row],[Product Category]]) -> Electronics | P70: =ROUND(Table1[[#This Row],[Sales Amount]],1) -> 2905.8 | Q70: =Table1[[#This Row],[Quantity Sold]] -> 20 | R70: =Table1[[#This Row],[Discount (%)]] -> 10 | S70: =Table1[[#This Row],[Profit]] -> 1417.43
A71: f92de80d | B71: 45091 | C71: South | D71: Furniture | E71: 2065.42 | F71: 22 | G71: 15 | H71: 787.51 | L71: =TRIM(A71) -> f92de80d | M71: 45091 | N71: =PROPER(Table1[[#This Row],[Region]]) -> South | O71: =PROPER(Table1[[#This Row],[Product Category]]) -> Furniture | P71: =ROUND(Table1[[#This Row],[Sales Amount]],1) -> 2065.4 | Q71: =Table1[[#This Row],[Quantity Sold]] -> 22 | R71: =Table1[[#This Row],[Discount (%)]] -> 15 | S71: =Table1[[#This Row],[Profit]] -> 787.51
A72: 647ff51a | B72: 45092 | C72: East | D72: Clothing | E72: 272.88 | F72: 47 | G72: 29 | H72: 1208.68 | L72: =TRIM(A72) -> 647ff51a | M72: 45092 | N72: =PROPER(Table1[[#This Row],[Region]]) -> East | O72: =PROPER(Table1[[#This Row],[Product Category]]) -> Clothing | P72: =ROUND(Table1[[#This Row],[Sales Amount]],1) -> 272.9 | Q72: =Table1[[#This Row],[Quantity Sold]] -> 47 | R72: =Table1[[#This Row],[Discount (%)]] -> 29 | S72: =Table1[[#This Row],[Profit]] -> 1208.68
A73: f8548ec7 | B73: 45093 | C73: East | D73: Clothing | E73: 4126.4 | F73: 34 | G73: 13 | H73: 1690.11 | L73: =TRIM(A73) -> f8548ec7 | M73: 45093 | N73: =PROPER(Table1[[#This Row],[Region]]) -> East | O73: =PROPER(Table1[[#This Row],[Product Category]]) -> Clothing | P73: =ROUND(Table1[[#This Row],[Sales Amount]],1) -> 4126.4 | Q73: =Table1[[#This Row],[Quantity Sold]] -> 34 | R73: =Table1[[#This Row],[Discount (%)]] -> 13 | S73: =Table1[[#This Row],[Profit]] -> 1690.11
A74: 7855a0d2 | B74: 45094 | C74: North | D74: Furniture | E74: 4204.55 | F74: 49 | G74: 1 | H74: 1534.82 | L74: =TRIM(A74) -> 7855a0d2 | M74: 45094 | N74: =PROPER(Table1[[#This Row],[Region]]) -> North | O74: =PROPER(Table1[[#This Row],[Product Category]]) -> Furniture | P74: =ROUND(Table1[[#This Row],[Sales Amount]],1) -> 4204.6 | Q74: =Table1[[#This Row],[Quantity Sold]] -> 49 | R74: =Table1[[#This Row],[Discount (%)]] -> 1 | S74: =Table1[[#This Row],[Profit]] -> 1534.82
A75: bf586512 | B75: 45095 | C75: West | D75: Clothing | E75: 2130.98 | F75: 7 | G75: 29 | H75: 679.16 | L75: =TRIM(A75) -> bf586512 | M75: 45095 | N75: =PROPER(Table1[[#This Row],[Region]]) -> West | O75: =PROPER(Table1[[#This Row],[Product Category]]) -> Clothing | P75: =ROUND(Table1[[#This Row],[Sales Amount]],1) -> 2131 | Q75: =Table1[[#This Row],[Quantity Sold]] -> 7 | R75: =Table1[[#This Row],[Discount (%)]] -> 29 | S75: =Table1[[#This Row],[Profit]] -> 679.16
A76: deea1965 | B76: 45096 | C76: South | D76: Furniture | E76: 1253.28 | F76: 4 | G76: 48 | H76: 317.33 | L76: =TRIM(A76) -> deea1965 | M76: 45096 | N76: =PROPER(Table1[[#This Row],[Region]]) -> South | O76: =PROPER(Table1[[#This Row],[Product Category]]) -> Furniture | P76: =ROUND(Table1[[#This Row],[Sales Amount]],1) -> 1253.3 | Q76: =Table1[[#This Row],[Quantity Sold]] -> 4 | R76: =Table1[[#This Row],[Discount (%)]] -> 48 | S76: =Table1[[#This Row],[Profit]] -> 317.33
A77: a0a8290f | B77: 45097 | C77: South | D77: Sports | E77: 1050.29 | F77: 30 | G77: 4 | H77: 423.5 | L77: =TRIM(A77) -> a0a8290f | M77: 45097 | N77: =PROPER(Table1[[#This Row],[Region]]) -> South | O77: =PROPER(Table1[[#This Row],[Product Category]]) -> Sports | P77: =ROUND(Table1[[#This Row],[Sales Amount]],1) -> 1050.3 | Q77: =Table1[[#This Row],[Quantity Sold]] -> 30 | R77: =Table1[[#This Row],[Discount (%)]] -> 4 | S77: =Table1[[#This Row],[Profit]] -> 423.5
A78: 077a9429 | B78: 45098 | C78: North | D78: Furniture | E78: 1269.1 | F78: 3 | G78: 7 | H78: 1819.88 | L78: =TRIM(A78) -> 077a9429 | M78: 45098 | N78: =PROPER(Table1[[#This Row],[Region]]) -> North | O78: =PROPER(Table1[[#This Row],[Product Category]]) -> Furniture | P78: =ROUND(Table1[[#This Row],[Sales Amount]],1) -> 1269.1 | Q78: =Table1[[#This Row],[Quantity Sold]] -> 3 | R78: =Table1[[#This Row],[Discount (%)]] -> 7 | S78: =Table1[[#This Row],[Profit]] -> 1819.88
A79: 8642940000 | B79: 45099 | C79: West | D79: Groceries | E79: 4229.47 | F79: 3 | G79: 9 | H79: 11.29 | L79: =TRIM(A79) -> 8642940000 | M79: 45099 | N79: =PROPER(Table1[[#This Row],[Region]]) -> West | O79: =PROPER(Table1[[#This Row],[Product Category]]) -> Groceries | P79: =ROUND(Table1[[#This Row],[Sales Amount]],1) -> 4229.5 | Q79: =Table1[[#This Row],[Quantity Sold]] -> 3 | R79: =Table1[[#This Row],[Discount (%)]] -> 9 | S79: =Table1[[#This Row],[Profit]] -> 11.29
A80: 41d1321a | B80: 45100 | C80: South | D80: Groceries | E80: 3767.63 | F80: 30 | G80: 41 | H80: 1031.74 | L80: =TRIM(A80) -> 41d1321a | M80: 45100 | N80: =PROPER(Table1[[#This Row],[Region]]) -> South | O80: =PROPER(Table1[[#This Row],[Product Category]]) -> Groceries | P80: =ROUND(Table1[[#This Row],[Sales Amount]],1) -> 3767.6 | Q80: =Table1[[#This Row],[Quantity Sold]] -> 30 | R80: =Table1[[#This Row],[Discount (%)]] -> 41 | S80: =Table1[[#This Row],[Profit]] -> 1031.74
A81: 44afa795 | B81: 45101 | C81: West | D81: Sports | E81: 640.91 | F81: 19 | G81: 19 | H81: 1148.62 | L81: =TRIM(A81) -> 44afa795 | M81: 45101 | N81: =PROPER(Table1[[#This Row],[Region]]) -> West | O81: =PROPER(Table1[[#This Row],[Product Category]]) -> Sports | P81: =ROUND(Table1[[#This Row],[Sales Amount]],1) -> 640.9 | Q81: =Table1[[#This Row],[Quantity Sold]] -> 19 | R81: =Table1[[#This Row],[Discount (%)]] -> 19 | S81: =Table1[[#This Row],[Profit]] -> 1148.62
A82: 8c329e53 | B82: 45102 | C82: North | D82: Furniture | E82: 2958 | F82: 4 | G82: 22 | H82: 1968.62 | L82: =TRIM(A82) -> 8c329e53 | M82: 45102 | N82: =PROPER(Table1[[#This Row],[Region]]) -> North | O82: =PROPER(Table1[[#This Row],[Product Category]]) -> Furniture | P82: =ROUND(Table1[[#This Row],[Sales Amount]],1) -> 2958 | Q82: =Table1[[#This Row],[Quantity Sold]] -> 4 | R82: =Table1[[#This Row],[Discount (%)]] -> 22 | S82: =Table1[[#This Row],[Profit]] -> 1968.62
A83: cdbba08a | B83: 45103 | C83: West | D83: Sports | E83: 4049.49 | F83: 5 | G83: 1 | H83: 1151.9 | L83: =TRIM(A83) -> cdbba08a | M83: 45103 | N83: =PROPER(Table1[[#This Row],[Region]]) -> West | O83: =PROPER(Table1[[#This Row],[Product Category]]) -> Sports | P83: =ROUND(Table1[[#This Row],[Sales Amount]],1) -> 4049.5 | Q83: =Table1[[#This Row],[Quantity Sold]] -> 5 | R83: =Table1[[#This Row],[Discount (%)]] -> 1 | S83: =Table1[[#This Row],[Profit]] -> 1151.9
A84: 4415c908 | B84: 45104 | C84: North | D84: Sports | E84: 4155.03 | F84: 32 | G84: 5 | H84: 1637.7 | L84: =TRIM(A84) -> 4415c908 | M84: 45104 | N84: =PROPER(Table1[[#This Row],[Region]]) -> North | O84: =PROPER(Table1[[#This Row],[Product Category]]) -> Sports | P84: =ROUND(Table1[[#This Row],[Sales Amount]],1) -> 4155 | Q84: =Table1[[#This Row],[Quantity Sold]] -> 32 | R84: =Table1[[#This Row],[Discount (%)]] -> 5 | S84: =Table1[[#This Row],[Profit]] -> 1637.7
A85: a9ac13d3 | B85: 45105 | C85: North | D85: Furniture | E85: 2011.35 | F85: 44 | G85: 10 | H85: 829.69 | L85: =TRIM(A85) -> a9ac13d3 | M85: 45105 | N85: =PROPER(Table1[[#This Row],[Region]]) -> North | O85: =PROPER(Table1[[#This Row],[Product Category]]) -> Furniture | P85: =ROUND(Table1[[#This Row],[Sales Amount]],1) -> 2011.4 | Q85: =Table1[[#This Row],[Quantity Sold]] -> 44 | R85: =Table1[[#This Row],[Discount (%)]] -> 10 | S85: =Table1[[#This Row],[Profit]] -> 829.69
A86: 5fbf219e | B86: 45106 | C86: West | D86: Electronics | E86: 2365.24 | F86: 10 | G86: 33 | H86: 1970.1 | L86: =TRIM(A86) -> 5fbf219e | M86: 45106 | N86: =PROPER(Table1[[#This Row],[Region]]) -> West | O86: =PROPER(Table1[[#This Row],[Product Category]]) -> Electronics | P86: =ROUND(Table1[[#This Row],[Sales Amount]],1) -> 2365.2 | Q86: =Table1[[#This Row],[Quantity Sold]] -> 10 | R86: =Table1[[#This Row],[Discount (%)]] -> 33 | S86: =Table1[[#This Row],[Profit]] -> 1970.1
A87: f3ba50cf | B87: 45107 | C87: South | D87: Clothing | E87: 2615.84 | F87: 31 | G87: 9 | H87: 1276.87 | L87: =TRIM(A87) -> f3ba50cf | M87: 45107 | N87: =PROPER(Table1[[#This Row],[Region]]) -> South | O87: =PROPER(Table1[[#This Row],[Product Category]]) -> Clothing | P87: =ROUND(Table1[[#This Row],[Sales Amount]],1) -> 2615.8 | Q87: =Table1[[#This Row],[Quantity Sold]] -> 31 | R87: =Table1[[#This Row],[Discount (%)]] -> 9 | S87: =Table1[[#This Row],[Profit]] -> 1276.87
A88: 88840b0f | B88: 45108 | C88: West | D88: Clothing | E88: 4954.33 | F88: 26 | G88: 43 | H88: 1723.31 | L88: =TRIM(A88) -> 88840b0f | M88: 45108 | N88: =PROPER(Table1[[#This Row],[Region]]) -> West | O88: =PROPER(Table1[[#This Row],[Product Category]]) -> Clothing | P88: =ROUND(Table1[[#This Row],[Sales Amount]],1) -> 4954.3 | Q88: =Table1[[#This Row],[Quantity Sold]] -> 26 | R88: =Table1[[#This Row],[Discount (%)]] -> 43 | S88: =Table1[[#This Row],[Profit]] -> 1723.31
A89: 3dcffe93 | B89: 45109 | C89: North | D89: Clothing | E89: 1969.35 | F89: 27 | G89: 11 | H89: 1532.9 | L89: =TRIM(A89) -> 3dcffe93 | M89: 45109 | N89: =PROPER(Table1[[#This Row],[Region]]) -> North | O89: =PROPER(Table1[[#This Row],[Product Category]]) -> Clothing | P89: =ROUND(Table1[[#This Row],[Sales Amount]],1) -> 1969.4 | Q89: =Table1[[#This Row],[Quantity Sold]] -> 27 | R89: =Table1[[#This Row],[Discount (%)]] -> 11 | S89: =Table1[[#This Row],[Profit]] -> 1532.9
A90: 745eb905 | B90: 45110 | C90: North | D90: Clothing | E90: 2083.02 | F90: 49 | G90: 11 | H90: 105.26 | L90: =TRIM(A90) -> 745eb905 | M90: 45110 | N90: =PROPER(Table1[[#This Row],[Region]]) -> North | O90: =PROPER(Table1[[#This Row],[Product Category]]) -> Clothing | P90: =ROUND(Table1[[#This Row],[Sales Amount]],1) -> 2083 | Q90: =Table1[[#This Row],[Quantity Sold]] -> 49 | R90: =Table1[[#This Row],[Discount (%)]] -> 11 | S90: =Table1[[#This Row],[Profit]] -> 105.26
A91: b8fca939 | B91: 45111 | C91: South | D91: Electronics | E91: 4752.49 | F91: 36 | G91: 8 | H91: 1903.35 | L91: =TRIM(A91) -> b8fca939 | M91: 45111 | N91: =PROPER(Table1[[#This Row],[Region]]) -> South | O91: =PROPER(Table1[[#This Row],[Product Category]]) -> Electronics | P91: =ROUND(Table1[[#This Row],[Sales Amount]],1) -> 4752.5 | Q91: =Table1[[#This Row],[Quantity Sold]] -> 36 | R91: =Table1[[#This Row],[Discount (%)]] -> 8 | S91: =Table1[[#This Row],[Profit]] -> 1903.35
... A150: c41efe4c | B150: 45170 | C150: South | D150: Furniture | E150: 1453.8 | F150: 13 | G150: 16 | H150: 385.22 | L150: =TRIM(A150) -> c41efe4c | M150: 45170 | N150: =PROPER(Table1[[#This Row],[Region]]) -> South | O150: =PROPER(Table1[[#This Row],[Product Category]]) -> Furniture | P150: =ROUND(Table1[[#This Row],[Sales Amount]],1) -> 1453.8 | Q150: =Table1[[#This Row],[Quantity Sold]] -> 13 | R150: =Table1[[#This Row],[Discount (%)]] -> 16 | S150: =Table1[[#This Row],[Profit]] -> 385.22
A151: 61831599 | B151: 45171 | C151: East | D151: Sports | E151: 4889.46 | F151: 1 | G151: 20 | H151: 807.13 | L151: =TRIM(A151) -> 61831599 | M151: 45171 | N151: =PROPER(Table1[[#This Row],[Region]]) -> East | O151: =PROPER(Table1[[#This Row],[Product Category]]) -> Sports | P151: =ROUND(Table1[[#This Row],[Sales Amount]],1) -> 4889.5 | Q151: =Table1[[#This Row],[Quantity Sold]] -> 1 | R151: =Table1[[#This Row],[Discount (%)]] -> 20 | S151: =Table1[[#This Row],[Profit]] -> 807.13
A152: cf159d42 | B152: 45172 | C152: East | D152: Sports | E152: 2548.91 | F152: 3 | G152: 7 | H152: 694.24 | L152: =TRIM(A152) -> cf159d42 | M152: 45172 | N152: =PROPER(Table1[[#This Row],[Region]]) -> East | O152: =PROPER(Table1[[#This Row],[Product Category]]) -> Sports | P152: =ROUND(Table1[[#This Row],[Sales Amount]],1) -> 2548.9 | Q152: =Table1[[#This Row],[Quantity Sold]] -> 3 | R152: =Table1[[#This Row],[Discount (%)]] -> 7 | S152: =Table1[[#This Row],[Profit]] -> 694.24
A153: ffa6342d | B153: 45173 | C153: South | D153: Clothing | E153: 3804.77 | F153: 31 | G153: 47 | H153: 185.46 | L153: =TRIM(A153) -> ffa6342d | M153: 45173 | N153: =PROPER(Table1[[#This Row],[Region]]) -> South | O153: =PROPER(Table1[[#This Row],[Product Category]]) -> Clothing | P153: =ROUND(Table1[[#This Row],[Sales Amount]],1) -> 3804.8 | Q153: =Table1[[#This Row],[Quantity Sold]] -> 31 | R153: =Table1[[#This Row],[Discount (%)]] -> 47 | S153: =Table1[[#This Row],[Profit]] -> 185.46
A154: 459360d4 | B154: 45174 | C154: East | D154: Groceries | E154: 372.53 | F154: 19 | G154: 13 | H154: 232.82 | L154: =TRIM(A154) -> 459360d4 | M154: 45174 | N154: =PROPER(Table1[[#This Row],[Region]]) -> East | O154: =PROPER(Table1[[#This Row],[Product Category]]) -> Groceries | P154: =ROUND(Table1[[#This Row],[Sales Amount]],1) -> 372.5 | Q154: =Table1[[#This Row],[Quantity Sold]] -> 19 | R154: =Table1[[#This Row],[Discount (%)]] -> 13 | S154: =Table1[[#This Row],[Profit]] -> 232.82
A155: fdf4755a | B155: 45175 | C155: North | D155: Electronics | E155: 2573.55 | F155: 48 | G155: 36 | H155: 1707.54 | L155: =TRIM(A155) -> fdf4755a | M155: 45175 | N155: =PROPER(Table1[[#This Row],[Region]]) -> North | O155: =PROPER(Table1[[#This Row],[Product Category]]) -> Electronics | P155: =ROUND(Table1[[#This Row],[Sales Amount]],1) -> 2573.6 | Q155: =Table1[[#This Row],[Quantity Sold]] -> 48 | R155: =Table1[[#This Row],[Discount (%)]] -> 36 | S155: =Table1[[#This Row],[Profit]] -> 1707.54
A156: 0a7d436c | B156: 45176 | C156: West | D156: Clothing | E156: 1761.29 | F156: 27 | G156: 12 | H156: 492.03 | L156: =TRIM(A156) -> 0a7d436c | M156: 45176 | N156: =PROPER(Table1[[#This Row],[Region]]) -> West | O156: =PROPER(Table1[[#This Row],[Product Category]]) -> Clothing | P156: =ROUND(Table1[[#This Row],[Sales Amount]],1) -> 1761.3 | Q156: =Table1[[#This Row],[Quantity Sold]] -> 27 | R156: =Table1[[#This Row],[Discount (%)]] -> 12 | S156: =Table1[[#This Row],[Profit]] -> 492.03
A157: 3c1ab674 | B157: 45177 | C157: East | D157: Groceries | E157: 4113.4 | F157: 32 | G157: 3 | H157: 1726.09 | L157: =TRIM(A157) -> 3c1ab674 | M157: 45177 | N157: =PROPER(Table1[[#This Row],[Region]]) -> East | O157: =PROPER(Table1[[#This Row],[Product Category]]) -> Groceries | P157: =ROUND(Table1[[#This Row],[Sales Amount]],1) -> 4113.4 | Q157: =Table1[[#This Row],[Quantity Sold]] -> 32 | R157: =Table1[[#This Row],[Discount (%)]] -> 3 | S157: =Table1[[#This Row],[Profit]] -> 1726.09
A158: 42b5d016 | B158: 45178 | C158: West | D158: Electronics | E158: 202.21 | F158: 6 | G158: 43 | H158: 734.47 | L158: =TRIM(A158) -> 42b5d016 | M158: 45178 | N158: =PROPER(Table1[[#This Row],[Region]]) -> West | O158: =PROPER(Table1[[#This Row],[Product Category]]) -> Electronics | P158: =ROUND(Table1[[#This Row],[Sales Amount]],1) -> 202.2 | Q158: =Table1[[#This Row],[Quantity Sold]] -> 6 | R158: =Table1[[#This Row],[Discount (%)]] -> 43 | S158: =Table1[[#This Row],[Profit]] -> 734.47
A159: 2616d5b4 | B159: 45179 | C159: North | D159: Sports | E159: 4347.15 | F159: 20 | G159: 34 | H159: 1392.45 | L159: =TRIM(A159) -> 2616d5b4 | M159: 45179 | N159: =PROPER(Table1[[#This Row],[Region]]) -> North | O159: =PROPER(Table1[[#This Row],[Product Category]]) -> Sports | P159: =ROUND(Table1[[#This Row],[Sales Amount]],1) -> 4347.2 | Q159: =Table1[[#This Row],[Quantity Sold]] -> 20 | R159: =Table1[[#This Row],[Discount (%)]] -> 34 | S159: =Table1[[#This Row],[Profit]] -> 1392.45
A160: 338c4722 | B160: 45180 | C160: West | D160: Clothing | E160: 4992.83 | F160: 2 | G160: 28 | H160: 1468.94 | L160: =TRIM(A160) -> 338c4722 | M160: 45180 | N160: =PROPER(Table1[[#This Row],[Region]]) -> West | O160: =PROPER(Table1[[#This Row],[Product Category]]) -> Clothing | P160: =ROUND(Table1[[#This Row],[Sales Amount]],1) -> 4992.8 | Q160: =Table1[[#This Row],[Quantity Sold]] -> 2 | R160: =Table1[[#This Row],[Discount (%)]] -> 28 | S160: =Table1[[#This Row],[Profit]] -> 1468.94
A161: 6b1e9797 | B161: 45181 | C161: East | D161: Sports | E161: 1387.18 | F161: 28 | G161: 9 | H161: 381.96 | L161: =TRIM(A161) -> 6b1e9797 | M161: 45181 | N161: =PROPER(Table1[[#This Row],[Region]]) -> East | O161: =PROPER(Table1[[#This Row],[Product Category]]) -> Sports | P161: =ROUND(Table1[[#This Row],[Sales Amount]],1) -> 1387.2 | Q161: =Table1[[#This Row],[Quantity Sold]] -> 28 | R161: =Table1[[#This Row],[Discount (%)]] -> 9 | S161: =Table1[[#This Row],[Profit]] -> 381.96
A162: 6e4fab78 | B162: 45182 | C162: North | D162: Clothing | E162: 4642.87 | F162: 35 | G162: 14 | H162: 216.96 | L162: =TRIM(A162) -> 6e4fab78 | M162: 45182 | N162: =PROPER(Table1[[#This Row],[Region]]) -> North | O162: =PROPER(Table1[[#This Row],[Product Category]]) -> Clothing | P162: =ROUND(Table1[[#This Row],[Sales Amount]],1) -> 4642.9 | Q162: =Table1[[#This Row],[Quantity Sold]] -> 35 | R162: =Table1[[#This Row],[Discount (%)]] -> 14 | S162: =Table1[[#This Row],[Profit]] -> 216.96
A163: 8944bc68 | B163: 45183 | C163: East | D163: Electronics | E163: 4879.9 | F163: 37 | G163: 5 | H163: 1424.1 | L163: =TRIM(A163) -> 8944bc68 | M163: 45183 | N163: =PROPER(Table1[[#This Row],[Region]]) -> East | O163: =PROPER(Table1[[#This Row],[Product Category]]) -> Electronics | P163: =ROUND(Table1[[#This Row],[Sales Amount]],1) -> 4879.9 | Q163: =Table1[[#This Row],[Quantity Sold]] -> 37 | R163: =Table1[[#This Row],[Discount (%)]] -> 5 | S163: =Table1[[#This Row],[Profit]] -> 1424.1
... A199: 1e18c00a | B199: 45219 | C199: North | D199: Clothing | E199: 2925.27 | F199: 24 | G199: 4 | H199: 1753.87 | L199: =TRIM(A199) -> 1e18c00a | M199: 45219 | N199: =PROPER(Table1[[#This Row],[Region]]) -> North | O199: =PROPER(Table1[[#This Row],[Product Category]]) -> Clothing | P199: =ROUND(Table1[[#This Row],[Sales Amount]],1) -> 2925.3 | Q199: =Table1[[#This Row],[Quantity Sold]] -> 24 | R199: =Table1[[#This Row],[Discount (%)]] -> 4 | S199: =Table1[[#This Row],[Profit]] -> 1753.87
A200: 37431000 | B200: 45220 | C200: South | D200: Groceries | E200: 2454.67 | F200: 10 | G200: 28 | H200: 47.54 | L200: =TRIM(A200) -> 37431000 | M200: 45220 | N200: =PROPER(Table1[[#This Row],[Region]]) -> South | O200: =PROPER(Table1[[#This Row],[Product Category]]) -> Groceries | P200: =ROUND(Table1[[#This Row],[Sales Amount]],1) -> 2454.7 | Q200: =Table1[[#This Row],[Quantity Sold]] -> 10 | R200: =Table1[[#This Row],[Discount (%)]] -> 28 | S200: =Table1[[#This Row],[Profit]] -> 47.54
A201: af24551a | B201: 45221 | C201: North | D201: Groceries | E201: 4662.47 | F201: 13 | G201: 22 | H201: 735.39 | L201: =TRIM(A201) -> af24551a | M201: 45221 | N201: =PROPER(Table1[[#This Row],[Region]]) -> North | O201: =PROPER(Table1[[#This Row],[Product Category]]) -> Groceries | P201: =ROUND(Table1[[#This Row],[Sales Amount]],1) -> 4662.5 | Q201: =Table1[[#This Row],[Quantity Sold]] -> 13 | R201: =Table1[[#This Row],[Discount (%)]] -> 22 | S201: =Table1[[#This Row],[Profit]] -> 735.39
A202: 6b389c40 | B202: 45222 | C202: West | D202: Clothing | E202: 2943.33 | F202: 45 | G202: 8 | H202: 571.04 | L202: =TRIM(A202) -> 6b389c40 | M202: 45222 | N202: =PROPER(Table1[[#This Row],[Region]]) -> West | O202: =PROPER(Table1[[#This Row],[Product Category]]) -> Clothing | P202: =ROUND(Table1[[#This Row],[Sales Amount]],1) -> 2943.3 | Q202: =Table1[[#This Row],[Quantity Sold]] -> 45 | R202: =Table1[[#This Row],[Discount (%)]] -> 8 | S202: =Table1[[#This Row],[Profit]] -> 571.04
A203: 7743bcd0 | B203: 45223 | C203: South | D203: Groceries | E203: 2261.46 | F203: 46 | G203: 39 | H203: 373.45 | L203: =TRIM(A203) -> 7743bcd0 | M203: 45223 | N203: =PROPER(Table1[[#This Row],[Region]]) -> South | O203: =PROPER(Table1[[#This Row],[Product Category]]) -> Groceries | P203: =ROUND(Table1[[#This Row],[Sales Amount]],1) -> 2261.5 | Q203: =Table1[[#This Row],[Quantity Sold]] -> 46 | R203: =Table1[[#This Row],[Discount (%)]] -> 39 | S203: =Table1[[#This Row],[Profit]] -> 373.45
A204: 84d09672 | B204: 45224 | C204: North | D204: Sports | E204: 2679.53 | F204: 36 | G204: 6 | H204: 1471 | L204: =TRIM(A204) -> 84d09672 | M204: 45224 | N204: =PROPER(Table1[[#This Row],[Region]]) -> North | O204: =PROPER(Table1[[#This Row],[Product Category]]) -> Sports | P204: =ROUND(Table1[[#This Row],[Sales Amount]],1) -> 2679.5 | Q204: =Table1[[#This Row],[Quantity Sold]] -> 36 | R204: =Table1[[#This Row],[Discount (%)]] -> 6 | S204: =Table1[[#This Row],[Profit]] -> 1471
A205: bd554f96 | B205: 45225 | C205: East | D205: Electronics | E205: 1290.66 | F205: 46 | G205: 8 | H205: 147.39 | L205: =TRIM(A205) -> bd554f96 | M205: 45225 | N205: =PROPER(Table1[[#This Row],[Region]]) -> East | O205: =PROPER(Table1[[#This Row],[Product Category]]) -> Electronics | P205: =ROUND(Table1[[#This Row],[Sales Amount]],1) -> 1290.7 | Q205: =Table1[[#This Row],[Quantity Sold]] -> 46 | R205: =Table1[[#This Row],[Discount (%)]] -> 8 | S205: =Table1[[#This Row],[Profit]] -> 147.39
A206: dee8766b | B206: 45226 | C206: East | D206: Groceries | E206: 211.31 | F206: 45 | G206: 48 | H206: 1844.45 | L206: =TRIM(A206) -> dee8766b | M206: 45226 | N206: =PROPER(Table1[[#This Row],[Region]]) -> East | O206: =PROPER(Table1[[#This Row],[Product Category]]) -> Groceries | P206: =ROUND(Table1[[#This Row],[Sales Amount]],1) -> 211.3 | Q206: =Table1[[#This Row],[Quantity Sold]] -> 45 | R206: =Table1[[#This Row],[Discount (%)]] -> 48 | S206: =Table1[[#This Row],[Profit]] -> 1844.45
A207: 733628ca | B207: 45227 | C207: West | D207: Furniture | E207: 3582.85 | F207: 42 | G207: 48 | H207: 1359.36 | L207: =TRIM(A207) -> 733628ca | M207: 45227 | N207: =PROPER(Table1[[#This Row],[Region]]) -> West | O207: =PROPER(Table1[[#This Row],[Product Category]]) -> Furniture | P207: =ROUND(Table1[[#This Row],[Sales Amount]],1) -> 3582.9 | Q207: =Table1[[#This Row],[Quantity Sold]] -> 42 | R207: =Table1[[#This Row],[Discount (%)]] -> 48 | S207: =Table1[[#This Row],[Profit]] -> 1359.36
A208: 7101a707 | B208: 45228 | C208: West | D208: Furniture | E208: 419.94 | F208: 12 | G208: 22 | H208: 1047.8 | L208: =TRIM(A208) -> 7101a707 | M208: 45228 | N208: =PROPER(Table1[[#This Row],[Region]]) -> West | O208: =PROPER(Table1[[#This Row],[Product Category]]) -> Furniture | P208: =ROUND(Table1[[#This Row],[Sales Amount]],1) -> 419.9 | Q208: =Table1[[#This Row],[Quantity Sold]] -> 12 | R208: =Table1[[#This Row],[Discount (%)]] -> 22 | S208: =Table1[[#This Row],[Profit]] -> 1047.8
A209: 7349ac4e | B209: 45229 | C209: East | D209: Sports | E209: 4422.18 | F209: 14 | G209: 33 | H209: 237.47 | L209: =TRIM(A209) -> 7349ac4e | M209: 45229 | N209: =PROPER(Table1[[#This Row],[Region]]) -> East | O209: =PROPER(Table1[[#This Row],[Product Category]]) -> Sports | P209: =ROUND(Table1[[#This Row],[Sales Amount]],1) -> 4422.2 | Q209: =Table1[[#This Row],[Quantity Sold]] -> 14 | R209: =Table1[[#This Row],[Discount (%)]] -> 33 | S209: =Table1[[#This Row],[Profit]] -> 237.47
A210: fbe74fbe | B210: 45230 | C210: East | D210: Furniture | E210: 3277.47 | F210: 11 | G210: 2 | H210: 379.92 | L210: =TRIM(A210) -> fbe74fbe | M210: 45230 | N210: =PROPER(Table1[[#This Row],[Region]]) -> East | O210: =PROPER(Table1[[#This Row],[Product Category]]) -> Furniture | P210: =ROUND(Table1[[#This Row],[Sales Amount]],1) -> 3277.5 | Q210: =Table1[[#This Row],[Quantity Sold]] -> 11 | R210: =Table1[[#This Row],[Discount (%)]] -> 2 | S210: =Table1[[#This Row],[Profit]] -> 379.92
A211: 6bde908c | B211: 45231 | C211: North | D211: Clothing | E211: 4264.38 | F211: 31 | G211: 24 | H211: 1179.93 | L211: =TRIM(A211) -> 6bde908c | M211: 45231 | N211: =PROPER(Table1[[#This Row],[Region]]) -> North | O211: =PROPER(Table1[[#This Row],[Product Category]]) -> Clothing | P211: =ROUND(Table1[[#This Row],[Sales Amount]],1) -> 4264.4 | Q211: =Table1[[#This Row],[Quantity Sold]] -> 31 | R211: =Table1[[#This Row],[Discount (%)]] -> 24 | S211: =Table1[[#This Row],[Profit]] -> 1179.93
A212: 56a98641 | B212: 45232 | C212: South | D212: Furniture | E212: 647.38 | F212: 16 | G212: 34 | H212: 1937.88 | L212: =TRIM(A212) -> 56a98641 | M212: 45232 | N212: =PROPER(Table1[[#This Row],[Region]]) -> South | O212: =PROPER(Table1[[#This Row],[Product Category]]) -> Furniture | P212: =ROUND(Table1[[#This Row],[Sales Amount]],1) -> 647.4 | Q212: =Table1[[#This Row],[Quantity Sold]] -> 16 | R212: =Table1[[#This Row],[Discount (%)]] -> 34 | S212: =Table1[[#This Row],[Profit]] -> 1937.88
... A216: 2ecc60c1 | B216: 45236 | C216: South | D216: Clothing | E216: 4559.22 | F216: 14 | G216: 29 | H216: 1055.86 | L216: =TRIM(A216) -> 2ecc60c1 | M216: 45236 | N216: =PROPER(Table1[[#This Row],[Region]]) -> South | O216: =PROPER(Table1[[#This Row],[Product Category]]) -> Clothing | P216: =ROUND(Table1[[#This Row],[Sales Amount]],1) -> 4559.2 | Q216: =Table1[[#This Row],[Quantity Sold]] -> 14 | R216: =Table1[[#This Row],[Discount (%)]] -> 29 | S216: =Table1[[#This Row],[Profit]] -> 1055.86
A217: 60839616 | B217: 45237 | C217: South | D217: Sports | E217: 1787.05 | F217: 11 | G217: 19 | H217: 40.81 | L217: =TRIM(A217) -> 60839616 | M217: 45237 | N217: =PROPER(Table1[[#This Row],[Region]]) -> South | O217: =PROPER(Table1[[#This Row],[Product Category]]) -> Sports | P217: =ROUND(Table1[[#This Row],[Sales Amount]],1) -> 1787.1 | Q217: =Table1[[#This Row],[Quantity Sold]] -> 11 | R217: =Table1[[#This Row],[Discount (%)]] -> 19 | S217: =Table1[[#This Row],[Profit]] -> 40.81
A218: a65dfe8b | B218: 45238 | C218: West | D218: Furniture | E218: 901.68 | F218: 7 | G218: 48 | H218: 903.11 | L218: =TRIM(A218) -> a65dfe8b | M218: 45238 | N218: =PROPER(Table1[[#This Row],[Region]]) -> West | O218: =PROPER(Table1[[#This Row],[Product Category]]) -> Furniture | P218: =ROUND(Table1[[#This Row],[Sales Amount]],1) -> 901.7 | Q218: =Table1[[#This Row],[Quantity Sold]] -> 7 | R218: =Table1[[#This Row],[Discount (%)]] -> 48 | S218: =Table1[[#This Row],[Profit]] -> 903.11
A219: 850b0c26 | B219: 45239 | C219: North | D219: Electronics | E219: 2934.72 | F219: 20 | G219: 12 | H219: 528.02 | L219: =TRIM(A219) -> 850b0c26 | M219: 45239 | N219: =PROPER(Table1[[#This Row],[Region]]) -> North | O219: =PROPER(Table1[[#This Row],[Product Category]]) -> Electronics | P219: =ROUND(Table1[[#This Row],[Sales Amount]],1) -> 2934.7 | Q219: =Table1[[#This Row],[Quantity Sold]] -> 20 | R219: =Table1[[#This Row],[Discount (%)]] -> 12 | S219: =Table1[[#This Row],[Profit]] -> 528.02
A220: 21fd10ea | B220: 45240 | C220: West | D220: Groceries | E220: 1058.57 | F220: 6 | G220: 13 | H220: 697.72 | L220: =TRIM(A220) -> 21fd10ea | M220: 45240 | N220: =PROPER(Table1[[#This Row],[Region]]) -> West | O220: =PROPER(Table1[[#This Row],[Product Category]]) -> Groceries | P220: =ROUND(Table1[[#This Row],[Sales Amount]],1) -> 1058.6 | Q220: =Table1[[#This Row],[Quantity Sold]] -> 6 | R220: =Table1[[#This Row],[Discount (%)]] -> 13 | S220: =Table1[[#This Row],[Profit]] -> 697.72
A221: 8d90e130 | B221: 45241 | C221: East | D221: Furniture | E221: 3988.42 | F221: 36 | G221: 1 | H221: 1637.88 | L221: =TRIM(A221) -> 8d90e130 | M221: 45241 | N221: =PROPER(Table1[[#This Row],[Region]]) -> East | O221: =PROPER(Table1[[#This Row],[Product Category]]) -> Furniture | P221: =ROUND(Table1[[#This Row],[Sales Amount]],1) -> 3988.4 | Q221: =Table1[[#This Row],[Quantity Sold]] -> 36 | R221: =Table1[[#This Row],[Discount (%)]] -> 1 | S221: =Table1[[#This Row],[Profit]] -> 1637.88
A222: 41aee1e8 | B222: 45242 | C222: South | D222: Sports | E222: 2727.47 | F222: 35 | G222: 1 | H222: 1875.23 | L222: =TRIM(A222) -> 41aee1e8 | M222: 45242 | N222: =PROPER(Table1[[#This Row],[Region]]) -> South | O222: =PROPER(Table1[[#This Row],[Product Category]]) -> Sports | P222: =ROUND(Table1[[#This Row],[Sales Amount]],1) -> 2727.5 | Q222: =Table1[[#This Row],[Quantity Sold]] -> 35 | R222: =Table1[[#This Row],[Discount (%)]] -> 1 | S222: =Table1[[#This Row],[Profit]] -> 1875.23
A223: 2f562dc0 | B223: 45243 | C223: South | D223: Groceries | E223: 1765.49 | F223: 13 | G223: 24 | H223: 1951.72 | L223: =TRIM(A223) -> 2f562dc0 | M223: 45243 | N223: =PROPER(Table1[[#This Row],[Region]]) -> South | O223: =PROPER(Table1[[#This Row],[Product Category]]) -> Groceries | P223: =ROUND(Table1[[#This Row],[Sales Amount]],1) -> 1765.5 | Q223: =Table1[[#This Row],[Quantity Sold]] -> 13 | R223: =Table1[[#This Row],[Discount (%)]] -> 24 | S223: =Table1[[#This Row],[Profit]] -> 1951.72
A224: 1790f693 | B224: 45244 | C224: North | D224: Furniture | E224: 4383.76 | F224: 40 | G224: 21 | H224: 1013.33 | L224: =TRIM(A224) -> 1790f693 | M224: 45244 | N224: =PROPER(Table1[[#This Row],[Region]]) -> North | O224: =PROPER(Table1[[#This Row],[Product Category]]) -> Furniture | P224: =ROUND(Table1[[#This Row],[Sales Amount]],1) -> 4383.8 | Q224: =Table1[[#This Row],[Quantity Sold]] -> 40 | R224: =Table1[[#This Row],[Discount (%)]] -> 21 | S224: =Table1[[#This Row],[Profit]] -> 1013.33
A225: 1ad9d5e9 | B225: 45245 | C225: South | D225: Groceries | E225: 4240.64 | F225: 49 | G225: 14 | H225: 1765.62 | L225: =TRIM(A225) -> 1ad9d5e9 | M225: 45245 | N225: =PROPER(Table1[[#This Row],[Region]]) -> South | O225: =PROPER(Table1[[#This Row],[Product Category]]) -> Groceries | P225: =ROUND(Table1[[#This Row],[Sales Amount]],1) -> 4240.6 | Q225: =Table1[[#This Row],[Quantity Sold]] -> 49 | R225: =Table1[[#This Row],[Discount (%)]] -> 14 | S225: =Table1[[#This Row],[Profit]] -> 1765.62
A226: ae129571 | B226: 45246 | C226: South | D226: Furniture | E226: 273.84 | F226: 44 | G226: 29 | H226: 821 | L226: =TRIM(A226) -> ae129571 | M226: 45246 | N226: =PROPER(Table1[[#This Row],[Region]]) -> South | O226: =PROPER(Table1[[#This Row],[Product Category]]) -> Furniture | P226: =ROUND(Table1[[#This Row],[Sales Amount]],1) -> 273.8 | Q226: =Table1[[#This Row],[Quantity Sold]] -> 44 | R226: =Table1[[#This Row],[Discount (%)]] -> 29 | S226: =Table1[[#This Row],[Profit]] -> 821
A227: 79a06bc6 | B227: 45247 | C227: East | D227: Sports | E227: 152.53 | F227: 10 | G227: 16 | H227: 1958.8 | L227: =TRIM(A227) -> 79a06bc6 | M227: 45247 | N227: =PROPER(Table1[[#This Row],[Region]]) -> East | O227: =PROPER(Table1[[#This Row],[Product Category]]) -> Sports | P227: =ROUND(Table1[[#This Row],[Sales Amount]],1) -> 152.5 | Q227: =Table1[[#This Row],[Quantity Sold]] -> 10 | R227: =Table1[[#This Row],[Discount (%)]] -> 16 | S227: =Table1[[#This Row],[Profit]] -> 1958.8
A228: 65240ae3 | B228: 45248 | C228: West | D228: Groceries | E228: 1407.97 | F228: 26 | G228: 35 | H228: 978.17 | L228: =TRIM(A228) -> 65240ae3 | M228: 45248 | N228: =PROPER(Table1[[#This Row],[Region]]) -> West | O228: =PROPER(Table1[[#This Row],[Product Category]]) -> Groceries | P228: =ROUND(Table1[[#This Row],[Sales Amount]],1) -> 1408 | Q228: =Table1[[#This Row],[Quantity Sold]] -> 26 | R228: =Table1[[#This Row],[Discount (%)]] -> 35 | S228: =Table1[[#This Row],[Profit]] -> 978.17
A229: d4df366c | B229: 45249 | C229: West | D229: Furniture | E229: 4083.3 | F229: 22 | G229: 40 | H229: 1003.31 | L229: =TRIM(A229) -> d4df366c | M229: 45249 | N229: =PROPER(Table1[[#This Row],[Region]]) -> West | O229: =PROPER(Table1[[#This Row],[Product Category]]) -> Furniture | P229: =ROUND(Table1[[#This Row],[Sales Amount]],1) -> 4083.3 | Q229: =Table1[[#This Row],[Quantity Sold]] -> 22 | R229: =Table1[[#This Row],[Discount (%)]] -> 40 | S229: =Table1[[#This Row],[Profit]] -> 1003.31
... A271: d344a2c7 | B271: 45291 | C271: East | D271: Furniture | E271: 3012.88 | F271: 16 | G271: 16 | H271: 789.81 | L271: =TRIM(A271) -> d344a2c7 | M271: 45291 | N271: =PROPER(Table1[[#This Row],[Region]]) -> East | O271: =PROPER(Table1[[#This Row],[Product Category]]) -> Furniture | P271: =ROUND(Table1[[#This Row],[Sales Amount]],1) -> 3012.9 | Q271: =Table1[[#This Row],[Quantity Sold]] -> 16 | R271: =Table1[[#This Row],[Discount (%)]] -> 16 | S271: =Table1[[#This Row],[Profit]] -> 789.81
A272: 6.7765e+71 | B272: 45292 | C272: North | D272: Clothing | E272: 1877.37 | F272: 40 | G272: 46 | H272: 730.86 | L272: =TRIM(A272) -> 6.7765E+71 | M272: 45292 | N272: =PROPER(Table1[[#This Row],[Region]]) -> North | O272: =PROPER(Table1[[#This Row],[Product Category]]) -> Clothing | P272: =ROUND(Table1[[#This Row],[Sales Amount]],1) -> 1877.4 | Q272: =Table1[[#This Row],[Quantity Sold]] -> 40 | R272: =Table1[[#This Row],[Discount (%)]] -> 46 | S272: =Table1[[#This Row],[Profit]] -> 730.86
A273: 3cccf911 | B273: 45293 | C273: West | D273: Electronics | E273: 2634.24 | F273: 19 | G273: 35 | H273: 38.85 | L273: =TRIM(A273) -> 3cccf911 | M273: 45293 | N273: =PROPER(Table1[[#This Row],[Region]]) -> West | O273: =PROPER(Table1[[#This Row],[Product Category]]) -> Electronics | P273: =ROUND(Table1[[#This Row],[Sales Amount]],1) -> 2634.2 | Q273: =Table1[[#This Row],[Quantity Sold]] -> 19 | R273: =Table1[[#This Row],[Discount (%)]] -> 35 | S273: =Table1[[#This Row],[Profit]] -> 38.85
A274: 7fc85b77 | B274: 45294 | C274: East | D274: Sports | E274: 2112.39 | F274: 29 | G274: 15 | H274: 1063.37 | L274: =TRIM(A274) -> 7fc85b77 | M274: 45294 | N274: =PROPER(Table1[[#This Row],[Region]]) -> East | O274: =PROPER(Table1[[#This Row],[Product Category]]) -> Sports | P274: =ROUND(Table1[[#This Row],[Sales Amount]],1) -> 2112.4 | Q274: =Table1[[#This Row],[Quantity Sold]] -> 29 | R274: =Table1[[#This Row],[Discount (%)]] -> 15 | S274: =Table1[[#This Row],[Profit]] -> 1063.37
A275: 67786d7a | B275: 45295 | C275: North | D275: Groceries | E275: 1184.59 | F275: 10 | G275: 32 | H275: 1911.66 | L275: =TRIM(A275) -> 67786d7a | M275: 45295 | N275: =PROPER(Table1[[#This Row],[Region]]) -> North | O275: =PROPER(Table1[[#This Row],[Product Category]]) -> Groceries | P275: =ROUND(Table1[[#This Row],[Sales Amount]],1) -> 1184.6 | Q275: =Table1[[#This Row],[Quantity Sold]] -> 10 | R275: =Table1[[#This Row],[Discount (%)]] -> 32 | S275: =Table1[[#This Row],[Profit]] -> 1911.66
...

Sheet task 1
A1: order id | B1: Order Date | C1: Region | D1: Product Category | E1: Sales Amount | F1: Quantity Sold | G1: Discount % | H1: profit
A2: ab899d2f | B2: 45022 | C2: =PROPER(Table1[[#This Row],[Region]]) -> North | D2: =PROPER(Table1[[#This Row],[Product Category]]) -> Groceries | E2: =ROUND(Table1[[#This Row],[Sales Amount]],1) -> 859.3 | F2: =Table1[[#This Row],[Quantity Sold]] -> 44 | G2: =Table1[[#This Row],[Discount (%)]] -> 37 | H2: =Table1[[#This Row],[Profit]] -> 1653.87 | K2: Sorting and Filtering
A3: 73484eb1 | B3: 45023 | C3: =PROPER(Table1[[#This Row],[Region]]) -> West | D3: =PROPER(Table1[[#This Row],[Product Category]]) -> Groceries | E3: =ROUND(Table1[[#This Row],[Sales Amount]],1) -> 1546.8 | F3: =Table1[[#This Row],[Quantity Sold]] -> 23 | G3: =Table1[[#This Row],[Discount (%)]] -> 33 | H3: =Table1[[#This Row],[Profit]] -> 1932.71
A4: 19395924 | B4: 45024 | C4: =PROPER(Table1[[#This Row],[Region]]) -> East | D4: =PROPER(Table1[[#This Row],[Product Category]]) -> Groceries | E4: =ROUND(Table1[[#This Row],[Sales Amount]],1) -> 4703.6 | F4: =Table1[[#This Row],[Quantity Sold]] -> 31 | G4: =Table1[[#This Row],[Discount (%)]] -> 15 | H4: =Table1[[#This Row],[Profit]] -> 527.47
A5: b3fded3d | B5: 45025 | C5: =PROPER(Table1[[#This Row],[Region]]) -> East | D5: =PROPER(Table1[[#This Row],[Product Category]]) -> Groceries | E5: =ROUND(Table1[[#This Row],[Sales Amount]],1) -> 3377.2 | F5: =Table1[[#This Row],[Quantity Sold]] -> 47 | G5: =Table1[[#This Row],[Discount (%)]] -> 3 | H5: =Table1[[#This Row],[Profit]] -> 482.65
A6: 6e4bdd51 | B6: 45026 | C6: =PROPER(Table1[[#This Row],[Region]]) -> South | D6: =PROPER(Table1[[#This Row],[Product Category]]) -> Clothing | E6: =ROUND(Table1[[#This Row],[Sales Amount]],1) -> 3517.5 | F6: =Table1[[#This Row],[Quantity Sold]] -> 6 | G6: =Table1[[#This Row],[Discount (%)]] -> 28 | H6: =Table1[[#This Row],[Profit]] -> 748.72
A7: 21d88d69 | B7: 45027 | C7: =PROPER(Table1[[#This Row],[Region]]) -> East | D7: =PROPER(Table1[[#This Row],[Product Category]]) -> Furniture | E7: =ROUND(Table1[[#This Row],[Sales Amount]],1) -> 362.6 | F7: =Table1[[#This Row],[Quantity Sold]] -> 19 | G7: =Table1[[#This Row],[Discount (%)]] -> 50 | H7: =Table1[[#This Row],[Profit]] -> 314.71
A8: 9da2704d | B8: 45028 | C8: =PROPER(Table1[[#This Row],[Region]]) -> East | D8: =PROPER(Table1[[#This Row],[Product Category]]) -> Sports | E8: =ROUND(Table1[[#This Row],[Sales Amount]],1) -> 4811.2 | F8: =Table1[[#This Row],[Quantity Sold]] -> 22 | G8: =Table1[[#This Row],[Discount (%)]] -> 18 | H8: =Table1[[#This Row],[Profit]] -> 1372.89
A9: a1bd6815 | B9: 45029 | C9: =PROPER(Table1[[#This Row],[Region]]) -> West | D9: =PROPER(Table1[[#This Row],[Product Category]]) -> Electronics | E9: =ROUND(Table1[[#This Row],[Sales Amount]],1) -> 3565.2 | F9: =Table1[[#This Row],[Quantity Sold]] -> 22 | G9: =Table1[[#This Row],[Discount (%)]] -> 16 | H9: =Table1[[#This Row],[Profit]] -> 1437.3
A10: 0bbd51fc | B10: 45030 | C10: =PROPER(Table1[[#This Row],[Region]]) -> East | D10: =PROPER(Table1[[#This Row],[Product Category]]) -> Clothing | E10: =ROUND(Table1[[#This Row],[Sales Amount]],1) -> 3805.3 | F10: =Table1[[#This Row],[Quantity Sold]] -> 19 | G10: =Table1[[#This Row],[Discount (%)]] -> 3 | H10: =Table1[[#This Row],[Profit]] -> 1537.28
A11: 8bf7e4b3 | B11: 45031 | C11: =PROPER(Table1[[#This Row],[Region]]) -> South | D11: =PROPER(Table1[[#This Row],[Product Category]]) -> Clothing | E11: =ROUND(Table1[[#This Row],[Sales Amount]],1) -> 2178.7 | F11: =Table1[[#This Row],[Quantity Sold]] -> 15 | G11: =Table1[[#This Row],[Discount (%)]] -> 24 | H11: =Table1[[#This Row],[Profit]] -> 1696.65
A12: e6cf1255 | B12: 45032 | C12: =PROPER(Table1[[#This Row],[Region]]) -> West | D12: =PROPER(Table1[[#This Row],[Product Category]]) -> Groceries | E12: =ROUND(Table1[[#This Row],[Sales Amount]],1) -> 2844.9 | F12: =Table1[[#This Row],[Quantity Sold]] -> 34 | G12: =Table1[[#This Row],[Discount (%)]] -> 12 | H12: =Table1[[#This Row],[Profit]] -> 1166.39
A13: 3ba1fc5c | B13: 45033 | C13: =PROPER(Table1[[#This Row],[Region]]) -> West | D13: =PROPER(Table1[[#This Row],[Product Category]]) -> Electronics | E13: =ROUND(Table1[[#This Row],[Sales Amount]],1) -> 3600 | F13: =Table1[[#This Row],[Quantity Sold]] -> 10 | G13: =Table1[[#This Row],[Discount (%)]] -> 2 | H13: =Table1[[#This Row],[Profit]] -> 1632.75
A14: 388ff70d | B14: 45034 | C14: =PROPER(Table1[[#This Row],[Region]]) -> East | D14: =PROPER(Table1[[#This Row],[Product Category]]) -> Sports | E14: =ROUND(Table1[[#This Row],[Sales Amount]],1) -> 941.9 | F14: =Table1[[#This Row],[Quantity Sold]] -> 13 | G14: =Table1[[#This Row],[Discount (%)]] -> 28 | H14: =Table1[[#This Row],[Profit]] -> 646.49
A15: ce2e9002 | B15: 45035 | C15: =PROPER(Table1[[#This Row],[Region]]) -> South | D15: =PROPER(Table1[[#This Row],[Product Category]]) -> Sports | E15: =ROUND(Table1[[#This Row],[Sales Amount]],1) -> 3300.9 | F15: =Table1[[#This Row],[Quantity Sold]] -> 1 | G15: =Table1[[#This Row],[Discount (%)]] -> 48 | H15: =Table1[[#This Row],[Profit]] -> 86.9
A16: a4f9a338 | B16: 45036 | C16: =PROPER(Table1[[#This Row],[Region]]) -> East | D16: =PROPER(Table1[[#This Row],[Product Category]]) -> Groceries | E16: =ROUND(Table1[[#This Row],[Sales Amount]],1) -> 1081.6 | F16: =Table1[[#This Row],[Quantity Sold]] -> 4 | G16: =Table1[[#This Row],[Discount (%)]] -> 19 | H16: =Table1[[#This Row],[Profit]] -> 611.06
... A19: 35358e9c | B19: 45039 | C19: =PROPER(Table1[[#This Row],[Region]]) -> North | D19: =PROPER(Table1[[#This Row],[Product Category]]) -> Clothing | E19: =ROUND(Table1[[#This Row],[Sales Amount]],1) -> 2784.8 | F19: =Table1[[#This Row],[Quantity Sold]] -> 35 | G19: =Table1[[#This Row],[Discount (%)]] -> 40 | H19: =Table1[[#This Row],[Profit]] -> 999.6
A20: 31676338 | B20: 45040 | C20: =PROPER(Table1[[#This Row],[Region]]) -> South | D20: =PROPER(Table1[[#This Row],[Product Category]]) -> Clothing | E20: =ROUND(Table1[[#This Row],[Sales Amount]],1) -> 1083 | F20: =Table1[[#This Row],[Quantity Sold]] -> 8 | G20: =Table1[[#This Row],[Discount (%)]] -> 11 | H20: =Table1[[#This Row],[Profit]] -> 1604.19
A21: 05d72e20 | B21: 45041 | C21: =PROPER(Table1[[#This Row],[Region]]) -> East | D21: =PROPER(Table1[[#This Row],[Product Category]]) -> Clothing | E21: =ROUND(Table1[[#This Row],[Sales Amount]],1) -> 787.8 | F21: =Table1[[#This Row],[Quantity Sold]] -> 47 | G21: =Table1[[#This Row],[Discount (%)]] -> 18 | H21: =Table1[[#This Row],[Profit]] -> 1313.33
A22: 68dbe328 | B22: 45042 | C22: =PROPER(Table1[[#This Row],[Region]]) -> South | D22: =PROPER(Table1[[#This Row],[Product Category]]) -> Furniture | E22: =ROUND(Table1[[#This Row],[Sales Amount]],1) -> 312.7 | F22: =Table1[[#This Row],[Quantity Sold]] -> 36 | G22: =Table1[[#This Row],[Discount (%)]] -> 43 | H22: =Table1[[#This Row],[Profit]] -> 559.52
A23: 78d3f47b | B23: 45043 | C23: =PROPER(Table1[[#This Row],[Region]]) -> East | D23: =PROPER(Table1[[#This Row],[Product Category]]) -> Sports | E23: =ROUND(Table1[[#This Row],[Sales Amount]],1) -> 265.3 | F23: =Table1[[#This Row],[Quantity Sold]] -> 21 | G23: =Table1[[#This Row],[Discount (%)]] -> 36 | H23: =Table1[[#This Row],[Profit]] -> 595.91
A24: 9e4d1fe0 | B24: 45044 | C24: =PROPER(Table1[[#This Row],[Region]]) -> West | D24: =PROPER(Table1[[#This Row],[Product Category]]) -> Furniture | E24: =ROUND(Table1[[#This Row],[Sales Amount]],1) -> 1253.6 | F24: =Table1[[#This Row],[Quantity Sold]] -> 35 | G24: =Table1[[#This Row],[Discount (%)]] -> 14 | H24: =Table1[[#This Row],[Profit]] -> 1653.66
A25: 9215a70e | B25: 45045 | C25: =PROPER(Table1[[#This Row],[Region]]) -> West | D25: =PROPER(Table1[[#This Row],[Product Category]]) -> Clothing | E25: =ROUND(Table1[[#This Row],[Sales Amount]],1) -> 1874.1 | F25: =Table1[[#This Row],[Quantity Sold]] -> 28 | G25: =Table1[[#This Row],[Discount (%)]] -> 23 | H25: =Table1[[#This Row],[Profit]] -> 1783.26
A26: 54ca3433 | B26: 45046 | C26: =PROPER(Table1[[#This Row],[Region]]) -> East | D26: =PROPER(Table1[[#This Row],[Product Category]]) -> Clothing | E26: =ROUND(Table1[[#This Row],[Sales Amount]],1) -> 2561.7 | F26: =Table1[[#This Row],[Quantity Sold]] -> 44 | G26: =Table1[[#This Row],[Discount (%)]] -> 10 | H26: =Table1[[#This Row],[Profit]] -> 800.82
A27: 0ba75cc7 | B27: 45047 | C27: =PROPER(Table1[[#This Row],[Region]]) -> West | D27: =PROPER(Table1[[#This Row],[Product Category]]) -> Sports | E27: =ROUND(Table1[[#This Row],[Sales Amount]],1) -> 1960.7 | F27: =Table1[[#This Row],[Quantity Sold]] -> 50 | G27: =Table1[[#This Row],[Discount (%)]] -> 6 | H27: =Table1[[#This Row],[Profit]] -> 1530.61
A28: 601860b1 | B28: 45048 | C28: =PROPER(Table1[[#This Row],[Region]]) -> East | D28: =PROPER(Table1[[#This Row],[Product Category]]) -> Electronics | E28: =ROUND(Table1[[#This Row],[Sales Amount]],1) -> 2415.4 | F28: =Table1[[#This Row],[Quantity Sold]] -> 35 | G28: =Table1[[#This Row],[Discount (%)]] -> 14 | H28: =Table1[[#This Row],[Profit]] -> 335.57
A29: e393e106 | B29: 45049 | C29: =PROPER(Table1[[#This Row],[Region]]) -> East | D29: =PROPER(Table1[[#This Row],[Product Category]]) -> Electronics | E29: =ROUND(Table1[[#This Row],[Sales Amount]],1) -> 2284.2 | F29: =Table1[[#This Row],[Quantity Sold]] -> 8 | G29: =Table1[[#This Row],[Discount (%)]] -> 41 | H29: =Table1[[#This Row],[Profit]] -> 1866.59
A30: 7ab3d472 | B30: 45050 | C30: =PROPER(Table1[[#This Row],[Region]]) -> West | D30: =PROPER(Table1[[#This Row],[Product Category]]) -> Sports | E30: =ROUND(Table1[[#This Row],[Sales Amount]],1) -> 2118.6 | F30: =Table1[[#This Row],[Quantity Sold]] -> 29 | G30: =Table1[[#This Row],[Discount (%)]] -> 24 | H30: =Table1[[#This Row],[Profit]] -> 702.15
A31: 01d9b1ae | B31: 45051 | C31: =PROPER(Table1[[#This Row],[Region]]) -> South | D31: =PROPER(Table1[[#This Row],[Product Category]]) -> Groceries | E31: =ROUND(Table1[[#This Row],[Sales Amount]],1) -> 4803.6 | F31: =Table1[[#This Row],[Quantity Sold]] -> 11 | G31: =Table1[[#This Row],[Discount (%)]] -> 12 | H31: =Table1[[#This Row],[Profit]] -> 1086.74
A32: 20385cb6 | B32: 45052 | C32: =PROPER(Table1[[#This Row],[Region]]) -> North | D32: =PROPER(Table1[[#This Row],[Product Category]]) -> Groceries | E32: =ROUND(Table1[[#This Row],[Sales Amount]],1) -> 4297 | F32: =Table1[[#This Row],[Quantity Sold]] -> 17 | G32: =Table1[[#This Row],[Discount (%)]] -> 49 | H32: =Table1[[#This Row],[Profit]] -> 678.7
... A69: 92458ed3 | B69: 45089 | C69: =PROPER(Table1[[#This Row],[Region]]) -> North | D69: =PROPER(Table1[[#This Row],[Product Category]]) -> Furniture | E69: =ROUND(Table1[[#This Row],[Sales Amount]],1) -> 1356.6 | F69: =Table1[[#This Row],[Quantity Sold]] -> 2 | G69: =Table1[[#This Row],[Discount (%)]] -> 21 | H69: =Table1[[#This Row],[Profit]] -> 1213.34
A70: 76740552 | B70: 45090 | C70: =PROPER(Table1[[#This Row],[Region]]) -> South | D70: =PROPER(Table1[[#This Row],[Product Category]]) -> Electronics | E70: =ROUND(Table1[[#This Row],[Sales Amount]],1) -> 2905.8 | F70: =Table1[[#This Row],[Quantity Sold]] -> 20 | G70: =Table1[[#This Row],[Discount (%)]] -> 10 | H70: =Table1[[#This Row],[Profit]] -> 1417.43
A71: f92de80d | B71: 45091 | C71: =PROPER(Table1[[#This Row],[Region]]) -> South | D71: =PROPER(Table1[[#This Row],[Product Category]]) -> Furniture | E71: =ROUND(Table1[[#This Row],[Sales Amount]],1) -> 2065.4 | F71: =Table1[[#This Row],[Quantity Sold]] -> 22 | G71: =Table1[[#This Row],[Discount (%)]] -> 15 | H71: =Table1[[#This Row],[Profit]] -> 787.51
A72: 647ff51a | B72: 45092 | C72: =PROPER(Table1[[#This Row],[Region]]) -> East | D72: =PROPER(Table1[[#This Row],[Product Category]]) -> Clothing | E72: =ROUND(Table1[[#This Row],[Sales Amount]],1) -> 272.9 | F72: =Table1[[#This Row],[Quantity Sold]] -> 47 | G72: =Table1[[#This Row],[Discount (%)]] -> 29 | H72: =Table1[[#This Row],[Profit]] -> 1208.68
A73: f8548ec7 | B73: 45093 | C73: =PROPER(Table1[[#This Row],[Region]]) -> East | D73: =PROPER(Table1[[#This Row],[Product Category]]) -> Clothing | E73: =ROUND(Table1[[#This Row],[Sales Amount]],1) -> 4126.4 | F73: =Table1[[#This Row],[Quantity Sold]] -> 34 | G73: =Table1[[#This Row],[Discount (%)]] -> 13 | H73: =Table1[[#This Row],[Profit]] -> 1690.11
A74: 7855a0d2 | B74: 45094 | C74: =PROPER(Table1[[#This Row],[Region]]) -> North | D74: =PROPER(Table1[[#This Row],[Product Category]]) -> Furniture | E74: =ROUND(Table1[[#This Row],[Sales Amount]],1) -> 4204.6 | F74: =Table1[[#This Row],[Quantity Sold]] -> 49 | G74: =Table1[[#This Row],[Discount (%)]] -> 1 | H74: =Table1[[#This Row],[Profit]] -> 1534.82
A75: bf586512 | B75: 45095 | C75: =PROPER(Table1[[#This Row],[Region]]) -> West | D75: =PROPER(Table1[[#This Row],[Product Category]]) -> Clothing | E75: =ROUND(Table1[[#This Row],[Sales Amount]],1) -> 2131 | F75: =Table1[[#This Row],[Quantity Sold]] -> 7 | G75: =Table1[[#This Row],[Discount (%)]] -> 29 | H75: =Table1[[#This Row],[Profit]] -> 679.16
A76: deea1965 | B76: 45096 | C76: =PROPER(Table1[[#This Row],[Region]]) -> South | D76: =PROPER(Table1[[#This Row],[Product Category]]) -> Furniture | E76: =ROUND(Table1[[#This Row],[Sales Amount]],1) -> 1253.3 | F76: =Table1[[#This Row],[Quantity Sold]] -> 4 | G76: =Table1[[#This Row],[Discount (%)]] -> 48 | H76: =Table1[[#This Row],[Profit]] -> 317.33
A77: a0a8290f | B77: 45097 | C77: =PROPER(Table1[[#This Row],[Region]]) -> South | D77: =PROPER(Table1[[#This Row],[Product Category]]) -> Sports | E77: =ROUND(Table1[[#This Row],[Sales Amount]],1) -> 1050.3 | F77: =Table1[[#This Row],[Quantity Sold]] -> 30 | G77: =Table1[[#This Row],[Discount (%)]] -> 4 | H77: =Table1[[#This Row],[Profit]] -> 423.5
A78: 077a9429 | B78: 45098 | C78: =PROPER(Table1[[#This Row],[Region]]) -> North | D78: =PROPER(Table1[[#This Row],[Product Category]]) -> Furniture | E78: =ROUND(Table1[[#This Row],[Sales Amount]],1) -> 1269.1 | F78: =Table1[[#This Row],[Quantity Sold]] -> 3 | G78: =Table1[[#This Row],[Discount (%)]] -> 7 | H78: =Table1[[#This Row],[Profit]] -> 1819.88
A79: 8642940000 | B79: 45099 | C79: =PROPER(Table1[[#This Row],[Region]]) -> West | D79: =PROPER(Table1[[#This Row],[Product Category]]) -> Groceries | E79: =ROUND(Table1[[#This Row],[Sales Amount]],1) -> 4229.5 | F79: =Table1[[#This Row],[Quantity Sold]] -> 3 | G79: =Table1[[#This Row],[Discount (%)]] -> 9 | H79: =Table1[[#This Row],[Profit]] -> 11.29
A80: 41d1321a | B80: 45100 | C80: =PROPER(Table1[[#This Row],[Region]]) -> South | D80: =PROPER(Table1[[#This Row],[Product Category]]) -> Groceries | E80: =ROUND(Table1[[#This Row],[Sales Amount]],1) -> 3767.6 | F80: =Table1[[#This Row],[Quantity Sold]] -> 30 | G80: =Table1[[#This Row],[Discount (%)]] -> 41 | H80: =Table1[[#This Row],[Profit]] -> 1031.74
A81: 44afa795 | B81: 45101 | C81: =PROPER(Table1[[#This Row],[Region]]) -> West | D81: =PROPER(Table1[[#This Row],[Product Category]]) -> Sports | E81: =ROUND(Table1[[#This Row],[Sales Amount]],1) -> 640.9 | F81: =Table1[[#This Row],[Quantity Sold]] -> 19 | G81: =Table1[[#This Row],[Discount (%)]] -> 19 | H81: =Table1[[#This Row],[Profit]] -> 1148.62
A82: 8c329e53 | B82: 45102 | C82: =PROPER(Table1[[#This Row],[Region]]) -> North | D82: =PROPER(Table1[[#This Row],[Product Category]]) -> Furniture | E82: =ROUND(Table1[[#This Row],[Sales Amount]],1) -> 2958 | F82: =Table1[[#This Row],[Quantity Sold]] -> 4 | G82: =Table1[[#This Row],[Discount (%)]] -> 22 | H82: =Table1[[#This Row],[Profit]] -> 1968.62
A83: cdbba08a | B83: 45103 | C83: =PROPER(Table1[[#This Row],[Region]]) -> West | D83: =PROPER(Table1[[#This Row],[Product Category]]) -> Sports | E83: =ROUND(Table1[[#This Row],[Sales Amount]],1) -> 4049.5 | F83: =Table1[[#This Row],[Quantity Sold]] -> 5 | G83: =Table1[[#This Row],[Discount (%)]] -> 1 | H83: =Table1[[#This Row],[Profit]] -> 1151.9
A84: 4415c908 | B84: 45104 | C84: =PROPER(Table1[[#This Row],[Region]]) -> North | D84: =PROPER(Table1[[#This Row],[Product Category]]) -> Sports | E84: =ROUND(Table1[[#This Row],[Sales Amount]],1) -> 4155 | F84: =Table1[[#This Row],[Quantity Sold]] -> 32 | G84: =Table1[[#This Row],[Discount (%)]] -> 5 | H84: =Table1[[#This Row],[Profit]] -> 1637.7
A85: a9ac13d3 | B85: 45105 | C85: =PROPER(Table1[[#This Row],[Region]]) -> North | D85: =PROPER(Table1[[#This Row],[Product Category]]) -> Furniture | E85: =ROUND(Table1[[#This Row],[Sales Amount]],1) -> 2011.4 | F85: =Table1[[#This Row],[Quantity Sold]] -> 44 | G85: =Table1[[#This Row],[Discount (%)]] -> 10 | H85: =Table1[[#This Row],[Profit]] -> 829.69
A86: 5fbf219e | B86: 45106 | C86: =PROPER(Table1[[#This Row],[Region]]) -> West | D86: =PROPER(Table1[[#This Row],[Product Category]]) -> Electronics | E86: =ROUND(Table1[[#This Row],[Sales Amount]],1) -> 2365.2 | F86: =Table1[[#This Row],[Quantity Sold]] -> 10 | G86: =Table1[[#This Row],[Discount (%)]] -> 33 | H86: =Table1[[#This Row],[Profit]] -> 1970.1
A87: f3ba50cf | B87: 45107 | C87: =PROPER(Table1[[#This Row],[Region]]) -> South | D87: =PROPER(Table1[[#This Row],[Product Category]]) -> Clothing | E87: =ROUND(Table1[[#This Row],[Sales Amount]],1) -> 2615.8 | F87: =Table1[[#This Row],[Quantity Sold]] -> 31 | G87: =Table1[[#This Row],[Discount (%)]] -> 9 | H87: =Table1[[#This Row],[Profit]] -> 1276.87
A88: 88840b0f | B88: 45108 | C88: =PROPER(Table1[[#This Row],[Region]]) -> West | D88: =PROPER(Table1[[#This Row],[Product Category]]) -> Clothing | E88: =ROUND(Table1[[#This Row],[Sales Amount]],1) -> 4954.3 | F88: =Table1[[#This Row],[Quantity Sold]] -> 26 | G88: =Table1[[#This Row],[Discount (%)]] -> 43 | H88: =Table1[[#This Row],[Profit]] -> 1723.31
A89: 3dcffe93 | B89: 45109 | C89: =PROPER(Table1[[#This Row],[Region]]) -> North | D89: =PROPER(Table1[[#This Row],[Product Category]]) -> Clothing | E89: =ROUND(Table1[[#This Row],[Sales Amount]],1) -> 1969.4 | F89: =Table1[[#This Row],[Quantity Sold]] -> 27 | G89: =Table1[[#This Row],[Discount (%)]] -> 11 | H89: =Table1[[#This Row],[Profit]] -> 1532.9
A90: 745eb905 | B90: 45110 | C90: =PROPER(Table1[[#This Row],[Region]]) -> North | D90: =PROPER(Table1[[#This Row],[Product Category]]) -> Clothing | E90: =ROUND(Table1[[#This Row],[Sales Amount]],1) -> 2083 | F90: =Table1[[#This Row],[Quantity Sold]] -> 49 | G90: =Table1[[#This Row],[Discount (%)]] -> 11 | H90: =Table1[[#This Row],[Profit]] -> 105.26
A91: b8fca939 | B91: 45111 | C91: =PROPER(Table1[[#This Row],[Region]]) -> South | D91: =PROPER(Table1[[#This Row],[Product Category]]) -> Electronics | E91: =ROUND(Table1[[#This Row],[Sales Amount]],1) -> 4752.5 | F91: =Table1[[#This Row],[Quantity Sold]] -> 36 | G91: =Table1[[#This Row],[Discount (%)]] -> 8 | H91: =Table1[[#This Row],[Profit]] -> 1903.35
... A150: c41efe4c | B150: 45170 | C150: =PROPER(Table1[[#This Row],[Region]]) -> South | D150: =PROPER(Table1[[#This Row],[Product Category]]) -> Furniture | E150: =ROUND(Table1[[#This Row],[Sales Amount]],1) -> 1453.8 | F150: =Table1[[#This Row],[Quantity Sold]] -> 13 | G150: =Table1[[#This Row],[Discount (%)]] -> 16 | H150: =Table1[[#This Row],[Profit]] -> 385.22
A151: 61831599 | B151: 45171 | C151: =PROPER(Table1[[#This Row],[Region]]) -> East | D151: =PROPER(Table1[[#This Row],[Product Category]]) -> Sports | E151: =ROUND(Table1[[#This Row],[Sales Amount]],1) -> 4889.5 | F151: =Table1[[#This Row],[Quantity Sold]] -> 1 | G151: =Table1[[#This Row],[Discount (%)]] -> 20 | H151: =Table1[[#This Row],[Profit]] -> 807.13
A152: cf159d42 | B152: 45172 | C152: =PROPER(Table1[[#This Row],[Region]]) -> East | D152: =PROPER(Table1[[#This Row],[Product Category]]) -> Sports | E152: =ROUND(Table1[[#This Row],[Sales Amount]],1) -> 2548.9 | F152: =Table1[[#This Row],[Quantity Sold]] -> 3 | G152: =Table1[[#This Row],[Discount (%)]] -> 7 | H152: =Table1[[#This Row],[Profit]] -> 694.24
A153: ffa6342d | B153: 45173 | C153: =PROPER(Table1[[#This Row],[Region]]) -> South | D153: =PROPER(Table1[[#This Row],[Product Category]]) -> Clothing | E153: =ROUND(Table1[[#This Row],[Sales Amount]],1) -> 3804.8 | F153: =Table1[[#This Row],[Quantity Sold]] -> 31 | G153: =Table1[[#This Row],[Discount (%)]] -> 47 | H153: =Table1[[#This Row],[Profit]] -> 185.46
A154: 459360d4 | B154: 45174 | C154: =PROPER(Table1[[#This Row],[Region]]) -> East | D154: =PROPER(Table1[[#This Row],[Product Category]]) -> Groceries | E154: =ROUND(Table1[[#This Row],[Sales Amount]],1) -> 372.5 | F154: =Table1[[#This Row],[Quantity Sold]] -> 19 | G154: =Table1[[#This Row],[Discount (%)]] -> 13 | H154: =Table1[[#This Row],[Profit]] -> 232.82
A155: fdf4755a | B155: 45175 | C155: =PROPER(Table1[[#This Row],[Region]]) -> North | D155: =PROPER(Table1[[#This Row],[Product Category]]) -> Electronics | E155: =ROUND(Table1[[#This Row],[Sales Amount]],1) -> 2573.6 | F155: =Table1[[#This Row],[Quantity Sold]] -> 48 | G155: =Table1[[#This Row],[Discount (%)]] -> 36 | H155: =Table1[[#This Row],[Profit]] -> 1707.54
A156: 0a7d436c | B156: 45176 | C156: =PROPER(Table1[[#This Row],[Region]]) -> West | D156: =PROPER(Table1[[#This Row],[Product Category]]) -> Clothing | E156: =ROUND(Table1[[#This Row],[Sales Amount]],1) -> 1761.3 | F156: =Table1[[#This Row],[Quantity Sold]] -> 27 | G156: =Table1[[#This Row],[Discount (%)]] -> 12 | H156: =Table1[[#This Row],[Profit]] -> 492.03
A157: 3c1ab674 | B157: 45177 | C157: =PROPER(Table1[[#This Row],[Region]]) -> East | D157: =PROPER(Table1[[#This Row],[Product Category]]) -> Groceries | E157: =ROUND(Table1[[#This Row],[Sales Amount]],1) -> 4113.4 | F157: =Table1[[#This Row],[Quantity Sold]] -> 32 | G157: =Table1[[#This Row],[Discount (%)]] -> 3 | H157: =Table1[[#This Row],[Profit]] -> 1726.09
A158: 42b5d016 | B158: 45178 | C158: =PROPER(Table1[[#This Row],[Region]]) -> West | D158: =PROPER(Table1[[#This Row],[Product Category]]) -> Electronics | E158: =ROUND(Table1[[#This Row],[Sales Amount]],1) -> 202.2 | F158: =Table1[[#This Row],[Quantity Sold]] -> 6 | G158: =Table1[[#This Row],[Discount (%)]] -> 43 | H158: =Table1[[#This Row],[Profit]] -> 734.47
A159: 2616d5b4 | B159: 45179 | C159: =PROPER(Table1[[#This Row],[Region]]) -> North | D159: =PROPER(Table1[[#This Row],[Product Category]]) -> Sports | E159: =ROUND(Table1[[#This Row],[Sales Amount]],1) -> 4347.2 | F159: =Table1[[#This Row],[Quantity Sold]] -> 20 | G159: =Table1[[#This Row],[Discount (%)]] -> 34 | H159: =Table1[[#This Row],[Profit]] -> 1392.45
A160: 338c4722 | B160: 45180 | C160: =PROPER(Table1[[#This Row],[Region]]) -> West | D160: =PROPER(Table1[[#This Row],[Product Category]]) -> Clothing | E160: =ROUND(Table1[[#This Row],[Sales Amount]],1) -> 4992.8 | F160: =Table1[[#This Row],[Quantity Sold]] -> 2 | G160: =Table1[[#This Row],[Discount (%)]] -> 28 | H160: =Table1[[#This Row],[Profit]] -> 1468.94
A161: 6b1e9797 | B161: 45181 | C161: =PROPER(Table1[[#This Row],[Region]]) -> East | D161: =PROPER(Table1[[#This Row],[Product Category]]) -> Sports | E161: =ROUND(Table1[[#This Row],[Sales Amount]],1) -> 1387.2 | F161: =Table1[[#This Row],[Quantity Sold]] -> 28 | G161: =Table1[[#This Row],[Discount (%)]] -> 9 | H161: =Table1[[#This Row],[Profit]] -> 381.96
A162: 6e4fab78 | B162: 45182 | C162: =PROPER(Table1[[#This Row],[Region]]) -> North | D162: =PROPER(Table1[[#This Row],[Product Category]]) -> Clothing | E162: =ROUND(Table1[[#This Row],[Sales Amount]],1) -> 4642.9 | F162: =Table1[[#This Row],[Quantity Sold]] -> 35 | G162: =Table1[[#This Row],[Discount (%)]] -> 14 | H162: =Table1[[#This Row],[Profit]] -> 216.96
A163: 8944bc68 | B163: 45183 | C163: =PROPER(Table1[[#This Row],[Region]]) -> East | D163: =PROPER(Table1[[#This Row],[Product Category]]) -> Electronics | E163: =ROUND(Table1[[#This Row],[Sales Amount]],1) -> 4879.9 | F163: =Table1[[#This Row],[Quantity Sold]] -> 37 | G163: =Table1[[#This Row],[Discount (%)]] -> 5 | H163: =Table1[[#This Row],[Profit]] -> 1424.1
... A199: 1e18c00a | B199: 45219 | C199: =PROPER(Table1[[#This Row],[Region]]) -> North | D199: =PROPER(Table1[[#This Row],[Product Category]]) -> Clothing | E199: =ROUND(Table1[[#This Row],[Sales Amount]],1) -> 2925.3 | F199: =Table1[[#This Row],[Quantity Sold]] -> 24 | G199: =Table1[[#This Row],[Discount (%)]] -> 4 | H199: =Table1[[#This Row],[Profit]] -> 1753.87
A200: 37431000 | B200: 45220 | C200: =PROPER(Table1[[#This Row],[Region]]) -> South | D200: =PROPER(Table1[[#This Row],[Product Category]]) -> Groceries | E200: =ROUND(Table1[[#This Row],[Sales Amount]],1) -> 2454.7 | F200: =Table1[[#This Row],[Quantity Sold]] -> 10 | G200: =Table1[[#This Row],[Discount (%)]] -> 28 | H200: =Table1[[#This Row],[Profit]] -> 47.54
A201: af24551a | B201: 45221 | C201: =PROPER(Table1[[#This Row],[Region]]) -> North | D201: =PROPER(Table1[[#This Row],[Product Category]]) -> Groceries | E201: =ROUND(Table1[[#This Row],[Sales Amount]],1) -> 4662.5 | F201: =Table1[[#This Row],[Quantity Sold]] -> 13 | G201: =Table1[[#This Row],[Discount (%)]] -> 22 | H201: =Table1[[#This Row],[Profit]] -> 735.39
A202: 6b389c40 | B202: 45222 | C202: =PROPER(Table1[[#This Row],[Region]]) -> West | D202: =PROPER(Table1[[#This Row],[Product Category]]) -> Clothing | E202: =ROUND(Table1[[#This Row],[Sales Amount]],1) -> 2943.3 | F202: =Table1[[#This Row],[Quantity Sold]] -> 45 | G202: =Table1[[#This Row],[Discount (%)]] -> 8 | H202: =Table1[[#This Row],[Profit]] -> 571.04
A203: 7743bcd0 | B203: 45223 | C203: =PROPER(Table1[[#This Row],[Region]]) -> South | D203: =PROPER(Table1[[#This Row],[Product Category]]) -> Groceries | E203: =ROUND(Table1[[#This Row],[Sales Amount]],1) -> 2261.5 | F203: =Table1[[#This Row],[Quantity Sold]] -> 46 | G203: =Table1[[#This Row],[Discount (%)]] -> 39 | H203: =Table1[[#This Row],[Profit]] -> 373.45
A204: 84d09672 | B204: 45224 | C204: =PROPER(Table1[[#This Row],[Region]]) -> North | D204: =PROPER(Table1[[#This Row],[Product Category]]) -> Sports | E204: =ROUND(Table1[[#This Row],[Sales Amount]],1) -> 2679.5 | F204: =Table1[[#This Row],[Quantity Sold]] -> 36 | G204: =Table1[[#This Row],[Discount (%)]] -> 6 | H204: =Table1[[#This Row],[Profit]] -> 1471
A205: bd554f96 | B205: 45225 | C205: =PROPER(Table1[[#This Row],[Region]]) -> East | D205: =PROPER(Table1[[#This Row],[Product Category]]) -> Electronics | E205: =ROUND(Table1[[#This Row],[Sales Amount]],1) -> 1290.7 | F205: =Table1[[#This Row],[Quantity Sold]] -> 46 | G205: =Table1[[#This Row],[Discount (%)]] -> 8 | H205: =Table1[[#This Row],[Profit]] -> 147.39
A206: dee8766b | B206: 45226 | C206: =PROPER(Table1[[#This Row],[Region]]) -> East | D206: =PROPER(Table1[[#This Row],[Product Category]]) -> Groceries | E206: =ROUND(Table1[[#This Row],[Sales Amount]],1) -> 211.3 | F206: =Table1[[#This Row],[Quantity Sold]] -> 45 | G206: =Table1[[#This Row],[Discount (%)]] -> 48 | H206: =Table1[[#This Row],[Profit]] -> 1844.45
A207: 733628ca | B207: 45227 | C207: =PROPER(Table1[[#This Row],[Region]]) -> West | D207: =PROPER(Table1[[#This Row],[Product Category]]) -> Furniture | E207: =ROUND(Table1[[#This Row],[Sales Amount]],1) -> 3582.9 | F207: =Table1[[#This Row],[Quantity Sold]] -> 42 | G207: =Table1[[#This Row],[Discount (%)]] -> 48 | H207: =Table1[[#This Row],[Profit]] -> 1359.36
A208: 7101a707 | B208: 45228 | C208: =PROPER(Table1[[#This Row],[Region]]) -> West | D208: =PROPER(Table1[[#This Row],[Product Category]]) -> Furniture | E208: =ROUND(Table1[[#This Row],[Sales Amount]],1) -> 419.9 | F208: =Table1[[#This Row],[Quantity Sold]] -> 12 | G208: =Table1[[#This Row],[Discount (%)]] -> 22 | H208: =Table1[[#This Row],[Profit]] -> 1047.8
A209: 7349ac4e | B209: 45229 | C209: =PROPER(Table1[[#This Row],[Region]]) -> East | D209: =PROPER(Table1[[#This Row],[Product Category]]) -> Sports | E209: =ROUND(Table1[[#This Row],[Sales Amount]],1) -> 4422.2 | F209: =Table1[[#This Row],[Quantity Sold]] -> 14 | G209: =Table1[[#This Row],[Discount (%)]] -> 33 | H209: =Table1[[#This Row],[Profit]] -> 237.47
A210: fbe74fbe | B210: 45230 | C210: =PROPER(Table1[[#This Row],[Region]]) -> East | D210: =PROPER(Table1[[#This Row],[Product Category]]) -> Furniture | E210: =ROUND(Table1[[#This Row],[Sales Amount]],1) -> 3277.5 | F210: =Table1[[#This Row],[Quantity Sold]] -> 11 | G210: =Table1[[#This Row],[Discount (%)]] -> 2 | H210: =Table1[[#This Row],[Profit]] -> 379.92
A211: 6bde908c | B211: 45231 | C211: =PROPER(Table1[[#This Row],[Region]]) -> North | D211: =PROPER(Table1[[#This Row],[Product Category]]) -> Clothing | E211: =ROUND(Table1[[#This Row],[Sales Amount]],1) -> 4264.4 | F211: =Table1[[#This Row],[Quantity Sold]] -> 31 | G211: =Table1[[#This Row],[Discount (%)]] -> 24 | H211: =Table1[[#This Row],[Profit]] -> 1179.93
A212: 56a98641 | B212: 45232 | C212: =PROPER(Table1[[#This Row],[Region]]) -> South | D212: =PROPER(Table1[[#This Row],[Product Category]]) -> Furniture | E212: =ROUND(Table1[[#This Row],[Sales Amount]],1) -> 647.4 | F212: =Table1[[#This Row],[Quantity Sold]] -> 16 | G212: =Table1[[#This Row],[Discount (%)]] -> 34 | H212: =Table1[[#This Row],[Profit]] -> 1937.88
... A216: 2ecc60c1 | B216: 45236 | C216: =PROPER(Table1[[#This Row],[Region]]) -> South | D216: =PROPER(Table1[[#This Row],[Product Category]]) -> Clothing | E216: =ROUND(Table1[[#This Row],[Sales Amount]],1) -> 4559.2 | F216: =Table1[[#This Row],[Quantity Sold]] -> 14 | G216: =Table1[[#This Row],[Discount (%)]] -> 29 | H216: =Table1[[#This Row],[Profit]] -> 1055.86
A217: 60839616 | B217: 45237 | C217: =PROPER(Table1[[#This Row],[Region]]) -> South | D217: =PROPER(Table1[[#This Row],[Product Category]]) -> Sports | E217: =ROUND(Table1[[#This Row],[Sales Amount]],1) -> 1787.1 | F217: =Table1[[#This Row],[Quantity Sold]] -> 11 | G217: =Table1[[#This Row],[Discount (%)]] -> 19 | H217: =Table1[[#This Row],[Profit]] -> 40.81
A218: a65dfe8b | B218: 45238 | C218: =PROPER(Table1[[#This Row],[Region]]) -> West | D218: =PROPER(Table1[[#This Row],[Product Category]]) -> Furniture | E218: =ROUND(Table1[[#This Row],[Sales Amount]],1) -> 901.7 | F218: =Table1[[#This Row],[Quantity Sold]] -> 7 | G218: =Table1[[#This Row],[Discount (%)]] -> 48 | H218: =Table1[[#This Row],[Profit]] -> 903.11
A219: 850b0c26 | B219: 45239 | C219: =PROPER(Table1[[#This Row],[Region]]) -> North | D219: =PROPER(Table1[[#This Row],[Product Category]]) -> Electronics | E219: =ROUND(Table1[[#This Row],[Sales Amount]],1) -> 2934.7 | F219: =Table1[[#This Row],[Quantity Sold]] -> 20 | G219: =Table1[[#This Row],[Discount (%)]] -> 12 | H219: =Table1[[#This Row],[Profit]] -> 528.02
A220: 21fd10ea | B220: 45240 | C220: =PROPER(Table1[[#This Row],[Region]]) -> West | D220: =PROPER(Table1[[#This Row],[Product Category]]) -> Groceries | E220: =ROUND(Table1[[#This Row],[Sales Amount]],1) -> 1058.6 | F220: =Table1[[#This Row],[Quantity Sold]] -> 6 | G220: =Table1[[#This Row],[Discount (%)]] -> 13 | H220: =Table1[[#This Row],[Profit]] -> 697.72
A221: 8d90e130 | B221: 45241 | C221: =PROPER(Table1[[#This Row],[Region]]) -> East | D221: =PROPER(Table1[[#This Row],[Product Category]]) -> Furniture | E221: =ROUND(Table1[[#This Row],[Sales Amount]],1) -> 3988.4 | F221: =Table1[[#This Row],[Quantity Sold]] -> 36 | G221: =Table1[[#This Row],[Discount (%)]] -> 1 | H221: =Table1[[#This Row],[Profit]] -> 1637.88
A222: 41aee1e8 | B222: 45242 | C222: =PROPER(Table1[[#This Row],[Region]]) -> South | D222: =PROPER(Table1[[#This Row],[Product Category]]) -> Sports | E222: =ROUND(Table1[[#This Row],[Sales Amount]],1) -> 2727.5 | F222: =Table1[[#This Row],[Quantity Sold]] -> 35 | G222: =Table1[[#This Row],[Discount (%)]] -> 1 | H222: =Table1[[#This Row],[Profit]] -> 1875.23
A223: 2f562dc0 | B223: 45243 | C223: =PROPER(Table1[[#This Row],[Region]]) -> South | D223: =PROPER(Table1[[#This Row],[Product Category]]) -> Groceries | E223: =ROUND(Table1[[#This Row],[Sales Amount]],1) -> 1765.5 | F223: =Table1[[#This Row],[Quantity Sold]] -> 13 | G223: =Table1[[#This Row],[Discount (%)]] -> 24 | H223: =Table1[[#This Row],[Profit]] -> 1951.72
A224: 1790f693 | B224: 45244 | C224: =PROPER(Table1[[#This Row],[Region]]) -> North | D224: =PROPER(Table1[[#This Row],[Product Category]]) -> Furniture | E224: =ROUND(Table1[[#This Row],[Sales Amount]],1) -> 4383.8 | F224: =Table1[[#This Row],[Quantity Sold]] -> 40 | G224: =Table1[[#This Row],[Discount (%)]] -> 21 | H224: =Table1[[#This Row],[Profit]] -> 1013.33
A225: 1ad9d5e9 | B225: 45245 | C225: =PROPER(Table1[[#This Row],[Region]]) -> South | D225: =PROPER(Table1[[#This Row],[Product Category]]) -> Groceries | E225: =ROUND(Table1[[#This Row],[Sales Amount]],1) -> 4240.6 | F225: =Table1[[#This Row],[Quantity Sold]] -> 49 | G225: =Table1[[#This Row],[Discount (%)]] -> 14 | H225: =Table1[[#This Row],[Profit]] -> 1765.62
A226: ae129571 | B226: 45246 | C226: =PROPER(Table1[[#This Row],[Region]]) -> South | D226: =PROPER(Table1[[#This Row],[Product Category]]) -> Furniture | E226: =ROUND(Table1[[#This Row],[Sales Amount]],1) -> 273.8 | F226: =Table1[[#This Row],[Quantity Sold]] -> 44 | G226: =Table1[[#This Row],[Discount (%)]] -> 29 | H226: =Table1[[#This Row],[Profit]] -> 821
A227: 79a06bc6 | B227: 45247 | C227: =PROPER(Table1[[#This Row],[Region]]) -> East | D227: =PROPER(Table1[[#This Row],[Product Category]]) -> Sports | E227: =ROUND(Table1[[#This Row],[Sales Amount]],1) -> 152.5 | F227: =Table1[[#This Row],[Quantity Sold]] -> 10 | G227: =Table1[[#This Row],[Discount (%)]] -> 16 | H227: =Table1[[#This Row],[Profit]] -> 1958.8
A228: 65240ae3 | B228: 45248 | C228: =PROPER(Table1[[#This Row],[Region]]) -> West | D228: =PROPER(Table1[[#This Row],[Product Category]]) -> Groceries | E228: =ROUND(Table1[[#This Row],[Sales Amount]],1) -> 1408 | F228: =Table1[[#This Row],[Quantity Sold]] -> 26 | G228: =Table1[[#This Row],[Discount (%)]] -> 35 | H228: =Table1[[#This Row],[Profit]] -> 978.17
A229: d4df366c | B229: 45249 | C229: =PROPER(Table1[[#This Row],[Region]]) -> West | D229: =PROPER(Table1[[#This Row],[Product Category]]) -> Furniture | E229: =ROUND(Table1[[#This Row],[Sales Amount]],1) -> 4083.3 | F229: =Table1[[#This Row],[Quantity Sold]] -> 22 | G229: =Table1[[#This Row],[Discount (%)]] -> 40 | H229: =Table1[[#This Row],[Profit]] -> 1003.31
... A271: d344a2c7 | B271: 45291 | C271: =PROPER(Table1[[#This Row],[Region]]) -> East | D271: =PROPER(Table1[[#This Row],[Product Category]]) -> Furniture | E271: =ROUND(Table1[[#This Row],[Sales Amount]],1) -> 3012.9 | F271: =Table1[[#This Row],[Quantity Sold]] -> 16 | G271: =Table1[[#This Row],[Discount (%)]] -> 16 | H271: =Table1[[#This Row],[Profit]] -> 789.81
A272: 6.7765e+71 | B272: 45292 | C272: =PROPER(Table1[[#This Row],[Region]]) -> North | D272: =PROPER(Table1[[#This Row],[Product Category]]) -> Clothing | E272: =ROUND(Table1[[#This Row],[Sales Amount]],1) -> 1877.4 | F272: =Table1[[#This Row],[Quantity Sold]] -> 40 | G272: =Table1[[#This Row],[Discount (%)]] -> 46 | H272: =Table1[[#This Row],[Profit]] -> 730.86
A273: 3cccf911 | B273: 45293 | C273: =PROPER(Table1[[#This Row],[Region]]) -> West | D273: =PROPER(Table1[[#This Row],[Product Category]]) -> Electronics | E273: =ROUND(Table1[[#This Row],[Sales Amount]],1) -> 2634.2 | F273: =Table1[[#This Row],[Quantity Sold]] -> 19 | G273: =Table1[[#This Row],[Discount (%)]] -> 35 | H273: =Table1[[#This Row],[Profit]] -> 38.85
A274: 7fc85b77 | B274: 45294 | C274: =PROPER(Table1[[#This Row],[Region]]) -> East | D274: =PROPER(Table1[[#This Row],[Product Category]]) -> Sports | E274: =ROUND(Table1[[#This Row],[Sales Amount]],1) -> 2112.4 | F274: =Table1[[#This Row],[Quantity Sold]] -> 29 | G274: =Table1[[#This Row],[Discount (%)]] -> 15 | H274: =Table1[[#This Row],[Profit]] -> 1063.37
A275: 67786d7a | B275: 45295 | C275: =PROPER(Table1[[#This Row],[Region]]) -> North | D275: =PROPER(Table1[[#This Row],[Product Category]]) -> Groceries | E275: =ROUND(Table1[[#This Row],[Sales Amount]],1) -> 1184.6 | F275: =Table1[[#This Row],[Quantity Sold]] -> 10 | G275: =Table1[[#This Row],[Discount (%)]] -> 32 | H275: =Table1[[#This Row],[Profit]] -> 1911.66
...

Sheet task 2
A1: TRIM | G1: UPPER | L1: LOWER
B3: Trim region | C3: Trim product | G3: Upper region | H3: Upper product | L3: lower region | M3: lower product
B4: =TRIM(Table24[[#This Row],[Region]]) -> East | C4: =TRIM(Table24[[#This Row],[Product Category]]) -> Groceries | G4: =UPPER('task 1'!C2) -> NORTH | H4: =UPPER(C4) -> GROCERIES | L4: =LOWER(G4) -> north | M4: =LOWER(H4) -> groceries
B5: =TRIM(Table24[[#This Row],[Region]]) -> East | C5: =TRIM(Table24[[#This Row],[Product Category]]) -> Groceries | G5: =UPPER('task 1'!C3) -> WEST | H5: =UPPER(C5) -> GROCERIES | L5: =LOWER(G5) -> west | M5: =LOWER(H5) -> groceries
B6: =TRIM(Table24[[#This Row],[Region]]) -> South | C6: =TRIM(Table24[[#This Row],[Product Category]]) -> Clothing | G6: =UPPER('task 1'!C4) -> EAST | H6: =UPPER(C6) -> CLOTHING | L6: =LOWER(G6) -> east | M6: =LOWER(H6) -> clothing
B7: =TRIM(Table24[[#This Row],[Region]]) -> East | C7: =TRIM(Table24[[#This Row],[Product Category]]) -> Furniture | G7: =UPPER('task 1'!C5) -> EAST | H7: =UPPER(C7) -> FURNITURE | L7: =LOWER(G7) -> east | M7: =LOWER(H7) -> furniture
B8: =TRIM(Table24[[#This Row],[Region]]) -> East | C8: =TRIM(Table24[[#This Row],[Product Category]]) -> Sports | G8: =UPPER('task 1'!C6) -> SOUTH | H8: =UPPER(C8) -> SPORTS | L8: =LOWER(G8) -> south | M8: =LOWER(H8) -> sports
B9: =TRIM(Table24[[#This Row],[Region]]) -> West | C9: =TRIM(Table24[[#This Row],[Product Category]]) -> Electronics | G9: =UPPER('task 1'!C7) -> EAST | H9: =UPPER(C9) -> ELECTRONICS | L9: =LOWER(G9) -> east | M9: =LOWER(H9) -> electronics
B10: =TRIM(Table24[[#This Row],[Region]]) -> East | C10: =TRIM(Table24[[#This Row],[Product Category]]) -> Clothing | G10: =UPPER('task 1'!C8) -> EAST | H10: =UPPER(C10) -> CLOTHING | L10: =LOWER(G10) -> east | M10: =LOWER(H10) -> clothing
B11: =TRIM(Table24[[#This Row],[Region]]) -> South | C11: =TRIM(Table24[[#This Row],[Product Category]]) -> Clothing | G11: =UPPER('task 1'!C9) -> WEST | H11: =UPPER(C11) -> CLOTHING | L11: =LOWER(G11) -> west | M11: =LOWER(H11) -> clothing
B12: =TRIM(Table24[[#This Row],[Region]]) -> West | C12: =TRIM(Table24[[#This Row],[Product Category]]) -> Groceries | G12: =UPPER('task 1'!C10) -> EAST | H12: =UPPER(C12) -> GROCERIES | L12: =LOWER(G12) -> east | M12: =LOWER(H12) -> groceries
B13: =TRIM(Table24[[#This Row],[Region]]) -> West | C13: =TRIM(Table24[[#This Row],[Product Category]]) -> Electronics | G13: =UPPER('task 1'!C11) -> SOUTH | H13: =UPPER(C13) -> ELECTRONICS | L13: =LOWER(G13) -> south | M13: =LOWER(H13) -> electronics
B14: =TRIM(Table24[[#This Row],[Region]]) -> East | C14: =TRIM(Table24[[#This Row],[Product Category]]) -> Sports | G14: =UPPER('task 1'!C12) -> WEST | H14: =UPPER(C14) -> SPORTS | L14: =LOWER(G14) -> west | M14: =LOWER(H14) -> sports
B15: =TRIM(Table24[[#This Row],[Region]]) -> South | C15: =TRIM(Table24[[#This Row],[Product Category]]) -> Sports | G15: =UPPER('task 1'!C13) -> WEST | H15: =UPPER(C15) -> SPORTS | L15: =LOWER(G15) -> west | M15: =LOWER(H15) -> sports
... B3998: =TRIM(Table24[[#This Row],[Region]]) -> South | C3998: =TRIM(Table24[[#This Row],[Product Category]]) -> Electronics | G3998: =UPPER('task 1'!C3996) -> EAST | H3998: =UPPER(C3998) -> ELECTRONICS | L3998: =LOWER(G3998) -> east | M3998: =LOWER(H3998) -> electronics

Sheet task 3
A1: order id | B1: Order Date | C1: Region | D1: Product Category | E1: Sales Amount | F1: Quantity Sold | G1: Discount % | H1: profit
A2: ab899d2f | B2: 45022 | C2: =PROPER(Table1[[#This Row],[Region]]) -> North | D2: =PROPER(Table1[[#This Row],[Product Category]]) -> Groceries | E2: =ROUND(Table1[[#This Row],[Sales Amount]],1) -> 859.3 | F2: =Table1[[#This Row],[Quantity Sold]] -> 44 | G2: =Table1[[#This Row],[Discount (%)]] -> 37 | H2: =Table1[[#This Row],[Profit]] -> 1653.87
A3: 73484eb1 | B3: 45023 | C3: =PROPER(Table1[[#This Row],[Region]]) -> West | D3: =PROPER(Table1[[#This Row],[Product Category]]) -> Groceries | E3: =ROUND(Table1[[#This Row],[Sales Amount]],1) -> 1546.8 | F3: =Table1[[#This Row],[Quantity Sold]] -> 23 | G3: =Table1[[#This Row],[Discount (%)]] -> 33 | H3: =Table1[[#This Row],[Profit]] -> 1932.71 | M3: Average by region
A4: 19395924 | B4: 45024 | C4: =PROPER(Table1[[#This Row],[Region]]) -> East | D4: =PROPER(Table1[[#This Row],[Product Category]]) -> Groceries | E4: =ROUND(Table1[[#This Row],[Sales Amount]],1) -> 4703.6 | F4: =Table1[[#This Row],[Quantity Sold]] -> 31 | G4: =Table1[[#This Row],[Discount (%)]] -> 15 | H4: =Table1[[#This Row],[Profit]] -> 527.47
A5: b3fded3d | B5: 45025 | C5: =PROPER(Table1[[#This Row],[Region]]) -> East | D5: =PROPER(Table1[[#This Row],[Product Category]]) -> Groceries | E5: =ROUND(Table1[[#This Row],[Sales Amount]],1) -> 3377.2 | F5: =Table1[[#This Row],[Quantity Sold]] -> 47 | G5: =Table1[[#This Row],[Discount (%)]] -> 3 | H5: =Table1[[#This Row],[Profit]] -> 482.65 | M5: North | N5: =AVERAGEIF(Table246[Region],"North",Table246[Sales Amount]) -> 2572.97
A6: 6e4bdd51 | B6: 45026 | C6: =PROPER(Table1[[#This Row],[Region]]) -> South | D6: =PROPER(Table1[[#This Row],[Product Category]]) -> Clothing | E6: =ROUND(Table1[[#This Row],[Sales Amount]],1) -> 3517.5 | F6: =Table1[[#This Row],[Quantity Sold]] -> 6 | G6: =Table1[[#This Row],[Discount (%)]] -> 28 | H6: =Table1[[#This Row],[Profit]] -> 748.72 | M6: west | N6: =AVERAGEIF(Table246[Region],"West",Table246[Sales Amount]) -> 2537.6247
A7: 21d88d69 | B7: 45027 | C7: =PROPER(Table1[[#This Row],[Region]]) -> East | D7: =PROPER(Table1[[#This Row],[Product Category]]) -> Furniture | E7: =ROUND(Table1[[#This Row],[Sales Amount]],1) -> 362.6 | F7: =Table1[[#This Row],[Quantity Sold]] -> 19 | G7: =Table1[[#This Row],[Discount (%)]] -> 50 | H7: =Table1[[#This Row],[Profit]] -> 314.71 | M7: south | N7: =AVERAGEIF(Table246[Region],"South",Table246[Sales Amount]) -> 2494.4148
A8: 9da2704d | B8: 45028 | C8: =PROPER(Table1[[#This Row],[Region]]) -> East | D8: =PROPER(Table1[[#This Row],[Product Category]]) -> Sports | E8: =ROUND(Table1[[#This Row],[Sales Amount]],1) -> 4811.2 | F8: =Table1[[#This Row],[Quantity Sold]] -> 22 | G8: =Table1[[#This Row],[Discount (%)]] -> 18 | H8: =Table1[[#This Row],[Profit]] -> 1372.89 | M8: east | N8: =AVERAGEIF(Table246[Region],"East",Table246[Sales Amount]) -> 2507.2789
A9: a1bd6815 | B9: 45029 | C9: =PROPER(Table1[[#This Row],[Region]]) -> West | D9: =PROPER(Table1[[#This Row],[Product Category]]) -> Electronics | E9: =ROUND(Table1[[#This Row],[Sales Amount]],1) -> 3565.2 | F9: =Table1[[#This Row],[Quantity Sold]] -> 22 | G9: =Table1[[#This Row],[Discount (%)]] -> 16 | H9: =Table1[[#This Row],[Profit]] -> 1437.3
A10: 0bbd51fc | B10: 45030 | C10: =PROPER(Table1[[#This Row],[Region]]) -> East | D10: =PROPER(Table1[[#This Row],[Product Category]]) -> Clothing | E10: =ROUND(Table1[[#This Row],[Sales Amount]],1) -> 3805.3 | F10: =Table1[[#This Row],[Quantity Sold]] -> 19 | G10: =Table1[[#This Row],[Discount (%)]] -> 3 | H10: =Table1[[#This Row],[Profit]] -> 1537.28
A11: 8bf7e4b3 | B11: 45031 | C11: =PROPER(Table1[[#This Row],[Region]]) -> South | D11: =PROPER(Table1[[#This Row],[Product Category]]) -> Clothing | E11: =ROUND(Table1[[#This Row],[Sales Amount]],1) -> 2178.7 | F11: =Table1[[#This Row],[Quantity Sold]] -> 15 | G11: =Table1[[#This Row],[Discount (%)]] -> 24 | H11: =Table1[[#This Row],[Profit]] -> 1696.65
A12: e6cf1255 | B12: 45032 | C12: =PROPER(Table1[[#This Row],[Region]]) -> West | D12: =PROPER(Table1[[#This Row],[Product Category]]) -> Groceries | E12: =ROUND(Table1[[#This Row],[Sales Amount]],1) -> 2844.9 | F12: =Table1[[#This Row],[Quantity Sold]] -> 34 | G12: =Table1[[#This Row],[Discount (%)]] -> 12 | H12: =Table1[[#This Row],[Profit]] -> 1166.39
A13: 3ba1fc5c | B13: 45033 | C13: =PROPER(Table1[[#This Row],[Region]]) -> West | D13: =PROPER(Table1[[#This Row],[Product Category]]) -> Electronics | E13: =ROUND(Table1[[#This Row],[Sales Amount]],1) -> 3600 | F13: =Table1[[#This Row],[Quantity Sold]] -> 10 | G13: =Table1[[#This Row],[Discount (%)]] -> 2 | H13: =Table1[[#This Row],[Profit]] -> 1632.75
A14: 388ff70d | B14: 45034 | C14: =PROPER(Table1[[#This Row],[Region]]) -> East | D14: =PROPER(Table1[[#This Row],[Product Category]]) -> Sports | E14: =ROUND(Table1[[#This Row],[Sales Amount]],1) -> 941.9 | F14: =Table1[[#This Row],[Quantity Sold]] -> 13 | G14: =Table1[[#This Row],[Discount (%)]] -> 28 | H14: =Table1[[#This Row],[Profit]] -> 646.49
A15: ce2e9002 | B15: 45035 | C15: =PROPER(Table1[[#This Row],[Region]]) -> South | D15: =PROPER(Table1[[#This Row],[Product Category]]) -> Sports | E15: =ROUND(Table1[[#This Row],[Sales Amount]],1) -> 3300.9 | F15: =Table1[[#This Row],[Quantity Sold]] -> 1 | G15: =Table1[[#This Row],[Discount (%)]] -> 48 | H15: =Table1[[#This Row],[Profit]] -> 86.9
A16: a4f9a338 | B16: 45036 | C16: =PROPER(Table1[[#This Row],[Region]]) -> East | D16: =PROPER(Table1[[#This Row],[Product Category]]) -> Groceries | E16: =ROUND(Table1[[#This Row],[Sales Amount]],1) -> 1081.6 | F16: =Table1[[#This Row],[Quantity Sold]] -> 4 | G16: =Table1[[#This Row],[Discount (%)]] -> 19 | H16: =Table1[[#This Row],[Profit]] -> 611.06
A17: eadceaa8 | B17: 45037 | C17: =PROPER(Table1[[#This Row],[Region]]) -> East | D17: =PROPER(Table1[[#This Row],[Product Category]]) -> Furniture | E17: =ROUND(Table1[[#This Row],[Sales Amount]],1) -> 3455.7 | F17: =Table1[[#This Row],[Quantity Sold]] -> 39 | G17: =Table1[[#This Row],[Discount (%)]] -> 21 | H17: =Table1[[#This Row],[Profit]] -> 208.1
A18: ad7f9de9 | B18: 45038 | C18: =PROPER(Table1[[#This Row],[Region]]) -> South | D18: =PROPER(Table1[[#This Row],[Product Category]]) -> Groceries | E18: =ROUND(Table1[[#This Row],[Sales Amount]],1) -> 2381.5 | F18: =Table1[[#This Row],[Quantity Sold]] -> 16 | G18: =Table1[[#This Row],[Discount (%)]] -> 39 | H18: =Table1[[#This Row],[Profit]] -> 1083.96
A19: 35358e9c | B19: 45039 | C19: =PROPER(Table1[[#This Row],[Region]]) -> North | D19: =PROPER(Table1[[#This Row],[Product Category]]) -> Clothing | E19: =ROUND(Table1[[#This Row],[Sales Amount]],1) -> 2784.8 | F19: =Table1[[#This Row],[Quantity Sold]] -> 35 | G19: =Table1[[#This Row],[Discount (%)]] -> 40 | H19: =Table1[[#This Row],[Profit]] -> 999.6
A20: 31676338 | B20: 45040 | C20: =PROPER(Table1[[#This Row],[Region]]) -> South | D20: =PROPER(Table1[[#This Row],[Product Category]]) -> Clothing | E20: =ROUND(Table1[[#This Row],[Sales Amount]],1) -> 1083 | F20: =Table1[[#This Row],[Quantity Sold]] -> 8 | G20: =Table1[[#This Row],[Discount (%)]] -> 11 | H20: =Table1[[#This Row],[Profit]] -> 1604.19
A21: 05d72e20 | B21: 45041 | C21: =PROPER(Table1[[#This Row],[Region]]) -> East | D21: =PROPER(Table1[[#This Row],[Product Category]]) -> Clothing | E21: =ROUND(Table1[[#This Row],[Sales Amount]],1) -> 787.8 | F21: =Table1[[#This Row],[Quantity Sold]] -> 47 | G21: =Table1[[#This Row],[Discount (%)]] -> 18 | H21: =Table1[[#This Row],[Profit]] -> 1313.33
A22: 68dbe328 | B22: 45042 | C22: =PROPER(Table1[[#This Row],[Region]]) -> South | D22: =PROPER(Table1[[#This Row],[Product Category]]) -> Furniture | E22: =ROUND(Table1[[#This Row],[Sales Amount]],1) -> 312.7 | F22: =Table1[[#This Row],[Quantity Sold]] -> 36 | G22: =Table1[[#This Row],[Discount (%)]] -> 43 | H22: =Table1[[#This Row],[Profit]] -> 559.52
A23: 78d3f47b | B23: 45043 | C23: =PROPER(Table1[[#This Row],[Region]]) -> East | D23: =PROPER(Table1[[#This Row],[Product Category]]) -> Sports | E23: =ROUND(Table1[[#This Row],[Sales Amount]],1) -> 265.3 | F23: =Table1[[#This Row],[Quantity Sold]] -> 21 | G23: =Table1[[#This Row],[Discount (%)]] -> 36 | H23: =Table1[[#This Row],[Profit]] -> 595.91
A24: 9e4d1fe0 | B24: 45044 | C24: =PROPER(Table1[[#This Row],[Region]]) -> West | D24: =PROPER(Table1[[#This Row],[Product Category]]) -> Furniture | E24: =ROUND(Table1[[#This Row],[Sales Amount]],1) -> 1253.6 | F24: =Table1[[#This Row],[Quantity Sold]] -> 35 | G24: =Table1[[#This Row],[Discount (%)]] -> 14 | H24: =Table1[[#This Row],[Profit]] -> 1653.66
A25: 9215a70e | B25: 45045 | C25: =PROPER(Table1[[#This Row],[Region]]) -> West | D25: =PROPER(Table1[[#This Row],[Product Category]]) -> Clothing | E25: =ROUND(Table1[[#This Row],[Sales Amount]],1) -> 1874.1 | F25: =Table1[[#This Row],[Quantity Sold]] -> 28 | G25: =Table1[[#This Row],[Discount (%)]] -> 23 | H25: =Table1[[#This Row],[Profit]] -> 1783.26
A26: 54ca3433 | B26: 45046 | C26: =PROPER(Table1[[#This Row],[Region]]) -> East | D26: =PROPER(Table1[[#This Row],[Product Category]]) -> Clothing | E26: =ROUND(Table1[[#This Row],[Sales Amount]],1) -> 2561.7 | F26: =Table1[[#This Row],[Quantity Sold]] -> 44 | G26: =Table1[[#This Row],[Discount (%)]] -> 10 | H26: =Table1[[#This Row],[Profit]] -> 800.82
A27: 0ba75cc7 | B27: 45047 | C27: =PROPER(Table1[[#This Row],[Region]]) -> West | D27: =PROPER(Table1[[#This Row],[Product Category]]) -> Sports | E27: =ROUND(Table1[[#This Row],[Sales Amount]],1) -> 1960.7 | F27: =Table1[[#This Row],[Quantity Sold]] -> 50 | G27: =Table1[[#This Row],[Discount (%)]] -> 6 | H27: =Table1[[#This Row],[Profit]] -> 1530.61
A28: 601860b1 | B28: 45048 | C28: =PROPER(Table1[[#This Row],[Region]]) -> East | D28: =PROPER(Table1[[#This Row],[Product Category]]) -> Electronics | E28: =ROUND(Table1[[#This Row],[Sales Amount]],1) -> 2415.4 | F28: =Table1[[#This Row],[Quantity Sold]] -> 35 | G28: =Table1[[#This Row],[Discount (%)]] -> 14 | H28: =Table1[[#This Row],[Profit]] -> 335.57
A29: e393e106 | B29: 45049 | C29: =PROPER(Table1[[#This Row],[Region]]) -> East | D29: =PROPER(Table1[[#This Row],[Product Category]]) -> Electronics | E29: =ROUND(Table1[[#This Row],[Sales Amount]],1) -> 2284.2 | F29: =Table1[[#This Row],[Quantity Sold]] -> 8 | G29: =Table1[[#This Row],[Discount (%)]] -> 41 | H29: =Table1[[#This Row],[Profit]] -> 1866.59
A30: 7ab3d472 | B30: 45050 | C30: =PROPER(Table1[[#This Row],[Region]]) -> West | D30: =PROPER(Table1[[#This Row],[Product Category]]) -> Sports | E30: =ROUND(Table1[[#This Row],[Sales Amount]],1) -> 2118.6 | F30: =Table1[[#This Row],[Quantity Sold]] -> 29 | G30: =Table1[[#This Row],[Discount (%)]] -> 24 | H30: =Table1[[#This Row],[Profit]] -> 702.15
A31: 01d9b1ae | B31: 45051 | C31: =PROPER(Table1[[#This Row],[Region]]) -> South | D31: =PROPER(Table1[[#This Row],[Product Category]]) -> Groceries | E31: =ROUND(Table1[[#This Row],[Sales Amount]],1) -> 4803.6 | F31: =Table1[[#This Row],[Quantity Sold]] -> 11 | G31: =Table1[[#This Row],[Discount (%)]] -> 12 | H31: =Table1[[#This Row],[Profit]] -> 1086.74
A32: 20385cb6 | B32: 45052 | C32: =PROPER(Table1[[#This Row],[Region]]) -> North | D32: =PROPER(Table1[[#This Row],[Product Category]]) -> Groceries | E32: =ROUND(Table1[[#This Row],[Sales Amount]],1) -> 4297 | F32: =Table1[[#This Row],[Quantity Sold]] -> 17 | G32: =Table1[[#This Row],[Discount (%)]] -> 49 | H32: =Table1[[#This Row],[Profit]] -> 678.7
... A69: 92458ed3 | B69: 45089 | C69: =PROPER(Table1[[#This Row],[Region]]) -> North | D69: =PROPER(Table1[[#This Row],[Product Category]]) -> Furniture | E69: =ROUND(Table1[[#This Row],[Sales Amount]],1) -> 1356.6 | F69: =Table1[[#This Row],[Quantity Sold]] -> 2 | G69: =Table1[[#This Row],[Discount (%)]] -> 21 | H69: =Table1[[#This Row],[Profit]] -> 1213.34
A70: 76740552 | B70: 45090 | C70: =PROPER(Table1[[#This Row],[Region]]) -> South | D70: =PROPER(Table1[[#This Row],[Product Category]]) -> Electronics | E70: =ROUND(Table1[[#This Row],[Sales Amount]],1) -> 2905.8 | F70: =Table1[[#This Row],[Quantity Sold]] -> 20 | G70: =Table1[[#This Row],[Discount (%)]] -> 10 | H70: =Table1[[#This Row],[Profit]] -> 1417.43
A71: f92de80d | B71: 45091 | C71: =PROPER(Table1[[#This Row],[Region]]) -> South | D71: =PROPER(Table1[[#This Row],[Product Category]]) -> Furniture | E71: =ROUND(Table1[[#This Row],[Sales Amount]],1) -> 2065.4 | F71: =Table1[[#This Row],[Quantity Sold]] -> 22 | G71: =Table1[[#This Row],[Discount (%)]] -> 15 | H71: =Table1[[#This Row],[Profit]] -> 787.51
A72: 647ff51a | B72: 45092 | C72: =PROPER(Table1[[#This Row],[Region]]) -> East | D72: =PROPER(Table1[[#This Row],[Product Category]]) -> Clothing | E72: =ROUND(Table1[[#This Row],[Sales Amount]],1) -> 272.9 | F72: =Table1[[#This Row],[Quantity Sold]] -> 47 | G72: =Table1[[#This Row],[Discount (%)]] -> 29 | H72: =Table1[[#This Row],[Profit]] -> 1208.68
A73: f8548ec7 | B73: 45093 | C73: =PROPER(Table1[[#This Row],[Region]]) -> East | D73: =PROPER(Table1[[#This Row],[Product Category]]) -> Clothing | E73: =ROUND(Table1[[#This Row],[Sales Amount]],1) -> 4126.4 | F73: =Table1[[#This Row],[Quantity Sold]] -> 34 | G73: =Table1[[#This Row],[Discount (%)]] -> 13 | H73: =Table1[[#This Row],[Profit]] -> 1690.11
A74: 7855a0d2 | B74: 45094 | C74: =PROPER(Table1[[#This Row],[Region]]) -> North | D74: =PROPER(Table1[[#This Row],[Product Category]]) -> Furniture | E74: =ROUND(Table1[[#This Row],[Sales Amount]],1) -> 4204.6 | F74: =Table1[[#This Row],[Quantity Sold]] -> 49 | G74: =Table1[[#This Row],[Discount (%)]] -> 1 | H74: =Table1[[#This Row],[Profit]] -> 1534.82
A75: bf586512 | B75: 45095 | C75: =PROPER(Table1[[#This Row],[Region]]) -> West | D75: =PROPER(Table1[[#This Row],[Product Category]]) -> Clothing | E75: =ROUND(Table1[[#This Row],[Sales Amount]],1) -> 2131 | F75: =Table1[[#This Row],[Quantity Sold]] -> 7 | G75: =Table1[[#This Row],[Discount (%)]] -> 29 | H75: =Table1[[#This Row],[Profit]] -> 679.16
A76: deea1965 | B76: 45096 | C76: =PROPER(Table1[[#This Row],[Region]]) -> South | D76: =PROPER(Table1[[#This Row],[Product Category]]) -> Furniture | E76: =ROUND(Table1[[#This Row],[Sales Amount]],1) -> 1253.3 | F76: =Table1[[#This Row],[Quantity Sold]] -> 4 | G76: =Table1[[#This Row],[Discount (%)]] -> 48 | H76: =Table1[[#This Row],[Profit]] -> 317.33
A77: a0a8290f | B77: 45097 | C77: =PROPER(Table1[[#This Row],[Region]]) -> South | D77: =PROPER(Table1[[#This Row],[Product Category]]) -> Sports | E77: =ROUND(Table1[[#This Row],[Sales Amount]],1) -> 1050.3 | F77: =Table1[[#This Row],[Quantity Sold]] -> 30 | G77: =Table1[[#This Row],[Discount (%)]] -> 4 | H77: =Table1[[#This Row],[Profit]] -> 423.5
A78: 077a9429 | B78: 45098 | C78: =PROPER(Table1[[#This Row],[Region]]) -> North | D78: =PROPER(Table1[[#This Row],[Product Category]]) -> Furniture | E78: =ROUND(Table1[[#This Row],[Sales Amount]],1) -> 1269.1 | F78: =Table1[[#This Row],[Quantity Sold]] -> 3 | G78: =Table1[[#This Row],[Discount (%)]] -> 7 | H78: =Table1[[#This Row],[Profit]] -> 1819.88
A79: 8642940000 | B79: 45099 | C79: =PROPER(Table1[[#This Row],[Region]]) -> West | D79: =PROPER(Table1[[#This Row],[Product Category]]) -> Groceries | E79: =ROUND(Table1[[#This Row],[Sales Amount]],1) -> 4229.5 | F79: =Table1[[#This Row],[Quantity Sold]] -> 3 | G79: =Table1[[#This Row],[Discount (%)]] -> 9 | H79: =Table1[[#This Row],[Profit]] -> 11.29
A80: 41d1321a | B80: 45100 | C80: =PROPER(Table1[[#This Row],[Region]]) -> South | D80: =PROPER(Table1[[#This Row],[Product Category]]) -> Groceries | E80: =ROUND(Table1[[#This Row],[Sales Amount]],1) -> 3767.6 | F80: =Table1[[#This Row],[Quantity Sold]] -> 30 | G80: =Table1[[#This Row],[Discount (%)]] -> 41 | H80: =Table1[[#This Row],[Profit]] -> 1031.74
A81: 44afa795 | B81: 45101 | C81: =PROPER(Table1[[#This Row],[Region]]) -> West | D81: =PROPER(Table1[[#This Row],[Product Category]]) -> Sports | E81: =ROUND(Table1[[#This Row],[Sales Amount]],1) -> 640.9 | F81: =Table1[[#This Row],[Quantity Sold]] -> 19 | G81: =Table1[[#This Row],[Discount (%)]] -> 19 | H81: =Table1[[#This Row],[Profit]] -> 1148.62
A82: 8c329e53 | B82: 45102 | C82: =PROPER(Table1[[#This Row],[Region]]) -> North | D82: =PROPER(Table1[[#This Row],[Product Category]]) -> Furniture | E82: =ROUND(Table1[[#This Row],[Sales Amount]],1) -> 2958 | F82: =Table1[[#This Row],[Quantity Sold]] -> 4 | G82: =Table1[[#This Row],[Discount (%)]] -> 22 | H82: =Table1[[#This Row],[Profit]] -> 1968.62
A83: cdbba08a | B83: 45103 | C83: =PROPER(Table1[[#This Row],[Region]]) -> West | D83: =PROPER(Table1[[#This Row],[Product Category]]) -> Sports | E83: =ROUND(Table1[[#This Row],[Sales Amount]],1) -> 4049.5 | F83: =Table1[[#This Row],[Quantity Sold]] -> 5 | G83: =Table1[[#This Row],[Discount (%)]] -> 1 | H83: =Table1[[#This Row],[Profit]] -> 1151.9
A84: 4415c908 | B84: 45104 | C84: =PROPER(Table1[[#This Row],[Region]]) -> North | D84: =PROPER(Table1[[#This Row],[Product Category]]) -> Sports | E84: =ROUND(Table1[[#This Row],[Sales Amount]],1) -> 4155 | F84: =Table1[[#This Row],[Quantity Sold]] -> 32 | G84: =Table1[[#This Row],[Discount (%)]] -> 5 | H84: =Table1[[#This Row],[Profit]] -> 1637.7
A85: a9ac13d3 | B85: 45105 | C85: =PROPER(Table1[[#This Row],[Region]]) -> North | D85: =PROPER(Table1[[#This Row],[Product Category]]) -> Furniture | E85: =ROUND(Table1[[#This Row],[Sales Amount]],1) -> 2011.4 | F85: =Table1[[#This Row],[Quantity Sold]] -> 44 | G85: =Table1[[#This Row],[Discount (%)]] -> 10 | H85: =Table1[[#This Row],[Profit]] -> 829.69
A86: 5fbf219e | B86: 45106 | C86: =PROPER(Table1[[#This Row],[Region]]) -> West | D86: =PROPER(Table1[[#This Row],[Product Category]]) -> Electronics | E86: =ROUND(Table1[[#This Row],[Sales Amount]],1) -> 2365.2 | F86: =Table1[[#This Row],[Quantity Sold]] -> 10 | G86: =Table1[[#This Row],[Discount (%)]] -> 33 | H86: =Table1[[#This Row],[Profit]] -> 1970.1
A87: f3ba50cf | B87: 45107 | C87: =PROPER(Table1[[#This Row],[Region]]) -> South | D87: =PROPER(Table1[[#This Row],[Product Category]]) -> Clothing | E87: =ROUND(Table1[[#This Row],[Sales Amount]],1) -> 2615.8 | F87: =Table1[[#This Row],[Quantity Sold]] -> 31 | G87: =Table1[[#This Row],[Discount (%)]] -> 9 | H87: =Table1[[#This Row],[Profit]] -> 1276.87
A88: 88840b0f | B88: 45108 | C88: =PROPER(Table1[[#This Row],[Region]]) -> West | D88: =PROPER(Table1[[#This Row],[Product Category]]) -> Clothing | E88: =ROUND(Table1[[#This Row],[Sales Amount]],1) -> 4954.3 | F88: =Table1[[#This Row],[Quantity Sold]] -> 26 | G88: =Table1[[#This Row],[Discount (%)]] -> 43 | H88: =Table1[[#This Row],[Profit]] -> 1723.31
A89: 3dcffe93 | B89: 45109 | C89: =PROPER(Table1[[#This Row],[Region]]) -> North | D89: =PROPER(Table1[[#This Row],[Product Category]]) -> Clothing | E89: =ROUND(Table1[[#This Row],[Sales Amount]],1) -> 1969.4 | F89: =Table1[[#This Row],[Quantity Sold]] -> 27 | G89: =Table1[[#This Row],[Discount (%)]] -> 11 | H89: =Table1[[#This Row],[Profit]] -> 1532.9
A90: 745eb905 | B90: 45110 | C90: =PROPER(Table1[[#This Row],[Region]]) -> North | D90: =PROPER(Table1[[#This Row],[Product Category]]) -> Clothing | E90: =ROUND(Table1[[#This Row],[Sales Amount]],1) -> 2083 | F90: =Table1[[#This Row],[Quantity Sold]] -> 49 | G90: =Table1[[#This Row],[Discount (%)]] -> 11 | H90: =Table1[[#This Row],[Profit]] -> 105.26
A91: b8fca939 | B91: 45111 | C91: =PROPER(Table1[[#This Row],[Region]]) -> South | D91: =PROPER(Table1[[#This Row],[Product Category]]) -> Electronics | E91: =ROUND(Table1[[#This Row],[Sales Amount]],1) -> 4752.5 | F91: =Table1[[#This Row],[Quantity Sold]] -> 36 | G91: =Table1[[#This Row],[Discount (%)]] -> 8 | H91: =Table1[[#This Row],[Profit]] -> 1903.35
... A150: c41efe4c | B150: 45170 | C150: =PROPER(Table1[[#This Row],[Region]]) -> South | D150: =PROPER(Table1[[#This Row],[Product Category]]) -> Furniture | E150: =ROUND(Table1[[#This Row],[Sales Amount]],1) -> 1453.8 | F150: =Table1[[#This Row],[Quantity Sold]] -> 13 | G150: =Table1[[#This Row],[Discount (%)]] -> 16 | H150: =Table1[[#This Row],[Profit]] -> 385.22
A151: 61831599 | B151: 45171 | C151: =PROPER(Table1[[#This Row],[Region]]) -> East | D151: =PROPER(Table1[[#This Row],[Product Category]]) -> Sports | E151: =ROUND(Table1[[#This Row],[Sales Amount]],1) -> 4889.5 | F151: =Table1[[#This Row],[Quantity Sold]] -> 1 | G151: =Table1[[#This Row],[Discount (%)]] -> 20 | H151: =Table1[[#This Row],[Profit]] -> 807.13
A152: cf159d42 | B152: 45172 | C152: =PROPER(Table1[[#This Row],[Region]]) -> East | D152: =PROPER(Table1[[#This Row],[Product Category]]) -> Sports | E152: =ROUND(Table1[[#This Row],[Sales Amount]],1) -> 2548.9 | F152: =Table1[[#This Row],[Quantity Sold]] -> 3 | G152: =Table1[[#This Row],[Discount (%)]] -> 7 | H152: =Table1[[#This Row],[Profit]] -> 694.24
A153: ffa6342d | B153: 45173 | C153: =PROPER(Table1[[#This Row],[Region]]) -> South | D153: =PROPER(Table1[[#This Row],[Product Category]]) -> Clothing | E153: =ROUND(Table1[[#This Row],[Sales Amount]],1) -> 3804.8 | F153: =Table1[[#This Row],[Quantity Sold]] -> 31 | G153: =Table1[[#This Row],[Discount (%)]] -> 47 | H153: =Table1[[#This Row],[Profit]] -> 185.46
A154: 459360d4 | B154: 45174 | C154: =PROPER(Table1[[#This Row],[Region]]) -> East | D154: =PROPER(Table1[[#This Row],[Product Category]]) -> Groceries | E154: =ROUND(Table1[[#This Row],[Sales Amount]],1) -> 372.5 | F154: =Table1[[#This Row],[Quantity Sold]] -> 19 | G154: =Table1[[#This Row],[Discount (%)]] -> 13 | H154: =Table1[[#This Row],[Profit]] -> 232.82
A155: fdf4755a | B155: 45175 | C155: =PROPER(Table1[[#This Row],[Region]]) -> North | D155: =PROPER(Table1[[#This Row],[Product Category]]) -> Electronics | E155: =ROUND(Table1[[#This Row],[Sales Amount]],1) -> 2573.6 | F155: =Table1[[#This Row],[Quantity Sold]] -> 48 | G155: =Table1[[#This Row],[Discount (%)]] -> 36 | H155: =Table1[[#This Row],[Profit]] -> 1707.54
A156: 0a7d436c | B156: 45176 | C156: =PROPER(Table1[[#This Row],[Region]]) -> West | D156: =PROPER(Table1[[#This Row],[Product Category]]) -> Clothing | E156: =ROUND(Table1[[#This Row],[Sales Amount]],1) -> 1761.3 | F156: =Table1[[#This Row],[Quantity Sold]] -> 27 | G156: =Table1[[#This Row],[Discount (%)]] -> 12 | H156: =Table1[[#This Row],[Profit]] -> 492.03
A157: 3c1ab674 | B157: 45177 | C157: =PROPER(Table1[[#This Row],[Region]]) -> East | D157: =PROPER(Table1[[#This Row],[Product Category]]) -> Groceries | E157: =ROUND(Table1[[#This Row],[Sales Amount]],1) -> 4113.4 | F157: =Table1[[#This Row],[Quantity Sold]] -> 32 | G157: =Table1[[#This Row],[Discount (%)]] -> 3 | H157: =Table1[[#This Row],[Profit]] -> 1726.09
A158: 42b5d016 | B158: 45178 | C158: =PROPER(Table1[[#This Row],[Region]]) -> West | D158: =PROPER(Table1[[#This Row],[Product Category]]) -> Electronics | E158: =ROUND(Table1[[#This Row],[Sales Amount]],1) -> 202.2 | F158: =Table1[[#This Row],[Quantity Sold]] -> 6 | G158: =Table1[[#This Row],[Discount (%)]] -> 43 | H158: =Table1[[#This Row],[Profit]] -> 734.47
A159: 2616d5b4 | B159: 45179 | C159: =PROPER(Table1[[#This Row],[Region]]) -> North | D159: =PROPER(Table1[[#This Row],[Product Category]]) -> Sports | E159: =ROUND(Table1[[#This Row],[Sales Amount]],1) -> 4347.2 | F159: =Table1[[#This Row],[Quantity Sold]] -> 20 | G159: =Table1[[#This Row],[Discount (%)]] -> 34 | H159: =Table1[[#This Row],[Profit]] -> 1392.45
A160: 338c4722 | B160: 45180 | C160: =PROPER(Table1[[#This Row],[Region]]) -> West | D160: =PROPER(Table1[[#This Row],[Product Category]]) -> Clothing | E160: =ROUND(Table1[[#This Row],[Sales Amount]],1) -> 4992.8 | F160: =Table1[[#This Row],[Quantity Sold]] -> 2 | G160: =Table1[[#This Row],[Discount (%)]] -> 28 | H160: =Table1[[#This Row],[Profit]] -> 1468.94
A161: 6b1e9797 | B161: 45181 | C161: =PROPER(Table1[[#This Row],[Region]]) -> East | D161: =PROPER(Table1[[#This Row],[Product Category]]) -> Sports | E161: =ROUND(Table1[[#This Row],[Sales Amount]],1) -> 1387.2 | F161: =Table1[[#This Row],[Quantity Sold]] -> 28 | G161: =Table1[[#This Row],[Discount (%)]] -> 9 | H161: =Table1[[#This Row],[Profit]] -> 381.96
A162: 6e4fab78 | B162: 45182 | C162: =PROPER(Table1[[#This Row],[Region]]) -> North | D162: =PROPER(Table1[[#This Row],[Product Category]]) -> Clothing | E162: =ROUND(Table1[[#This Row],[Sales Amount]],1) -> 4642.9 | F162: =Table1[[#This Row],[Quantity Sold]] -> 35 | G162: =Table1[[#This Row],[Discount (%)]] -> 14 | H162: =Table1[[#This Row],[Profit]] -> 216.96
A163: 8944bc68 | B163: 45183 | C163: =PROPER(Table1[[#This Row],[Region]]) -> East | D163: =PROPER(Table1[[#This Row],[Product Category]]) -> Electronics | E163: =ROUND(Table1[[#This Row],[Sales Amount]],1) -> 4879.9 | F163: =Table1[[#This Row],[Quantity Sold]] -> 37 | G163: =Table1[[#This Row],[Discount (%)]] -> 5 | H163: =Table1[[#This Row],[Profit]] -> 1424.1
... A199: 1e18c00a | B199: 45219 | C199: =PROPER(Table1[[#This Row],[Region]]) -> North | D199: =PROPER(Table1[[#This Row],[Product Category]]) -> Clothing | E199: =ROUND(Table1[[#This Row],[Sales Amount]],1) -> 2925.3 | F199: =Table1[[#This Row],[Quantity Sold]] -> 24 | G199: =Table1[[#This Row],[Discount (%)]] -> 4 | H199: =Table1[[#This Row],[Profit]] -> 1753.87
A200: 37431000 | B200: 45220 | C200: =PROPER(Table1[[#This Row],[Region]]) -> South | D200: =PROPER(Table1[[#This Row],[Product Category]]) -> Groceries | E200: =ROUND(Table1[[#This Row],[Sales Amount]],1) -> 2454.7 | F200: =Table1[[#This Row],[Quantity Sold]] -> 10 | G200: =Table1[[#This Row],[Discount (%)]] -> 28 | H200: =Table1[[#This Row],[Profit]] -> 47.54
A201: af24551a | B201: 45221 | C201: =PROPER(Table1[[#This Row],[Region]]) -> North | D201: =PROPER(Table1[[#This Row],[Product Category]]) -> Groceries | E201: =ROUND(Table1[[#This Row],[Sales Amount]],1) -> 4662.5 | F201: =Table1[[#This Row],[Quantity Sold]] -> 13 | G201: =Table1[[#This Row],[Discount (%)]] -> 22 | H201: =Table1[[#This Row],[Profit]] -> 735.39
A202: 6b389c40 | B202: 45222 | C202: =PROPER(Table1[[#This Row],[Region]]) -> West | D202: =PROPER(Table1[[#This Row],[Product Category]]) -> Clothing | E202: =ROUND(Table1[[#This Row],[Sales Amount]],1) -> 2943.3 | F202: =Table1[[#This Row],[Quantity Sold]] -> 45 | G202: =Table1[[#This Row],[Discount (%)]] -> 8 | H202: =Table1[[#This Row],[Profit]] -> 571.04
A203: 7743bcd0 | B203: 45223 | C203: =PROPER(Table1[[#This Row],[Region]]) -> South | D203: =PROPER(Table1[[#This Row],[Product Category]]) -> Groceries | E203: =ROUND(Table1[[#This Row],[Sales Amount]],1) -> 2261.5 | F203: =Table1[[#This Row],[Quantity Sold]] -> 46 | G203: =Table1[[#This Row],[Discount (%)]] -> 39 | H203: =Table1[[#This Row],[Profit]] -> 373.45
A204: 84d09672 | B204: 45224 | C204: =PROPER(Table1[[#This Row],[Region]]) -> North | D204: =PROPER(Table1[[#This Row],[Product Category]]) -> Sports | E204: =ROUND(Table1[[#This Row],[Sales Amount]],1) -> 2679.5 | F204: =Table1[[#This Row],[Quantity Sold]] -> 36 | G204: =Table1[[#This Row],[Discount (%)]] -> 6 | H204: =Table1[[#This Row],[Profit]] -> 1471
A205: bd554f96 | B205: 45225 | C205: =PROPER(Table1[[#This Row],[Region]]) -> East | D205: =PROPER(Table1[[#This Row],[Product Category]]) -> Electronics | E205: =ROUND(Table1[[#This Row],[Sales Amount]],1) -> 1290.7 | F205: =Table1[[#This Row],[Quantity Sold]] -> 46 | G205: =Table1[[#This Row],[Discount (%)]] -> 8 | H205: =Table1[[#This Row],[Profit]] -> 147.39
A206: dee8766b | B206: 45226 | C206: =PROPER(Table1[[#This Row],[Region]]) -> East | D206: =PROPER(Table1[[#This Row],[Product Category]]) -> Groceries | E206: =ROUND(Table1[[#This Row],[Sales Amount]],1) -> 211.3 | F206: =Table1[[#This Row],[Quantity Sold]] -> 45 | G206: =Table1[[#This Row],[Discount (%)]] -> 48 | H206: =Table1[[#This Row],[Profit]] -> 1844.45
A207: 733628ca | B207: 45227 | C207: =PROPER(Table1[[#This Row],[Region]]) -> West | D207: =PROPER(Table1[[#This Row],[Product Category]]) -> Furniture | E207: =ROUND(Table1[[#This Row],[Sales Amount]],1) -> 3582.9 | F207: =Table1[[#This Row],[Quantity Sold]] -> 42 | G207: =Table1[[#This Row],[Discount (%)]] -> 48 | H207: =Table1[[#This Row],[Profit]] -> 1359.36
A208: 7101a707 | B208: 45228 | C208: =PROPER(Table1[[#This Row],[Region]]) -> West | D208: =PROPER(Table1[[#This Row],[Product Category]]) -> Furniture | E208: =ROUND(Table1[[#This Row],[Sales Amount]],1) -> 419.9 | F208: =Table1[[#This Row],[Quantity Sold]] -> 12 | G208: =Table1[[#This Row],[Discount (%)]] -> 22 | H208: =Table1[[#This Row],[Profit]] -> 1047.8
A209: 7349ac4e | B209: 45229 | C209: =PROPER(Table1[[#This Row],[Region]]) -> East | D209: =PROPER(Table1[[#This Row],[Product Category]]) -> Sports | E209: =ROUND(Table1[[#This Row],[Sales Amount]],1) -> 4422.2 | F209: =Table1[[#This Row],[Quantity Sold]] -> 14 | G209: =Table1[[#This Row],[Discount (%)]] -> 33 | H209: =Table1[[#This Row],[Profit]] -> 237.47
A210: fbe74fbe | B210: 45230 | C210: =PROPER(Table1[[#This Row],[Region]]) -> East | D210: =PROPER(Table1[[#This Row],[Product Category]]) -> Furniture | E210: =ROUND(Table1[[#This Row],[Sales Amount]],1) -> 3277.5 | F210: =Table1[[#This Row],[Quantity Sold]] -> 11 | G210: =Table1[[#This Row],[Discount (%)]] -> 2 | H210: =Table1[[#This Row],[Profit]] -> 379.92
A211: 6bde908c | B211: 45231 | C211: =PROPER(Table1[[#This Row],[Region]]) -> North | D211: =PROPER(Table1[[#This Row],[Product Category]]) -> Clothing | E211: =ROUND(Table1[[#This Row],[Sales Amount]],1) -> 4264.4 | F211: =Table1[[#This Row],[Quantity Sold]] -> 31 | G211: =Table1[[#This Row],[Discount (%)]] -> 24 | H211: =Table1[[#This Row],[Profit]] -> 1179.93
A212: 56a98641 | B212: 45232 | C212: =PROPER(Table1[[#This Row],[Region]]) -> South | D212: =PROPER(Table1[[#This Row],[Product Category]]) -> Furniture | E212: =ROUND(Table1[[#This Row],[Sales Amount]],1) -> 647.4 | F212: =Table1[[#This Row],[Quantity Sold]] -> 16 | G212: =Table1[[#This Row],[Discount (%)]] -> 34 | H212: =Table1[[#This Row],[Profit]] -> 1937.88
... A216: 2ecc60c1 | B216: 45236 | C216: =PROPER(Table1[[#This Row],[Region]]) -> South | D216: =PROPER(Table1[[#This Row],[Product Category]]) -> Clothing | E216: =ROUND(Table1[[#This Row],[Sales Amount]],1) -> 4559.2 | F216: =Table1[[#This Row],[Quantity Sold]] -> 14 | G216: =Table1[[#This Row],[Discount (%)]] -> 29 | H216: =Table1[[#This Row],[Profit]] -> 1055.86
A217: 60839616 | B217: 45237 | C217: =PROPER(Table1[[#This Row],[Region]]) -> South | D217: =PROPER(Table1[[#This Row],[Product Category]]) -> Sports | E217: =ROUND(Table1[[#This Row],[Sales Amount]],1) -> 1787.1 | F217: =Table1[[#This Row],[Quantity Sold]] -> 11 | G217: =Table1[[#This Row],[Discount (%)]] -> 19 | H217: =Table1[[#This Row],[Profit]] -> 40.81
A218: a65dfe8b | B218: 45238 | C218: =PROPER(Table1[[#This Row],[Region]]) -> West | D218: =PROPER(Table1[[#This Row],[Product Category]]) -> Furniture | E218: =ROUND(Table1[[#This Row],[Sales Amount]],1) -> 901.7 | F218: =Table1[[#This Row],[Quantity Sold]] -> 7 | G218: =Table1[[#This Row],[Discount (%)]] -> 48 | H218: =Table1[[#This Row],[Profit]] -> 903.11
A219: 850b0c26 | B219: 45239 | C219: =PROPER(Table1[[#This Row],[Region]]) -> North | D219: =PROPER(Table1[[#This Row],[Product Category]]) -> Electronics | E219: =ROUND(Table1[[#This Row],[Sales Amount]],1) -> 2934.7 | F219: =Table1[[#This Row],[Quantity Sold]] -> 20 | G219: =Table1[[#This Row],[Discount (%)]] -> 12 | H219: =Table1[[#This Row],[Profit]] -> 528.02
A220: 21fd10ea | B220: 45240 | C220: =PROPER(Table1[[#This Row],[Region]]) -> West | D220: =PROPER(Table1[[#This Row],[Product Category]]) -> Groceries | E220: =ROUND(Table1[[#This Row],[Sales Amount]],1) -> 1058.6 | F220: =Table1[[#This Row],[Quantity Sold]] -> 6 | G220: =Table1[[#This Row],[Discount (%)]] -> 13 | H220: =Table1[[#This Row],[Profit]] -> 697.72
A221: 8d90e130 | B221: 45241 | C221: =PROPER(Table1[[#This Row],[Region]]) -> East | D221: =PROPER(Table1[[#This Row],[Product Category]]) -> Furniture | E221: =ROUND(Table1[[#This Row],[Sales Amount]],1) -> 3988.4 | F221: =Table1[[#This Row],[Quantity Sold]] -> 36 | G221: =Table1[[#This Row],[Discount (%)]] -> 1 | H221: =Table1[[#This Row],[Profit]] -> 1637.88
A222: 41aee1e8 | B222: 45242 | C222: =PROPER(Table1[[#This Row],[Region]]) -> South | D222: =PROPER(Table1[[#This Row],[Product Category]]) -> Sports | E222: =ROUND(Table1[[#This Row],[Sales Amount]],1) -> 2727.5 | F222: =Table1[[#This Row],[Quantity Sold]] -> 35 | G222: =Table1[[#This Row],[Discount (%)]] -> 1 | H222: =Table1[[#This Row],[Profit]] -> 1875.23
A223: 2f562dc0 | B223: 45243 | C223: =PROPER(Table1[[#This Row],[Region]]) -> South | D223: =PROPER(Table1[[#This Row],[Product Category]]) -> Groceries | E223: =ROUND(Table1[[#This Row],[Sales Amount]],1) -> 1765.5 | F223: =Table1[[#This Row],[Quantity Sold]] -> 13 | G223: =Table1[[#This Row],[Discount (%)]] -> 24 | H223: =Table1[[#This Row],[Profit]] -> 1951.72
A224: 1790f693 | B224: 45244 | C224: =PROPER(Table1[[#This Row],[Region]]) -> North | D224: =PROPER(Table1[[#This Row],[Product Category]]) -> Furniture | E224: =ROUND(Table1[[#This Row],[Sales Amount]],1) -> 4383.8 | F224: =Table1[[#This Row],[Quantity Sold]] -> 40 | G224: =Table1[[#This Row],[Discount (%)]] -> 21 | H224: =Table1[[#This Row],[Profit]] -> 1013.33
A225: 1ad9d5e9 | B225: 45245 | C225: =PROPER(Table1[[#This Row],[Region]]) -> South | D225: =PROPER(Table1[[#This Row],[Product Category]]) -> Groceries | E225: =ROUND(Table1[[#This Row],[Sales Amount]],1) -> 4240.6 | F225: =Table1[[#This Row],[Quantity Sold]] -> 49 | G225: =Table1[[#This Row],[Discount (%)]] -> 14 | H225: =Table1[[#This Row],[Profit]] -> 1765.62
A226: ae129571 | B226: 45246 | C226: =PROPER(Table1[[#This Row],[Region]]) -> South | D226: =PROPER(Table1[[#This Row],[Product Category]]) -> Furniture | E226: =ROUND(Table1[[#This Row],[Sales Amount]],1) -> 273.8 | F226: =Table1[[#This Row],[Quantity Sold]] -> 44 | G226: =Table1[[#This Row],[Discount (%)]] -> 29 | H226: =Table1[[#This Row],[Profit]] -> 821
A227: 79a06bc6 | B227: 45247 | C227: =PROPER(Table1[[#This Row],[Region]]) -> East | D227: =PROPER(Table1[[#This Row],[Product Category]]) -> Sports | E227: =ROUND(Table1[[#This Row],[Sales Amount]],1) -> 152.5 | F227: =Table1[[#This Row],[Quantity Sold]] -> 10 | G227: =Table1[[#This Row],[Discount (%)]] -> 16 | H227: =Table1[[#This Row],[Profit]] -> 1958.8
A228: 65240ae3 | B228: 45248 | C228: =PROPER(Table1[[#This Row],[Region]]) -> West | D228: =PROPER(Table1[[#This Row],[Product Category]]) -> Groceries | E228: =ROUND(Table1[[#This Row],[Sales Amount]],1) -> 1408 | F228: =Table1[[#This Row],[Quantity Sold]] -> 26 | G228: =Table1[[#This Row],[Discount (%)]] -> 35 | H228: =Table1[[#This Row],[Profit]] -> 978.17
A229: d4df366c | B229: 45249 | C229: =PROPER(Table1[[#This Row],[Region]]) -> West | D229: =PROPER(Table1[[#This Row],[Product Category]]) -> Furniture | E229: =ROUND(Table1[[#This Row],[Sales Amount]],1) -> 4083.3 | F229: =Table1[[#This Row],[Quantity Sold]] -> 22 | G229: =Table1[[#This Row],[Discount (%)]] -> 40 | H229: =Table1[[#This Row],[Profit]] -> 1003.31
... A271: d344a2c7 | B271: 45291 | C271: =PROPER(Table1[[#This Row],[Region]]) -> East | D271: =PROPER(Table1[[#This Row],[Product Category]]) -> Furniture | E271: =ROUND(Table1[[#This Row],[Sales Amount]],1) -> 3012.9 | F271: =Table1[[#This Row],[Quantity Sold]] -> 16 | G271: =Table1[[#This Row],[Discount (%)]] -> 16 | H271: =Table1[[#This Row],[Profit]] -> 789.81
A272: 6.7765e+71 | B272: 45292 | C272: =PROPER(Table1[[#This Row],[Region]]) -> North | D272: =PROPER(Table1[[#This Row],[Product Category]]) -> Clothing | E272: =ROUND(Table1[[#This Row],[Sales Amount]],1) -> 1877.4 | F272: =Table1[[#This Row],[Quantity Sold]] -> 40 | G272: =Table1[[#This Row],[Discount (%)]] -> 46 | H272: =Table1[[#This Row],[Profit]] -> 730.86
A273: 3cccf911 | B273: 45293 | C273: =PROPER(Table1[[#This Row],[Region]]) -> West | D273: =PROPER(Table1[[#This Row],[Product Category]]) -> Electronics | E273: =ROUND(Table1[[#This Row],[Sales Amount]],1) -> 2634.2 | F273: =Table1[[#This Row],[Quantity Sold]] -> 19 | G273: =Table1[[#This Row],[Discount (%)]] -> 35 | H273: =Table1[[#This Row],[Profit]] -> 38.85
...

Sheet task 4
A1: Sum Average
C6: region | D6: sum of region | J6: Category | K6: Average
C7: North | D7: =SUMIF(Table246[Region],"North",Table246[Sales Amount]) -> 2536948.4 | J7: Average Discount of Furniture | K7: =AVERAGEIF(Table246[Product Category],"Furniture",Table246[Discount %]) -> 25.215951
C8: West | D8: =SUMIF(Table246[Region],"West",Table246[Sales Amount]) -> 2479259.3 | J8: Average profit of Furniture | K8: =AVERAGEIF(Table246[Product Category],"Furniture",Table246[profit]) -> 1022.3432
C9: East | D9: =SUMIF(Table246[Region],"East",Table246[Sales Amount]) -> 2592526.4
C10: South | D10: =SUMIF(Table246[Region],"South",Table246[Sales Amount]) -> 2494414.8

Sheet task 5
A1: SUM OF SALES BY REGION SUM OF PROFIT BY REGION
C4: Region | D4: Sum of Sales Amount | J4: Region | K4: Sum of profit
C5: East | D5: 2592526.4 | J5: East | K5: 1049790.1
C6: North | D6: 2536948.4 | J6: North | K6: 969077.71
C7: South | D7: 2494414.8 | J7: South | K7: 1010902.6
C8: West | D8: 2479259.3 | J8: West | K8: 998358.03
C9: Grand Total | D9: 10103149 | J9: Grand Total | K9: 4028128.4
A20: BY USING PIVOT TABLE
U61: Region | V61: Sum of Sales Amount
U62: Clothing | V62: 2156010.8
U63: Electronics | V63: 2047839.5
U64: Furniture | V64: 2046524.5
U65: Groceries | V65: 1864229.2
U66: Sports | V66: 1988544.9
U67: Grand Total | V67: 10103149

Sheet task 6
A1: TOTAL SALES BY REGION | L1: TOTAL SALES BY CATEGORY

Sheet task 7
A1: REGRESSION ANALYSIS
E5: Discount % | F5: profit
E6: =Table1[[#This Row],[Discount (%)]] -> 28 | F6: =Table1[[#This Row],[Profit]] -> 748.72
E7: =Table1[[#This Row],[Discount (%)]] -> 50 | F7: =Table1[[#This Row],[Profit]] -> 314.71
E8: =Table1[[#This Row],[Discount (%)]] -> 18 | F8: =Table1[[#This Row],[Profit]] -> 1372.89
E9: =Table1[[#This Row],[Discount (%)]] -> 16 | F9: =Table1[[#This Row],[Profit]] -> 1437.3
E10: =Table1[[#This Row],[Discount (%)]] -> 3 | F10: =Table1[[#This Row],[Profit]] -> 1537.28
E11: =Table1[[#This Row],[Discount (%)]] -> 24 | F11: =Table1[[#This Row],[Profit]] -> 1696.65
E12: =Table1[[#This Row],[Discount (%)]] -> 12 | F12: =Table1[[#This Row],[Profit]] -> 1166.39
E13: =Table1[[#This Row],[Discount (%)]] -> 2 | F13: =Table1[[#This Row],[Profit]] -> 1632.75
E14: =Table1[[#This Row],[Discount (%)]] -> 28 | F14: =Table1[[#This Row],[Profit]] -> 646.49
E15: =Table1[[#This Row],[Discount (%)]] -> 48 | F15: =Table1[[#This Row],[Profit]] -> 86.9
E16: =Table1[[#This Row],[Discount (%)]] -> 19 | F16: =Table1[[#This Row],[Profit]] -> 611.06
E17: =Table1[[#This Row],[Discount (%)]] -> 21 | F17: =Table1[[#This Row],[Profit]] -> 208.1
... E4002: =Table1[[#This Row],[Discount (%)]] -> #VALUE! | F4002: =Table1[[#This Row],[Profit]] -> #VALUE!

Sheet task 8
A1: STACKED BAR CHART
D9: Region | E9: Sum of Sales Amount
D10: East | E10: 2592526.4
D11: North | E11: 2536948.4
D12: South | E12: 2494414.8
D13: West | E13: 2479259.3
D14: Grand Total | E14: 10103149
D28: Region | E28: Total Sales by Region
D29: Clothing | E29: 2156010.8
D30: Electronics | E30: 2047839.5
D31: Furniture | E31: 2046524.5
D32: Groceries | E32: 1864229.2
D33: Sports | E33: 1988544.9
D34: Grand Total | E34: 10103149

Sheet Dashboard

Sheet task 10
A1: order id | B1: Order Date | C1: Region | D1: Product Category | E1: Sales Amount | F1: Quantity Sold | G1: Discount % | H1: profit | I1: profit Margin
A2: ab899d2f | B2: 45022 | C2: =PROPER(Table1[[#This Row],[Region]]) -> North | D2: =PROPER(Table1[[#This Row],[Product Category]]) -> Groceries | E2: =ROUND(Table1[[#This Row],[Sales Amount]],1) -> 859.3 | F2: =Table1[[#This Row],[Quantity Sold]] -> 44 | G2: =Table1[[#This Row],[Discount (%)]] -> 37 | H2: =Table1[[#This Row],[Profit]] -> 1653.87 | I2: =Table24610[[#This Row],[profit]]/Table24610[[#This Row],[Sales Amount]] -> 1.9246712
A3: 73484eb1 | B3: 45023 | C3: =PROPER(Table1[[#This Row],[Region]]) -> West | D3: =PROPER(Table1[[#This Row],[Product Category]]) -> Groceries | E3: =ROUND(Table1[[#This Row],[Sales Amount]],1) -> 1546.8 | F3: =Table1[[#This Row],[Quantity Sold]] -> 23 | G3: =Table1[[#This Row],[Discount (%)]] -> 33 | H3: =Table1[[#This Row],[Profit]] -> 1932.71 | I3: =Table24610[[#This Row],[profit]]/Table24610[[#This Row],[Sales Amount]] -> 1.2494893 | M3: Adding colum and finding profit margin
A4: 19395924 | B4: 45024 | C4: =PROPER(Table1[[#This Row],[Region]]) -> East | D4: =PROPER(Table1[[#This Row],[Product Category]]) -> Groceries | E4: =ROUND(Table1[[#This Row],[Sales Amount]],1) -> 4703.6 | F4: =Table1[[#This Row],[Quantity Sold]] -> 31 | G4: =Table1[[#This Row],[Discount (%)]] -> 15 | H4: =Table1[[#This Row],[Profit]] -> 527.47 | I4: =Table24610[[#This Row],[profit]]/Table24610[[#This Row],[Sales Amount]] -> 0.11214176
A5: b3fded3d | B5: 45025 | C5: =PROPER(Table1[[#This Row],[Region]]) -> East | D5: =PROPER(Table1[[#This Row],[Product Category]]) -> Groceries | E5: =ROUND(Table1[[#This Row],[Sales Amount]],1) -> 3377.2 | F5: =Table1[[#This Row],[Quantity Sold]] -> 47 | G5: =Table1[[#This Row],[Discount (%)]] -> 3 | H5: =Table1[[#This Row],[Profit]] -> 482.65 | I5: =Table24610[[#This Row],[profit]]/Table24610[[#This Row],[Sales Amount]] -> 0.14291425 | M5: Highlight profit margin
A6: 6e4bdd51 | B6: 45026 | C6: =PROPER(Table1[[#This Row],[Region]]) -> South | D6: =PROPER(Table1[[#This Row],[Product Category]]) -> Clothing | E6: =ROUND(Table1[[#This Row],[Sales Amount]],1) -> 3517.5 | F6: =Table1[[#This Row],[Quantity Sold]] -> 6 | G6: =Table1[[#This Row],[Discount (%)]] -> 28 | H6: =Table1[[#This Row],[Profit]] -> 748.72 | I6: =Table24610[[#This Row],[profit]]/Table24610[[#This Row],[Sales Amount]] -> 0.21285572
A7: 21d88d69 | B7: 45027 | C7: =PROPER(Table1[[#This Row],[Region]]) -> East | D7: =PROPER(Table1[[#This Row],[Product Category]]) -> Furniture | E7: =ROUND(Table1[[#This Row],[Sales Amount]],1) -> 362.6 | F7: =Table1[[#This Row],[Quantity Sold]] -> 19 | G7: =Table1[[#This Row],[Discount (%)]] -> 50 | H7: =Table1[[#This Row],[Profit]] -> 314.71 | I7: =Table24610[[#This Row],[profit]]/Table24610[[#This Row],[Sales Amount]] -> 0.86792609 | M7: highlight sales>4000
A8: 9da2704d | B8: 45028 | C8: =PROPER(Table1[[#This Row],[Region]]) -> East | D8: =PROPER(Table1[[#This Row],[Product Category]]) -> Sports | E8: =ROUND(Table1[[#This Row],[Sales Amount]],1) -> 4811.2 | F8: =Table1[[#This Row],[Quantity Sold]] -> 22 | G8: =Table1[[#This Row],[Discount (%)]] -> 18 | H8: =Table1[[#This Row],[Profit]] -> 1372.89 | I8: =Table24610[[#This Row],[profit]]/Table24610[[#This Row],[Sales Amount]] -> 0.28535293
A9: a1bd6815 | B9: 45029 | C9: =PROPER(Table1[[#This Row],[Region]]) -> West | D9: =PROPER(Table1[[#This Row],[Product Category]]) -> Electronics | E9: =ROUND(Table1[[#This Row],[Sales Amount]],1) -> 3565.2 | F9: =Table1[[#This Row],[Quantity Sold]] -> 22 | G9: =Table1[[#This Row],[Discount (%)]] -> 16 | H9: =Table1[[#This Row],[Profit]] -> 1437.3 | I9: =Table24610[[#This Row],[profit]]/Table24610[[#This Row],[Sales Amount]] -> 0.40314709
A10: 0bbd51fc | B10: 45030 | C10: =PROPER(Table1[[#This Row],[Region]]) -> East | D10: =PROPER(Table1[[#This Row],[Product Category]]) -> Clothing | E10: =ROUND(Table1[[#This Row],[Sales Amount]],1) -> 3805.3 | F10: =Table1[[#This Row],[Quantity Sold]] -> 19 | G10: =Table1[[#This Row],[Discount (%)]] -> 3 | H10: =Table1[[#This Row],[Profit]] -> 1537.28 | I10: =Table24610[[#This Row],[profit]]/Table24610[[#This Row],[Sales Amount]] -> 0.40398392
A11: 8bf7e4b3 | B11: 45031 | C11: =PROPER(Table1[[#This Row],[Region]]) -> South | D11: =PROPER(Table1[[#This Row],[Product Category]]) -> Clothing | E11: =ROUND(Table1[[#This Row],[Sales Amount]],1) -> 2178.7 | F11: =Table1[[#This Row],[Quantity Sold]] -> 15 | G11: =Table1[[#This Row],[Discount (%)]] -> 24 | H11: =Table1[[#This Row],[Profit]] -> 1696.65 | I11: =Table24610[[#This Row],[profit]]/Table24610[[#This Row],[Sales Amount]] -> 0.77874421
A12: e6cf1255 | B12: 45032 | C12: =PROPER(Table1[[#This Row],[Region]]) -> West | D12: =PROPER(Table1[[#This Row],[Product Category]]) -> Groceries | E12: =ROUND(Table1[[#This Row],[Sales Amount]],1) -> 2844.9 | F12: =Table1[[#This Row],[Quantity Sold]] -> 34 | G12: =Table1[[#This Row],[Discount (%)]] -> 12 | H12: =Table1[[#This Row],[Profit]] -> 1166.39 | I12: =Table24610[[#This Row],[profit]]/Table24610[[#This Row],[Sales Amount]] -> 0.40999332
A13: 3ba1fc5c | B13: 45033 | C13: =PROPER(Table1[[#This Row],[Region]]) -> West | D13: =PROPER(Table1[[#This Row],[Product Category]]) -> Electronics | E13: =ROUND(Table1[[#This Row],[Sales Amount]],1) -> 3600 | F13: =Table1[[#This Row],[Quantity Sold]] -> 10 | G13: =Table1[[#This Row],[Discount (%)]] -> 2 | H13: =Table1[[#This Row],[Profit]] -> 1632.75 | I13: =Table24610[[#This Row],[profit]]/Table24610[[#This Row],[Sales Amount]] -> 0.45354167
A14: 388ff70d | B14: 45034 | C14: =PROPER(Table1[[#This Row],[Region]]) -> East | D14: =PROPER(Table1[[#This Row],[Product Category]]) -> Sports | E14: =ROUND(Table1[[#This Row],[Sales Amount]],1) -> 941.9 | F14: =Table1[[#This Row],[Quantity Sold]] -> 13 | G14: =Table1[[#This Row],[Discount (%)]] -> 28 | H14: =Table1[[#This Row],[Profit]] -> 646.49 | I14: =Table24610[[#This Row],[profit]]/Table24610[[#This Row],[Sales Amount]] -> 0.68636798
A15: ce2e9002 | B15: 45035 | C15: =PROPER(Table1[[#This Row],[Region]]) -> South | D15: =PROPER(Table1[[#This Row],[Product Category]]) -> Sports | E15: =ROUND(Table1[[#This Row],[Sales Amount]],1) -> 3300.9 | F15: =Table1[[#This Row],[Quantity Sold]] -> 1 | G15: =Table1[[#This Row],[Discount (%)]] -> 48 | H15: =Table1[[#This Row],[Profit]] -> 86.9 | I15: =Table24610[[#This Row],[profit]]/Table24610[[#This Row],[Sales Amount]] -> 0.026326153
A16: a4f9a338 | B16: 45036 | C16: =PROPER(Table1[[#This Row],[Region]]) -> East | D16: =PROPER(Table1[[#This Row],[Product Category]]) -> Groceries | E16: =ROUND(Table1[[#This Row],[Sales Amount]],1) -> 1081.6 | F16: =Table1[[#This Row],[Quantity Sold]] -> 4 | G16: =Table1[[#This Row],[Discount (%)]] -> 19 | H16: =Table1[[#This Row],[Profit]] -> 611.06 | I16: =Table24610[[#This Row],[profit]]/Table24610[[#This Row],[Sales Amount]] -> 0.56495932
A17: eadceaa8 | B17: 45037 | C17: =PROPER(Table1[[#This Row],[Region]]) -> East | D17: =PROPER(Table1[[#This Row],[Product Category]]) -> Furniture | E17: =ROUND(Table1[[#This Row],[Sales Amount]],1) -> 3455.7 | F17: =Table1[[#This Row],[Quantity Sold]] -> 39 | G17: =Table1[[#This Row],[Discount (%)]] -> 21 | H17: =Table1[[#This Row],[Profit]] -> 208.1 | I17: =Table24610[[#This Row],[profit]]/Table24610[[#This Row],[Sales Amount]] -> 0.060219348
A18: ad7f9de9 | B18: 45038 | C18: =PROPER(Table1[[#This Row],[Region]]) -> South | D18: =PROPER(Table1[[#This Row],[Product Category]]) -> Groceries | E18: =ROUND(Table1[[#This Row],[Sales Amount]],1) -> 2381.5 | F18: =Table1[[#This Row],[Quantity Sold]] -> 16 | G18: =Table1[[#This Row],[Discount (%)]] -> 39 | H18: =Table1[[#This Row],[Profit]] -> 1083.96 | I18: =Table24610[[#This Row],[profit]]/Table24610[[#This Row],[Sales Amount]] -> 0.45515851
A19: 35358e9c | B19: 45039 | C19: =PROPER(Table1[[#This Row],[Region]]) -> North | D19: =PROPER(Table1[[#This Row],[Product Category]]) -> Clothing | E19: =ROUND(Table1[[#This Row],[Sales Amount]],1) -> 2784.8 | F19: =Table1[[#This Row],[Quantity Sold]] -> 35 | G19: =Table1[[#This Row],[Discount (%)]] -> 40 | H19: =Table1[[#This Row],[Profit]] -> 999.6 | I19: =Table24610[[#This Row],[profit]]/Table24610[[#This Row],[Sales Amount]] -> 0.35894858
A20: 31676338 | B20: 45040 | C20: =PROPER(Table1[[#This Row],[Region]]) -> South | D20: =PROPER(Table1[[#This Row],[Product Category]]) -> Clothing | E20: =ROUND(Table1[[#This Row],[Sales Amount]],1) -> 1083 | F20: =Table1[[#This Row],[Quantity Sold]] -> 8 | G20: =Table1[[#This Row],[Discount (%)]] -> 11 | H20: =Table1[[#This Row],[Profit]] -> 1604.19 | I20: =Table24610[[#This Row],[profit]]/Table24610[[#This Row],[Sales Amount]] -> 1.4812465
A21: 05d72e20 | B21: 45041 | C21: =PROPER(Table1[[#This Row],[Region]]) -> East | D21: =PROPER(Table1[[#This Row],[Product Category]]) -> Clothing | E21: =ROUND(Table1[[#This Row],[Sales Amount]],1) -> 787.8 | F21: =Table1[[#This Row],[Quantity Sold]] -> 47 | G21: =Table1[[#This Row],[Discount (%)]] -> 18 | H21: =Table1[[#This Row],[Profit]] -> 1313.33 | I21: =Table24610[[#This Row],[profit]]/Table24610[[#This Row],[Sales Amount]] -> 1.6670856
A22: 68dbe328 | B22: 45042 | C22: =PROPER(Table1[[#This Row],[Region]]) -> South | D22: =PROPER(Table1[[#This Row],[Product Category]]) -> Furniture | E22: =ROUND(Table1[[#This Row],[Sales Amount]],1) -> 312.7 | F22: =Table1[[#This Row],[Quantity Sold]] -> 36 | G22: =Table1[[#This Row],[Discount (%)]] -> 43 | H22: =Table1[[#This Row],[Profit]] -> 559.52 | I22: =Table24610[[#This Row],[profit]]/Table24610[[#This Row],[Sales Amount]] -> 1.7893188
A23: 78d3f47b | B23: 45043 | C23: =PROPER(Table1[[#This Row],[Region]]) -> East | D23: =PROPER(Table1[[#This Row],[Product Category]]) -> Sports | E23: =ROUND(Table1[[#This Row],[Sales Amount]],1) -> 265.3 | F23: =Table1[[#This Row],[Quantity Sold]] -> 21 | G23: =Table1[[#This Row],[Discount (%)]] -> 36 | H23: =Table1[[#This Row],[Profit]] -> 595.91 | I23: =Table24610[[#This Row],[profit]]/Table24610[[#This Row],[Sales Amount]] -> 2.2461741
A24: 9e4d1fe0 | B24: 45044 | C24: =PROPER(Table1[[#This Row],[Region]]) -> West | D24: =PROPER(Table1[[#This Row],[Product Category]]) -> Furniture | E24: =ROUND(Table1[[#This Row],[Sales Amount]],1) -> 1253.6 | F24: =Table1[[#This Row],[Quantity Sold]] -> 35 | G24: =Table1[[#This Row],[Discount (%)]] -> 14 | H24: =Table1[[#This Row],[Profit]] -> 1653.66 | I24: =Table24610[[#This Row],[profit]]/Table24610[[#This Row],[Sales Amount]] -> 1.3191289
A25: 9215a70e | B25: 45045 | C25: =PROPER(Table1[[#This Row],[Region]]) -> West | D25: =PROPER(Table1[[#This Row],[Product Category]]) -> Clothing | E25: =ROUND(Table1[[#This Row],[Sales Amount]],1) -> 1874.1 | F25: =Table1[[#This Row],[Quantity Sold]] -> 28 | G25: =Table1[[#This Row],[Discount (%)]] -> 23 | H25: =Table1[[#This Row],[Profit]] -> 1783.26 | I25: =Table24610[[#This Row],[profit]]/Table24610[[#This Row],[Sales Amount]] -> 0.95152873
A26: 54ca3433 | B26: 45046 | C26: =PROPER(Table1[[#This Row],[Region]]) -> East | D26: =PROPER(Table1[[#This Row],[Product Category]]) -> Clothing | E26: =ROUND(Table1[[#This Row],[Sales Amount]],1) -> 2561.7 | F26: =Table1[[#This Row],[Quantity Sold]] -> 44 | G26: =Table1[[#This Row],[Discount (%)]] -> 10 | H26: =Table1[[#This Row],[Profit]] -> 800.82 | I26: =Table24610[[#This Row],[profit]]/Table24610[[#This Row],[Sales Amount]] -> 0.31261272
A27: 0ba75cc7 | B27: 45047 | C27: =PROPER(Table1[[#This Row],[Region]]) -> West | D27: =PROPER(Table1[[#This Row],[Product Category]]) -> Sports | E27: =ROUND(Table1[[#This Row],[Sales Amount]],1) -> 1960.7 | F27: =Table1[[#This Row],[Quantity Sold]] -> 50 | G27: =Table1[[#This Row],[Discount (%)]] -> 6 | H27: =Table1[[#This Row],[Profit]] -> 1530.61 | I27: =Table24610[[#This Row],[profit]]/Table24610[[#This Row],[Sales Amount]] -> 0.78064467
A28: 601860b1 | B28: 45048 | C28: =PROPER(Table1[[#This Row],[Region]]) -> East | D28: =PROPER(Table1[[#This Row],[Product Category]]) -> Electronics | E28: =ROUND(Table1[[#This Row],[Sales Amount]],1) -> 2415.4 | F28: =Table1[[#This Row],[Quantity Sold]] -> 35 | G28: =Table1[[#This Row],[Discount (%)]] -> 14 | H28: =Table1[[#This Row],[Profit]] -> 335.57 | I28: =Table24610[[#This Row],[profit]]/Table24610[[#This Row],[Sales Amount]] -> 0.13892937
A29: e393e106 | B29: 45049 | C29: =PROPER(Table1[[#This Row],[Region]]) -> East | D29: =PROPER(Table1[[#This Row],[Product Category]]) -> Electronics | E29: =ROUND(Table1[[#This Row],[Sales Amount]],1) -> 2284.2 | F29: =Table1[[#This Row],[Quantity Sold]] -> 8 | G29: =Table1[[#This Row],[Discount (%)]] -> 41 | H29: =Table1[[#This Row],[Profit]] -> 1866.59 | I29: =Table24610[[#This Row],[profit]]/Table24610[[#This Row],[Sales Amount]] -> 0.8171745
A30: 7ab3d472 | B30: 45050 | C30: =PROPER(Table1[[#This Row],[Region]]) -> West | D30: =PROPER(Table1[[#This Row],[Product Category]]) -> Sports | E30: =ROUND(Table1[[#This Row],[Sales Amount]],1) -> 2118.6 | F30: =Table1[[#This Row],[Quantity Sold]] -> 29 | G30: =Table1[[#This Row],[Discount (%)]] -> 24 | H30: =Table1[[#This Row],[Profit]] -> 702.15 | I30: =Table24610[[#This Row],[profit]]/Table24610[[#This Row],[Sales Amount]] -> 0.33142169
A31: 01d9b1ae | B31: 45051 | C31: =PROPER(Table1[[#This Row],[Region]]) -> South | D31: =PROPER(Table1[[#This Row],[Product Category]]) -> Groceries | E31: =ROUND(Table1[[#This Row],[Sales Amount]],1) -> 4803.6 | F31: =Table1[[#This Row],[Quantity Sold]] -> 11 | G31: =Table1[[#This Row],[Discount (%)]] -> 12 | H31: =Table1[[#This Row],[Profit]] -> 1086.74 | I31: =Table24610[[#This Row],[profit]]/Table24610[[#This Row],[Sales Amount]] -> 0.22623449
A32: 20385cb6 | B32: 45052 | C32: =PROPER(Table1[[#This Row],[Region]]) -> North | D32: =PROPER(Table1[[#This Row],[Product Category]]) -> Groceries | E32: =ROUND(Table1[[#This Row],[Sales Amount]],1) -> 4297 | F32: =Table1[[#This Row],[Quantity Sold]] -> 17 | G32: =Table1[[#This Row],[Discount (%)]] -> 49 | H32: =Table1[[#This Row],[Profit]] -> 678.7 | I32: =Table24610[[#This Row],[profit]]/Table24610[[#This Row],[Sales Amount]] -> 0.15794741
... A69: 92458ed3 | B69: 45089 | C69: =PROPER(Table1[[#This Row],[Region]]) -> North | D69: =PROPER(Table1[[#This Row],[Product Category]]) -> Furniture | E69: =ROUND(Table1[[#This Row],[Sales Amount]],1) -> 1356.6 | F69: =Table1[[#This Row],[Quantity Sold]] -> 2 | G69: =Table1[[#This Row],[Discount (%)]] -> 21 | H69: =Table1[[#This Row],[Profit]] -> 1213.34 | I69: =Table24610[[#This Row],[profit]]/Table24610[[#This Row],[Sales Amount]] -> 0.89439776
A70: 76740552 | B70: 45090 | C70: =PROPER(Table1[[#This Row],[Region]]) -> South | D70: =PROPER(Table1[[#This Row],[Product Category]]) -> Electronics | E70: =ROUND(Table1[[#This Row],[Sales Amount]],1) -> 2905.8 | F70: =Table1[[#This Row],[Quantity Sold]] -> 20 | G70: =Table1[[#This Row],[Discount (%)]] -> 10 | H70: =Table1[[#This Row],[Profit]] -> 1417.43 | I70: =Table24610[[#This Row],[profit]]/Table24610[[#This Row],[Sales Amount]] -> 0.48779338
A71: f92de80d | B71: 45091 | C71: =PROPER(Table1[[#This Row],[Region]]) -> South | D71: =PROPER(Table1[[#This Row],[Product Category]]) -> Furniture | E71: =ROUND(Table1[[#This Row],[Sales Amount]],1) -> 2065.4 | F71: =Table1[[#This Row],[Quantity Sold]] -> 22 | G71: =Table1[[#This Row],[Discount (%)]] -> 15 | H71: =Table1[[#This Row],[Profit]] -> 787.51 | I71: =Table24610[[#This Row],[profit]]/Table24610[[#This Row],[Sales Amount]] -> 0.38128692
A72: 647ff51a | B72: 45092 | C72: =PROPER(Table1[[#This Row],[Region]]) -> East | D72: =PROPER(Table1[[#This Row],[Product Category]]) -> Clothing | E72: =ROUND(Table1[[#This Row],[Sales Amount]],1) -> 272.9 | F72: =Table1[[#This Row],[Quantity Sold]] -> 47 | G72: =Table1[[#This Row],[Discount (%)]] -> 29 | H72: =Table1[[#This Row],[Profit]] -> 1208.68 | I72: =Table24610[[#This Row],[profit]]/Table24610[[#This Row],[Sales Amount]] -> 4.4290216
A73: f8548ec7 | B73: 45093 | C73: =PROPER(Table1[[#This Row],[Region]]) -> East | D73: =PROPER(Table1[[#This Row],[Product Category]]) -> Clothing | E73: =ROUND(Table1[[#This Row],[Sales Amount]],1) -> 4126.4 | F73: =Table1[[#This Row],[Quantity Sold]] -> 34 | G73: =Table1[[#This Row],[Discount (%)]] -> 13 | H73: =Table1[[#This Row],[Profit]] -> 1690.11 | I73: =Table24610[[#This Row],[profit]]/Table24610[[#This Row],[Sales Amount]] -> 0.40958463
A74: 7855a0d2 | B74: 45094 | C74: =PROPER(Table1[[#This Row],[Region]]) -> North | D74: =PROPER(Table1[[#This Row],[Product Category]]) -> Furniture | E74: =ROUND(Table1[[#This Row],[Sales Amount]],1) -> 4204.6 | F74: =Table1[[#This Row],[Quantity Sold]] -> 49 | G74: =Table1[[#This Row],[Discount (%)]] -> 1 | H74: =Table1[[#This Row],[Profit]] -> 1534.82 | I74: =Table24610[[#This Row],[profit]]/Table24610[[#This Row],[Sales Amount]] -> 0.36503353
A75: bf586512 | B75: 45095 | C75: =PROPER(Table1[[#This Row],[Region]]) -> West | D75: =PROPER(Table1[[#This Row],[Product Category]]) -> Clothing | E75: =ROUND(Table1[[#This Row],[Sales Amount]],1) -> 2131 | F75: =Table1[[#This Row],[Quantity Sold]] -> 7 | G75: =Table1[[#This Row],[Discount (%)]] -> 29 | H75: =Table1[[#This Row],[Profit]] -> 679.16 | I75: =Table24610[[#This Row],[profit]]/Table24610[[#This Row],[Sales Amount]] -> 0.31870483
A76: deea1965 | B76: 45096 | C76: =PROPER(Table1[[#This Row],[Region]]) -> South | D76: =PROPER(Table1[[#This Row],[Product Category]]) -> Furniture | E76: =ROUND(Table1[[#This Row],[Sales Amount]],1) -> 1253.3 | F76: =Table1[[#This Row],[Quantity Sold]] -> 4 | G76: =Table1[[#This Row],[Discount (%)]] -> 48 | H76: =Table1[[#This Row],[Profit]] -> 317.33 | I76: =Table24610[[#This Row],[profit]]/Table24610[[#This Row],[Sales Amount]] -> 0.25319556
A77: a0a8290f | B77: 45097 | C77: =PROPER(Table1[[#This Row],[Region]]) -> South | D77: =PROPER(Table1[[#This Row],[Product Category]]) -> Sports | E77: =ROUND(Table1[[#This Row],[Sales Amount]],1) -> 1050.3 | F77: =Table1[[#This Row],[Quantity Sold]] -> 30 | G77: =Table1[[#This Row],[Discount (%)]] -> 4 | H77: =Table1[[#This Row],[Profit]] -> 423.5 | I77: =Table24610[[#This Row],[profit]]/Table24610[[#This Row],[Sales Amount]] -> 0.40321813
A78: 077a9429 | B78: 45098 | C78: =PROPER(Table1[[#This Row],[Region]]) -> North | D78: =PROPER(Table1[[#This Row],[Product Category]]) -> Furniture | E78: =ROUND(Table1[[#This Row],[Sales Amount]],1) -> 1269.1 | F78: =Table1[[#This Row],[Quantity Sold]] -> 3 | G78: =Table1[[#This Row],[Discount (%)]] -> 7 | H78: =Table1[[#This Row],[Profit]] -> 1819.88 | I78: =Table24610[[#This Row],[profit]]/Table24610[[#This Row],[Sales Amount]] -> 1.4339926
A79: 8642940000 | B79: 45099 | C79: =PROPER(Table1[[#This Row],[Region]]) -> West | D79: =PROPER(Table1[[#This Row],[Product Category]]) -> Groceries | E79: =ROUND(Table1[[#This Row],[Sales Amount]],1) -> 4229.5 | F79: =Table1[[#This Row],[Quantity Sold]] -> 3 | G79: =Table1[[#This Row],[Discount (%)]] -> 9 | H79: =Table1[[#This Row],[Profit]] -> 11.29 | I79: =Table24610[[#This Row],[profit]]/Table24610[[#This Row],[Sales Amount]] -> 0.0026693463
A80: 41d1321a | B80: 45100 | C80: =PROPER(Table1[[#This Row],[Region]]) -> South | D80: =PROPER(Table1[[#This Row],[Product Category]]) -> Groceries | E80: =ROUND(Table1[[#This Row],[Sales Amount]],1) -> 3767.6 | F80: =Table1[[#This Row],[Quantity Sold]] -> 30 | G80: =Table1[[#This Row],[Discount (%)]] -> 41 | H80: =Table1[[#This Row],[Profit]] -> 1031.74 | I80: =Table24610[[#This Row],[profit]]/Table24610[[#This Row],[Sales Amount]] -> 0.27384542
A81: 44afa795 | B81: 45101 | C81: =PROPER(Table1[[#This Row],[Region]]) -> West | D81: =PROPER(Table1[[#This Row],[Product Category]]) -> Sports | E81: =ROUND(Table1[[#This Row],[Sales Amount]],1) -> 640.9 | F81: =Table1[[#This Row],[Quantity Sold]] -> 19 | G81: =Table1[[#This Row],[Discount (%)]] -> 19 | H81: =Table1[[#This Row],[Profit]] -> 1148.62 | I81: =Table24610[[#This Row],[profit]]/Table24610[[#This Row],[Sales Amount]] -> 1.7921985
A82: 8c329e53 | B82: 45102 | C82: =PROPER(Table1[[#This Row],[Region]]) -> North | D82: =PROPER(Table1[[#This Row],[Product Category]]) -> Furniture | E82: =ROUND(Table1[[#This Row],[Sales Amount]],1) -> 2958 | F82: =Table1[[#This Row],[Quantity Sold]] -> 4 | G82: =Table1[[#This Row],[Discount (%)]] -> 22 | H82: =Table1[[#This Row],[Profit]] -> 1968.62 | I82: =Table24610[[#This Row],[profit]]/Table24610[[#This Row],[Sales Amount]] -> 0.665524
A83: cdbba08a | B83: 45103 | C83: =PROPER(Table1[[#This Row],[Region]]) -> West | D83: =PROPER(Table1[[#This Row],[Product Category]]) -> Sports | E83: =ROUND(Table1[[#This Row],[Sales Amount]],1) -> 4049.5 | F83: =Table1[[#This Row],[Quantity Sold]] -> 5 | G83: =Table1[[#This Row],[Discount (%)]] -> 1 | H83: =Table1[[#This Row],[Profit]] -> 1151.9 | I83: =Table24610[[#This Row],[profit]]/Table24610[[#This Row],[Sales Amount]] -> 0.28445487
A84: 4415c908 | B84: 45104 | C84: =PROPER(Table1[[#This Row],[Region]]) -> North | D84: =PROPER(Table1[[#This Row],[Product Category]]) -> Sports | E84: =ROUND(Table1[[#This Row],[Sales Amount]],1) -> 4155 | F84: =Table1[[#This Row],[Quantity Sold]] -> 32 | G84: =Table1[[#This Row],[Discount (%)]] -> 5 | H84: =Table1[[#This Row],[Profit]] -> 1637.7 | I84: =Table24610[[#This Row],[profit]]/Table24610[[#This Row],[Sales Amount]] -> 0.39415162
A85: a9ac13d3 | B85: 45105 | C85: =PROPER(Table1[[#This Row],[Region]]) -> North | D85: =PROPER(Table1[[#This Row],[Product Category]]) -> Furniture | E85: =ROUND(Table1[[#This Row],[Sales Amount]],1) -> 2011.4 | F85: =Table1[[#This Row],[Quantity Sold]] -> 44 | G85: =Table1[[#This Row],[Discount (%)]] -> 10 | H85: =Table1[[#This Row],[Profit]] -> 829.69 | I85: =Table24610[[#This Row],[profit]]/Table24610[[#This Row],[Sales Amount]] -> 0.41249379
A86: 5fbf219e | B86: 45106 | C86: =PROPER(Table1[[#This Row],[Region]]) -> West | D86: =PROPER(Table1[[#This Row],[Product Category]]) -> Electronics | E86: =ROUND(Table1[[#This Row],[Sales Amount]],1) -> 2365.2 | F86: =Table1[[#This Row],[Quantity Sold]] -> 10 | G86: =Table1[[#This Row],[Discount (%)]] -> 33 | H86: =Table1[[#This Row],[Profit]] -> 1970.1 | I86: =Table24610[[#This Row],[profit]]/Table24610[[#This Row],[Sales Amount]] -> 0.83295282
A87: f3ba50cf | B87: 45107 | C87: =PROPER(Table1[[#This Row],[Region]]) -> South | D87: =PROPER(Table1[[#This Row],[Product Category]]) -> Clothing | E87: =ROUND(Table1[[#This Row],[Sales Amount]],1) -> 2615.8 | F87: =Table1[[#This Row],[Quantity Sold]] -> 31 | G87: =Table1[[#This Row],[Discount (%)]] -> 9 | H87: =Table1[[#This Row],[Profit]] -> 1276.87 | I87: =Table24610[[#This Row],[profit]]/Table24610[[#This Row],[Sales Amount]] -> 0.48813747
A88: 88840b0f | B88: 45108 | C88: =PROPER(Table1[[#This Row],[Region]]) -> West | D88: =PROPER(Table1[[#This Row],[Product Category]]) -> Clothing | E88: =ROUND(Table1[[#This Row],[Sales Amount]],1) -> 4954.3 | F88: =Table1[[#This Row],[Quantity Sold]] -> 26 | G88: =Table1[[#This Row],[Discount (%)]] -> 43 | H88: =Table1[[#This Row],[Profit]] -> 1723.31 | I88: =Table24610[[#This Row],[profit]]/Table24610[[#This Row],[Sales Amount]] -> 0.34784127
A89: 3dcffe93 | B89: 45109 | C89: =PROPER(Table1[[#This Row],[Region]]) -> North | D89: =PROPER(Table1[[#This Row],[Product Category]]) -> Clothing | E89: =ROUND(Table1[[#This Row],[Sales Amount]],1) -> 1969.4 | F89: =Table1[[#This Row],[Quantity Sold]] -> 27 | G89: =Table1[[#This Row],[Discount (%)]] -> 11 | H89: =Table1[[#This Row],[Profit]] -> 1532.9 | I89: =Table24610[[#This Row],[profit]]/Table24610[[#This Row],[Sales Amount]] -> 0.77835889
A90: 745eb905 | B90: 45110 | C90: =PROPER(Table1[[#This Row],[Region]]) -> North | D90: =PROPER(Table1[[#This Row],[Product Category]]) -> Clothing | E90: =ROUND(Table1[[#This Row],[Sales Amount]],1) -> 2083 | F90: =Table1[[#This Row],[Quantity Sold]] -> 49 | G90: =Table1[[#This Row],[Discount (%)]] -> 11 | H90: =Table1[[#This Row],[Profit]] -> 105.26 | I90: =Table24610[[#This Row],[profit]]/Table24610[[#This Row],[Sales Amount]] -> 0.050532885
A91: b8fca939 | B91: 45111 | C91: =PROPER(Table1[[#This Row],[Region]]) -> South | D91: =PROPER(Table1[[#This Row],[Product Category]]) -> Electronics | E91: =ROUND(Table1[[#This Row],[Sales Amount]],1) -> 4752.5 | F91: =Table1[[#This Row],[Quantity Sold]] -> 36 | G91: =Table1[[#This Row],[Discount (%)]] -> 8 | H91: =Table1[[#This Row],[Profit]] -> 1903.35 | I91: =Table24610[[#This Row],[profit]]/Table24610[[#This Row],[Sales Amount]] -> 0.40049448
... A150: c41efe4c | B150: 45170 | C150: =PROPER(Table1[[#This Row],[Region]]) -> South | D150: =PROPER(Table1[[#This Row],[Product Category]]) -> Furniture | E150: =ROUND(Table1[[#This Row],[Sales Amount]],1) -> 1453.8 | F150: =Table1[[#This Row],[Quantity Sold]] -> 13 | G150: =Table1[[#This Row],[Discount (%)]] -> 16 | H150: =Table1[[#This Row],[Profit]] -> 385.22 | I150: =Table24610[[#This Row],[profit]]/Table24610[[#This Row],[Sales Amount]] -> 0.26497455
A151: 61831599 | B151: 45171 | C151: =PROPER(Table1[[#This Row],[Region]]) -> East | D151: =PROPER(Table1[[#This Row],[Product Category]]) -> Sports | E151: =ROUND(Table1[[#This Row],[Sales Amount]],1) -> 4889.5 | F151: =Table1[[#This Row],[Quantity Sold]] -> 1 | G151: =Table1[[#This Row],[Discount (%)]] -> 20 | H151: =Table1[[#This Row],[Profit]] -> 807.13 | I151: =Table24610[[#This Row],[profit]]/Table24610[[#This Row],[Sales Amount]] -> 0.16507414
A152: cf159d42 | B152: 45172 | C152: =PROPER(Table1[[#This Row],[Region]]) -> East | D152: =PROPER(Table1[[#This Row],[Product Category]]) -> Sports | E152: =ROUND(Table1[[#This Row],[Sales Amount]],1) -> 2548.9 | F152: =Table1[[#This Row],[Quantity Sold]] -> 3 | G152: =Table1[[#This Row],[Discount (%)]] -> 7 | H152: =Table1[[#This Row],[Profit]] -> 694.24 | I152: =Table24610[[#This Row],[profit]]/Table24610[[#This Row],[Sales Amount]] -> 0.27236847
A153: ffa6342d | B153: 45173 | C153: =PROPER(Table1[[#This Row],[Region]]) -> South | D153: =PROPER(Table1[[#This Row],[Product Category]]) -> Clothing | E153: =ROUND(Table1[[#This Row],[Sales Amount]],1) -> 3804.8 | F153: =Table1[[#This Row],[Quantity Sold]] -> 31 | G153: =Table1[[#This Row],[Discount (%)]] -> 47 | H153: =Table1[[#This Row],[Profit]] -> 185.46 | I153: =Table24610[[#This Row],[profit]]/Table24610[[#This Row],[Sales Amount]] -> 0.048743692
A154: 459360d4 | B154: 45174 | C154: =PROPER(Table1[[#This Row],[Region]]) -> East | D154: =PROPER(Table1[[#This Row],[Product Category]]) -> Groceries | E154: =ROUND(Table1[[#This Row],[Sales Amount]],1) -> 372.5 | F154: =Table1[[#This Row],[Quantity Sold]] -> 19 | G154: =Table1[[#This Row],[Discount (%)]] -> 13 | H154: =Table1[[#This Row],[Profit]] -> 232.82 | I154: =Table24610[[#This Row],[profit]]/Table24610[[#This Row],[Sales Amount]] -> 0.62502013
A155: fdf4755a | B155: 45175 | C155: =PROPER(Table1[[#This Row],[Region]]) -> North | D155: =PROPER(Table1[[#This Row],[Product Category]]) -> Electronics | E155: =ROUND(Table1[[#This Row],[Sales Amount]],1) -> 2573.6 | F155: =Table1[[#This Row],[Quantity Sold]] -> 48 | G155: =Table1[[#This Row],[Discount (%)]] -> 36 | H155: =Table1[[#This Row],[Profit]] -> 1707.54 | I155: =Table24610[[#This Row],[profit]]/Table24610[[#This Row],[Sales Amount]] -> 0.66348306
A156: 0a7d436c | B156: 45176 | C156: =PROPER(Table1[[#This Row],[Region]]) -> West | D156: =PROPER(Table1[[#This Row],[Product Category]]) -> Clothing | E156: =ROUND(Table1[[#This Row],[Sales Amount]],1) -> 1761.3 | F156: =Table1[[#This Row],[Quantity Sold]] -> 27 | G156: =Table1[[#This Row],[Discount (%)]] -> 12 | H156: =Table1[[#This Row],[Profit]] -> 492.03 | I156: =Table24610[[#This Row],[profit]]/Table24610[[#This Row],[Sales Amount]] -> 0.27935616
A157: 3c1ab674 | B157: 45177 | C157: =PROPER(Table1[[#This Row],[Region]]) -> East | D157: =PROPER(Table1[[#This Row],[Product Category]]) -> Groceries | E157: =ROUND(Table1[[#This Row],[Sales Amount]],1) -> 4113.4 | F157: =Table1[[#This Row],[Quantity Sold]] -> 32 | G157: =Table1[[#This Row],[Discount (%)]] -> 3 | H157: =Table1[[#This Row],[Profit]] -> 1726.09 | I157: =Table24610[[#This Row],[profit]]/Table24610[[#This Row],[Sales Amount]] -> 0.4196261
A158: 42b5d016 | B158: 45178 | C158: =PROPER(Table1[[#This Row],[Region]]) -> West | D158: =PROPER(Table1[[#This Row],[Product Category]]) -> Electronics | E158: =ROUND(Table1[[#This Row],[Sales Amount]],1) -> 202.2 | F158: =Table1[[#This Row],[Quantity Sold]] -> 6 | G158: =Table1[[#This Row],[Discount (%)]] -> 43 | H158: =Table1[[#This Row],[Profit]] -> 734.47 | I158: =Table24610[[#This Row],[profit]]/Table24610[[#This Row],[Sales Amount]] -> 3.6323937
A159: 2616d5b4 | B159: 45179 | C159: =PROPER(Table1[[#This Row],[Region]]) -> North | D159: =PROPER(Table1[[#This Row],[Product Category]]) -> Sports | E159: =ROUND(Table1[[#This Row],[Sales Amount]],1) -> 4347.2 | F159: =Table1[[#This Row],[Quantity Sold]] -> 20 | G159: =Table1[[#This Row],[Discount (%)]] -> 34 | H159: =Table1[[#This Row],[Profit]] -> 1392.45 | I159: =Table24610[[#This Row],[profit]]/Table24610[[#This Row],[Sales Amount]] -> 0.32030962
A160: 338c4722 | B160: 45180 | C160: =PROPER(Table1[[#This Row],[Region]]) -> West | D160: =PROPER(Table1[[#This Row],[Product Category]]) -> Clothing | E160: =ROUND(Table1[[#This Row],[Sales Amount]],1) -> 4992.8 | F160: =Table1[[#This Row],[Quantity Sold]] -> 2 | G160: =Table1[[#This Row],[Discount (%)]] -> 28 | H160: =Table1[[#This Row],[Profit]] -> 1468.94 | I160: =Table24610[[#This Row],[profit]]/Table24610[[#This Row],[Sales Amount]] -> 0.29421166
A161: 6b1e9797 | B161: 45181 | C161: =PROPER(Table1[[#This Row],[Region]]) -> East | D161: =PROPER(Table1[[#This Row],[Product Category]]) -> Sports | E161: =ROUND(Table1[[#This Row],[Sales Amount]],1) -> 1387.2 | F161: =Table1[[#This Row],[Quantity Sold]] -> 28 | G161: =Table1[[#This Row],[Discount (%)]] -> 9 | H161: =Table1[[#This Row],[Profit]] -> 381.96 | I161: =Table24610[[#This Row],[profit]]/Table24610[[#This Row],[Sales Amount]] -> 0.27534602
A162: 6e4fab78 | B162: 45182 | C162: =PROPER(Table1[[#This Row],[Region]]) -> North | D162: =PROPER(Table1[[#This Row],[Product Category]]) -> Clothing | E162: =ROUND(Table1[[#This Row],[Sales Amount]],1) -> 4642.9 | F162: =Table1[[#This Row],[Quantity Sold]] -> 35 | G162: =Table1[[#This Row],[Discount (%)]] -> 14 | H162: =Table1[[#This Row],[Profit]] -> 216.96 | I162: =Table24610[[#This Row],[profit]]/Table24610[[#This Row],[Sales Amount]] -> 0.046729415
A163: 8944bc68 | B163: 45183 | C163: =PROPER(Table1[[#This Row],[Region]]) -> East | D163: =PROPER(Table1[[#This Row],[Product Category]]) -> Electronics | E163: =ROUND(Table1[[#This Row],[Sales Amount]],1) -> 4879.9 | F163: =Table1[[#This Row],[Quantity Sold]] -> 37 | G163: =Table1[[#This Row],[Discount (%)]] -> 5 | H163: =Table1[[#This Row],[Profit]] -> 1424.1 | I163: =Table24610[[#This Row],[profit]]/Table24610[[#This Row],[Sales Amount]] -> 0.29182975
... A199: 1e18c00a | B199: 45219 | C199: =PROPER(Table1[[#This Row],[Region]]) -> North | D199: =PROPER(Table1[[#This Row],[Product Category]]) -> Clothing | E199: =ROUND(Table1[[#This Row],[Sales Amount]],1) -> 2925.3 | F199: =Table1[[#This Row],[Quantity Sold]] -> 24 | G199: =Table1[[#This Row],[Discount (%)]] -> 4 | H199: =Table1[[#This Row],[Profit]] -> 1753.87 | I199: =Table24610[[#This Row],[profit]]/Table24610[[#This Row],[Sales Amount]] -> 0.59955218
A200: 37431000 | B200: 45220 | C200: =PROPER(Table1[[#This Row],[Region]]) -> South | D200: =PROPER(Table1[[#This Row],[Product Category]]) -> Groceries | E200: =ROUND(Table1[[#This Row],[Sales Amount]],1) -> 2454.7 | F200: =Table1[[#This Row],[Quantity Sold]] -> 10 | G200: =Table1[[#This Row],[Discount (%)]] -> 28 | H200: =Table1[[#This Row],[Profit]] -> 47.54 | I200: =Table24610[[#This Row],[profit]]/Table24610[[#This Row],[Sales Amount]] -> 0.019366929
A201: af24551a | B201: 45221 | C201: =PROPER(Table1[[#This Row],[Region]]) -> North | D201: =PROPER(Table1[[#This Row],[Product Category]]) -> Groceries | E201: =ROUND(Table1[[#This Row],[Sales Amount]],1) -> 4662.5 | F201: =Table1[[#This Row],[Quantity Sold]] -> 13 | G201: =Table1[[#This Row],[Discount (%)]] -> 22 | H201: =Table1[[#This Row],[Profit]] -> 735.39 | I201: =Table24610[[#This Row],[profit]]/Table24610[[#This Row],[Sales Amount]] -> 0.1577244
A202: 6b389c40 | B202: 45222 | C202: =PROPER(Table1[[#This Row],[Region]]) -> West | D202: =PROPER(Table1[[#This Row],[Product Category]]) -> Clothing | E202: =ROUND(Table1[[#This Row],[Sales Amount]],1) -> 2943.3 | F202: =Table1[[#This Row],[Quantity Sold]] -> 45 | G202: =Table1[[#This Row],[Discount (%)]] -> 8 | H202: =Table1[[#This Row],[Profit]] -> 571.04 | I202: =Table24610[[#This Row],[profit]]/Table24610[[#This Row],[Sales Amount]] -> 0.19401352
A203: 7743bcd0 | B203: 45223 | C203: =PROPER(Table1[[#This Row],[Region]]) -> South | D203: =PROPER(Table1[[#This Row],[Product Category]]) -> Groceries | E203: =ROUND(Table1[[#This Row],[Sales Amount]],1) -> 2261.5 | F203: =Table1[[#This Row],[Quantity Sold]] -> 46 | G203: =Table1[[#This Row],[Discount (%)]] -> 39 | H203: =Table1[[#This Row],[Profit]] -> 373.45 | I203: =Table24610[[#This Row],[profit]]/Table24610[[#This Row],[Sales Amount]] -> 0.16513376
A204: 84d09672 | B204: 45224 | C204: =PROPER(Table1[[#This Row],[Region]]) -> North | D204: =PROPER(Table1[[#This Row],[Product Category]]) -> Sports | E204: =ROUND(Table1[[#This Row],[Sales Amount]],1) -> 2679.5 | F204: =Table1[[#This Row],[Quantity Sold]] -> 36 | G204: =Table1[[#This Row],[Discount (%)]] -> 6 | H204: =Table1[[#This Row],[Profit]] -> 1471 | I204: =Table24610[[#This Row],[profit]]/Table24610[[#This Row],[Sales Amount]] -> 0.54898302
A205: bd554f96 | B205: 45225 | C205: =PROPER(Table1[[#This Row],[Region]]) -> East | D205: =PROPER(Table1[[#This Row],[Product Category]]) -> Electronics | E205: =ROUND(Table1[[#This Row],[Sales Amount]],1) -> 1290.7 | F205: =Table1[[#This Row],[Quantity Sold]] -> 46 | G205: =Table1[[#This Row],[Discount (%)]] -> 8 | H205: =Table1[[#This Row],[Profit]] -> 147.39 | I205: =Table24610[[#This Row],[profit]]/Table24610[[#This Row],[Sales Amount]] -> 0.11419385
A206: dee8766b | B206: 45226 | C206: =PROPER(Table1[[#This Row],[Region]]) -> East | D206: =PROPER(Table1[[#This Row],[Product Category]]) -> Groceries | E206: =ROUND(Table1[[#This Row],[Sales Amount]],1) -> 211.3 | F206: =Table1[[#This Row],[Quantity Sold]] -> 45 | G206: =Table1[[#This Row],[Discount (%)]] -> 48 | H206: =Table1[[#This Row],[Profit]] -> 1844.45 | I206: =Table24610[[#This Row],[profit]]/Table24610[[#This Row],[Sales Amount]] -> 8.7290582
A207: 733628ca | B207: 45227 | C207: =PROPER(Table1[[#This Row],[Region]]) -> West | D207: =PROPER(Table1[[#This Row],[Product Category]]) -> Furniture | E207: =ROUND(Table1[[#This Row],[Sales Amount]],1) -> 3582.9 | F207: =Table1[[#This Row],[Quantity Sold]] -> 42 | G207: =Table1[[#This Row],[Discount (%)]] -> 48 | H207: =Table1[[#This Row],[Profit]] -> 1359.36 | I207: =Table24610[[#This Row],[profit]]/Table24610[[#This Row],[Sales Amount]] -> 0.37940216
A208: 7101a707 | B208: 45228 | C208: =PROPER(Table1[[#This Row],[Region]]) -> West | D208: =PROPER(Table1[[#This Row],[Product Category]]) -> Furniture | E208: =ROUND(Table1[[#This Row],[Sales Amount]],1) -> 419.9 | F208: =Table1[[#This Row],[Quantity Sold]] -> 12 | G208: =Table1[[#This Row],[Discount (%)]] -> 22 | H208: =Table1[[#This Row],[Profit]] -> 1047.8 | I208: =Table24610[[#This Row],[profit]]/Table24610[[#This Row],[Sales Amount]] -> 2.495356
A209: 7349ac4e | B209: 45229 | C209: =PROPER(Table1[[#This Row],[Region]]) -> East | D209: =PROPER(Table1[[#This Row],[Product Category]]) -> Sports | E209: =ROUND(Table1[[#This Row],[Sales Amount]],1) -> 4422.2 | F209: =Table1[[#This Row],[Quantity Sold]] -> 14 | G209: =Table1[[#This Row],[Discount (%)]] -> 33 | H209: =Table1[[#This Row],[Profit]] -> 237.47 | I209: =Table24610[[#This Row],[profit]]/Table24610[[#This Row],[Sales Amount]] -> 0.053699516
A210: fbe74fbe | B210: 45230 | C210: =PROPER(Table1[[#This Row],[Region]]) -> East | D210: =PROPER(Table1[[#This Row],[Product Category]]) -> Furniture | E210: =ROUND(Table1[[#This Row],[Sales Amount]],1) -> 3277.5 | F210: =Table1[[#This Row],[Quantity Sold]] -> 11 | G210: =Table1[[#This Row],[Discount (%)]] -> 2 | H210: =Table1[[#This Row],[Profit]] -> 379.92 | I210: =Table24610[[#This Row],[profit]]/Table24610[[#This Row],[Sales Amount]] -> 0.11591762
A211: 6bde908c | B211: 45231 | C211: =PROPER(Table1[[#This Row],[Region]]) -> North | D211: =PROPER(Table1[[#This Row],[Product Category]]) -> Clothing | E211: =ROUND(Table1[[#This Row],[Sales Amount]],1) -> 4264.4 | F211: =Table1[[#This Row],[Quantity Sold]] -> 31 | G211: =Table1[[#This Row],[Discount (%)]] -> 24 | H211: =Table1[[#This Row],[Profit]] -> 1179.93 | I211: =Table24610[[#This Row],[profit]]/Table24610[[#This Row],[Sales Amount]] -> 0.27669309
A212: 56a98641 | B212: 45232 | C212: =PROPER(Table1[[#This Row],[Region]]) -> South | D212: =PROPER(Table1[[#This Row],[Product Category]]) -> Furniture | E212: =ROUND(Table1[[#This Row],[Sales Amount]],1) -> 647.4 | F212: =Table1[[#This Row],[Quantity Sold]] -> 16 | G212: =Table1[[#This Row],[Discount (%)]] -> 34 | H212: =Table1[[#This Row],[Profit]] -> 1937.88 | I212: =Table24610[[#This Row],[profit]]/Table24610[[#This Row],[Sales Amount]] -> 2.9933272
... A216: 2ecc60c1 | B216: 45236 | C216: =PROPER(Table1[[#This Row],[Region]]) -> South | D216: =PROPER(Table1[[#This Row],[Product Category]]) -> Clothing | E216: =ROUND(Table1[[#This Row],[Sales Amount]],1) -> 4559.2 | F216: =Table1[[#This Row],[Quantity Sold]] -> 14 | G216: =Table1[[#This Row],[Discount (%)]] -> 29 | H216: =Table1[[#This Row],[Profit]] -> 1055.86 | I216: =Table24610[[#This Row],[profit]]/Table24610[[#This Row],[Sales Amount]] -> 0.23158888
A217: 60839616 | B217: 45237 | C217: =PROPER(Table1[[#This Row],[Region]]) -> South | D217: =PROPER(Table1[[#This Row],[Product Category]]) -> Sports | E217: =ROUND(Table1[[#This Row],[Sales Amount]],1) -> 1787.1 | F217: =Table1[[#This Row],[Quantity Sold]] -> 11 | G217: =Table1[[#This Row],[Discount (%)]] -> 19 | H217: =Table1[[#This Row],[Profit]] -> 40.81 | I217: =Table24610[[#This Row],[profit]]/Table24610[[#This Row],[Sales Amount]] -> 0.022835879
A218: a65dfe8b | B218: 45238 | C218: =PROPER(Table1[[#This Row],[Region]]) -> West | D218: =PROPER(Table1[[#This Row],[Product Category]]) -> Furniture | E218: =ROUND(Table1[[#This Row],[Sales Amount]],1) -> 901.7 | F218: =Table1[[#This Row],[Quantity Sold]] -> 7 | G218: =Table1[[#This Row],[Discount (%)]] -> 48 | H218: =Table1[[#This Row],[Profit]] -> 903.11 | I218: =Table24610[[#This Row],[profit]]/Table24610[[#This Row],[Sales Amount]] -> 1.0015637
A219: 850b0c26 | B219: 45239 | C219: =PROPER(Table1[[#This Row],[Region]]) -> North | D219: =PROPER(Table1[[#This Row],[Product Category]]) -> Electronics | E219: =ROUND(Table1[[#This Row],[Sales Amount]],1) -> 2934.7 | F219: =Table1[[#This Row],[Quantity Sold]] -> 20 | G219: =Table1[[#This Row],[Discount (%)]] -> 12 | H219: =Table1[[#This Row],[Profit]] -> 528.02 | I219: =Table24610[[#This Row],[profit]]/Table24610[[#This Row],[Sales Amount]] -> 0.17992299
A220: 21fd10ea | B220: 45240 | C220: =PROPER(Table1[[#This Row],[Region]]) -> West | D220: =PROPER(Table1[[#This Row],[Product Category]]) -> Groceries | E220: =ROUND(Table1[[#This Row],[Sales Amount]],1) -> 1058.6 | F220: =Table1[[#This Row],[Quantity Sold]] -> 6 | G220: =Table1[[#This Row],[Discount (%)]] -> 13 | H220: =Table1[[#This Row],[Profit]] -> 697.72 | I220: =Table24610[[#This Row],[profit]]/Table24610[[#This Row],[Sales Amount]] -> 0.65909692
A221: 8d90e130 | B221: 45241 | C221: =PROPER(Table1[[#This Row],[Region]]) -> East | D221: =PROPER(Table1[[#This Row],[Product Category]]) -> Furniture | E221: =ROUND(Table1[[#This Row],[Sales Amount]],1) -> 3988.4 | F221: =Table1[[#This Row],[Quantity Sold]] -> 36 | G221: =Table1[[#This Row],[Discount (%)]] -> 1 | H221: =Table1[[#This Row],[Profit]] -> 1637.88 | I221: =Table24610[[#This Row],[profit]]/Table24610[[#This Row],[Sales Amount]] -> 0.41066092
A222: 41aee1e8 | B222: 45242 | C222: =PROPER(Table1[[#This Row],[Region]]) -> South | D222: =PROPER(Table1[[#This Row],[Product Category]]) -> Sports | E222: =ROUND(Table1[[#This Row],[Sales Amount]],1) -> 2727.5 | F222: =Table1[[#This Row],[Quantity Sold]] -> 35 | G222: =Table1[[#This Row],[Discount (%)]] -> 1 | H222: =Table1[[#This Row],[Profit]] -> 1875.23 | I222: =Table24610[[#This Row],[profit]]/Table24610[[#This Row],[Sales Amount]] -> 0.68752704
A223: 2f562dc0 | B223: 45243 | C223: =PROPER(Table1[[#This Row],[Region]]) -> South | D223: =PROPER(Table1[[#This Row],[Product Category]]) -> Groceries | E223: =ROUND(Table1[[#This Row],[Sales Amount]],1) -> 1765.5 | F223: =Table1[[#This Row],[Quantity Sold]] -> 13 | G223: =Table1[[#This Row],[Discount (%)]] -> 24 | H223: =Table1[[#This Row],[Profit]] -> 1951.72 | I223: =Table24610[[#This Row],[profit]]/Table24610[[#This Row],[Sales Amount]] -> 1.1054772
A224: 1790f693 | B224: 45244 | C224: =PROPER(Table1[[#This Row],[Region]]) -> North | D224: =PROPER(Table1[[#This Row],[Product Category]]) -> Furniture | E224: =ROUND(Table1[[#This Row],[Sales Amount]],1) -> 4383.8 | F224: =Table1[[#This Row],[Quantity Sold]] -> 40 | G224: =Table1[[#This Row],[Discount (%)]] -> 21 | H224: =Table1[[#This Row],[Profit]] -> 1013.33 | I224: =Table24610[[#This Row],[profit]]/Table24610[[#This Row],[Sales Amount]] -> 0.23115334
A225: 1ad9d5e9 | B225: 45245 | C225: =PROPER(Table1[[#This Row],[Region]]) -> South | D225: =PROPER(Table1[[#This Row],[Product Category]]) -> Groceries | E225: =ROUND(Table1[[#This Row],[Sales Amount]],1) -> 4240.6 | F225: =Table1[[#This Row],[Quantity Sold]] -> 49 | G225: =Table1[[#This Row],[Discount (%)]] -> 14 | H225: =Table1[[#This Row],[Profit]] -> 1765.62 | I225: =Table24610[[#This Row],[profit]]/Table24610[[#This Row],[Sales Amount]] -> 0.41636089
A226: ae129571 | B226: 45246 | C226: =PROPER(Table1[[#This Row],[Region]]) -> South | D226: =PROPER(Table1[[#This Row],[Product Category]]) -> Furniture | E226: =ROUND(Table1[[#This Row],[Sales Amount]],1) -> 273.8 | F226: =Table1[[#This Row],[Quantity Sold]] -> 44 | G226: =Table1[[#This Row],[Discount (%)]] -> 29 | H226: =Table1[[#This Row],[Profit]] -> 821 | I226: =Table24610[[#This Row],[profit]]/Table24610[[#This Row],[Sales Amount]] -> 2.9985391
A227: 79a06bc6 | B227: 45247 | C227: =PROPER(Table1[[#This Row],[Region]]) -> East | D227: =PROPER(Table1[[#This Row],[Product Category]]) -> Sports | E227: =ROUND(Table1[[#This Row],[Sales Amount]],1) -> 152.5 | F227: =Table1[[#This Row],[Quantity Sold]] -> 10 | G227: =Table1[[#This Row],[Discount (%)]] -> 16 | H227: =Table1[[#This Row],[Profit]] -> 1958.8 | I227: =Table24610[[#This Row],[profit]]/Table24610[[#This Row],[Sales Amount]] -> 12.84459
A228: 65240ae3 | B228: 45248 | C228: =PROPER(Table1[[#This Row],[Region]]) -> West | D228: =PROPER(Table1[[#This Row],[Product Category]]) -> Groceries | E228: =ROUND(Table1[[#This Row],[Sales Amount]],1) -> 1408 | F228: =Table1[[#This Row],[Quantity Sold]] -> 26 | G228: =Table1[[#This Row],[Discount (%)]] -> 35 | H228: =Table1[[#This Row],[Profit]] -> 978.17 | I228: =Table24610[[#This Row],[profit]]/Table24610[[#This Row],[Sales Amount]] -> 0.69472301
A229: d4df366c | B229: 45249 | C229: =PROPER(Table1[[#This Row],[Region]]) -> West | D229: =PROPER(Table1[[#This Row],[Product Category]]) -> Furniture | E229: =ROUND(Table1[[#This Row],[Sales Amount]],1) -> 4083.3 | F229: =Table1[[#This Row],[Quantity Sold]] -> 22 | G229: =Table1[[#This Row],[Discount (%)]] -> 40 | H229: =Table1[[#This Row],[Profit]] -> 1003.31 | I229: =Table24610[[#This Row],[profit]]/Table24610[[#This Row],[Sales Amount]] -> 0.24571058
... A271: d344a2c7 | B271: 45291 | C271: =PROPER(Table1[[#This Row],[Region]]) -> East | D271: =PROPER(Table1[[#This Row],[Product Category]]) -> Furniture | E271: =ROUND(Table1[[#This Row],[Sales Amount]],1) -> 3012.9 | F271: =Table1[[#This Row],[Quantity Sold]] -> 16 | G271: =Table1[[#This Row],[Discount (%)]] -> 16 | H271: =Table1[[#This Row],[Profit]] -> 789.81 | I271: =Table24610[[#This Row],[profit]]/Table24610[[#This Row],[Sales Amount]] -> 0.26214279
A272: 6.7765e+71 | B272: 45292 | C272: =PROPER(Table1[[#This Row],[Region]]) -> North | D272: =PROPER(Table1[[#This Row],[Product Category]]) -> Clothing | E272: =ROUND(Table1[[#This Row],[Sales Amount]],1) -> 1877.4 | F272: =Table1[[#This Row],[Quantity Sold]] -> 40 | G272: =Table1[[#This Row],[Discount (%)]] -> 46 | H272: =Table1[[#This Row],[Profit]] -> 730.86 | I272: =Table24610[[#This Row],[profit]]/Table24610[[#This Row],[Sales Amount]] -> 0.3892937
A273: 3cccf911 | B273: 45293 | C273: =PROPER(Table1[[#This Row],[Region]]) -> West | D273: =PROPER(Table1[[#This Row],[Product Category]]) -> Electronics | E273: =ROUND(Table1[[#This Row],[Sales Amount]],1) -> 2634.2 | F273: =Table1[[#This Row],[Quantity Sold]] -> 19 | G273: =Table1[[#This Row],[Discount (%)]] -> 35 | H273: =Table1[[#This Row],[Profit]] -> 38.85 | I273: =Table24610[[#This Row],[profit]]/Table24610[[#This Row],[Sales Amount]] -> 0.014748311
...

Sheet sample dashboard
A1: Sales Dashboard
A3: Total Sales | D3: =SUM(Table246[Sales Amount]) -> 10103149
A5: Total Profit | D5: =SUM(Table246[profit]) -> 4028128.4
C8: Quantiy sold | D8: =SUM(Table246[Quantity Sold]) -> 102690
C9: profit | D9: =SUM(Table246[profit]) -> 4028128.4
C16: Category | D16: Sum of profit | K16: REGION | L16: Sum of Sales Amount
C17: Clothing | D17: 856347.49 | K17: East | L17: 2592526.4
C18: Electronics | D18: 803657.96 | K18: North | L18: 2536948.4
C19: Furniture | D19: 833209.71 | K19: South | L19: 2494414.8
C20: Groceries | D20: 739605.38 | K20: West | L20: 2479259.3
C21: Sports | D21: 795307.89 | K21: Grand Total | L21: 10103149
C22: Grand Total | D22: 4028128.4
C34: Category | D34: Sum of Sales Amount
C35: Clothing | D35: 2156010.8
C36: Electronics | D36: 2047839.5
C37: Furniture | D37: 2046524.5
C38: Groceries | D38: 1864229.2
C39: Sports | D39: 1988544.9
C40: Grand Total | D40: 10103149
